Workbook
Name Economic: Drop_down_coding!$E$44:$E$51
Name Feature: Drop_down_coding!$E$54:$E$61
Name Legal: Drop_down_coding!$N$44:$N$51
Name Market.Pulse: Drop_down_coding!$E$19:$E$28
Name Market_Pulse: Drop_down_coding!$B$33:$B$37
Name Marketing: Drop_down_coding!$H$54:$H$61
Name Partnership: Drop_down_coding!$K$54:$K$61
Name Players.Movement: Drop_down_coding!$H$19:$H$28
Name Players_Movement: Drop_down_coding!$E$33:$E$38
Name Political: Drop_down_coding!$B$44:$B$51
Name Product: Drop_down_coding!$B$54:$B$61
Name Slicer_category: #N/A
Name Slicer_signal_level: #N/A
Name Slicer_sub_topic_group: #N/A
Name Slicer_subcategory: #N/A
Name Slicer_topic_group: #N/A
Name Slicer_week: #N/A
Name Social: Drop_down_coding!$H$44:$H$51
Name Strategy: Drop_down_coding!$N$54:$N$61
Name Technology: Drop_down_coding!$K$44:$K$51
Name topic_group: Drop_down_coding!$B$19:$B$20

Sheet NGUYÊN TẮC
A1: NGUYÊN TẮC CHUNG
A2: Market Watch hướng tới target audience là Product/ Kinh doanh/ Marketing/ Growth/ CX - CEE nắm bắt được tình hình thị trường liên quan đến V-App theo 7 vertical chính: AI - Chat - E-commerce - Travel (khách sạn/ vui chơi giải trí) - Ride/ Food Delivery - E-wallet - Ticket (sự kiện, concert,...) - Nhận diện mô hình / xu hướng - Dự đoán (đón trước) hành động của đối thủ - Chuẩn bị chính sách - Thích nghi với công nghệ - Ra quyết định về Marketing / Tăng trưởng / Trải nghiệm khách hàng (CX)
A3: 2 streams chính - Market Pulse - Tín hiệu thị trường về chính sách, công nghệ, đối thủ adjacent, xu hướng - Players Movement - Hành động cụ thể của các players theo từng verticals tại Việt Nam
A4: Tracked players: | B4: MoMo; Zalo; ZaloPay; Grab; Traveloka; Shopee; TikTok Shop; WhatsApp; Telegram; WeChat; AliPay
A5: Adjacent players: | B5: GoTo; Gojek; Sea; Lazada; Tiki; Sendo; Be; Xanh SM; Green SM; ViettelPay; VNPAY; ShopeePay; Apple Pay; Google Pay; WeChat Pay; Ant; Stripe; PayPal; Uber; DoorDash; Bolt; Meta; Threads; Instagram; ByteDance; Anthropic; OpenAI; Google; Apple
A7: Danh sách sheet
A8: Sheet name | B8: Mục đích
A9: Soure_Crawl_Data | B9: Tổng hợp tất các source để crawl bài viết
A10: Scanning | B10: Nguyên tắc lọc bài viết - Round 1 dựa trên title/ short description
A11: Grading | B11: Nguyên tắc chấm điểm bài viết theo tiêu chí để lọc bài viết - Roudn 2 dựa trên nội dung bài viết
A12: Coding | B12: Nguyên tắc phân loại bài viết theo Topic/ Category/ Verticals
A13: Database | B13: Tổng hợp tất cả các bài viết chi tiết
A15: THAO TÁC CHÍNH
A16: Bước | B16: Deliverable | C16: Rule/ Reference sheet
A17: Bước 1 - Crawl data
A18: Truy cập link bài viết trong Source_Crawl_Data | B18: orginal_orginal_source | C18: Source_Crawl_Data
A19: Scan để lọc bài viết thỏa mãn (1) thời gian đăng bài thuộc thời gian tracking (1) tiêu đều/short description chứa keywords | B19: url | C19: Source_Crawl_Data: tracking week Scanning: keyword
A20: Tổng hợp lại trong Database thỏa mãn điều kiện | B20: excel
A22: Bước 2 - AI phân loại tin tức, viết title_normalized và summary
A23: Gửi danh sách url đã tổng hợp ở B1 cho AI | B23: Lọc URL có trùng nội dung Xóa URL từ các nguồn báo có độ uy tín thấp hơn/ hoặc ít nội dung hơn và giữa URL của nguồn báo có độ uy tín cao hơn/ hoặc đầy đủ nội dung hơn
A24: AI trả lại file excel đầy đủ các trường thông tin | B24: source_name | C24: fetch từ url
B25: URL | C25: fetch từ bài viết
B26: week | C26: theo craw_date
B27: publish_date | C27: fetch từ bài viết
B28: topic_group | C28: Coding B2
B29: sub_topic_group | C29: Coding B2
B30: category | C30: Coding B3
B31: subcategory | C31: Coding B4
B32: related _vertical | C32: Coding B5
B33: title_normalized | C33: Updating
B34: summary | C34: Updating
B35: start-date | C35: fetch từ bài viết: thời gian diễn ra chương trình, bắt đầu từ, hiệu lực từ, ra mắt từ
B36: end-date | C36: fetch từ bài viết: kết thúc vào, hết hiệu lực từ, đóng sản phẩm từ,
... B39: title_raw | C39: fetch từ bài viết
A41: Bước 3 - Quality control
A42: Input vào database | B42: Clean database
A43: Review về cách grading | B43: Clean database
A44: Review title_normalized và summary | B44: Clean database

Sheet Source_Crawl_Data
A1: week_start | B1: 46144
A2: week_end | B2: =B1+6 -> 46150 | C2: =WEEKNUM(B2,2) -> 19
A5: no | B5: topic_group | C5: source_name | D5: chuyên mục | E5: original_source_url | F5: source_url | G5: overview | H5: characteristics | I5: method | J5: note | K5: extract_source | L5: date_edit | M5: Column1 | N5: Column2 | O5: Column3
A6: 1 | B6: Market Purlse | C6: GenK | D6: AI | E6: https://genk.vn/ai.chn | F6: =_xlfn.TEXTJOIN("-",TRUE,K6&M6,N6,O6)&".chn" -> https://genk.vn/ai/2-5-2026.chn | G6: - Trang chuyên mục riêng để cập nhật về AI (ai.html) - Có thể filter để xem theo ngày | H6: Timestamp trong UI hiển thị published_date = bao nhiêu ngày trước | I6: - Quét theo timestamp hiển thị trên UI 1-8 ngày trước - Hoặc tự động gen URL bằng cách điều chỉnh trong URL sau /23-2-2026 theo từng ngày trong tuần tracking | J6: theo ngày | K6: https://genk.vn/ai/ | L6: =B1 -> 46144 | M6: =DAY(L6) -> 2 | N6: =MONTH(L6) -> 5 | O6: =YEAR(L6) -> 2026
A7: 2 | B7: Market Purlse | C7: GenK | D7: Tin ICT | E7: https://genk.vn/tin-ict.chn | F7: =_xlfn.TEXTJOIN("-",TRUE,K7&M7,N7,O7)&".chn" -> https://genk.vn/tin-ict/2-5-2026.chn | G7: - Trang chuyên mục riêng để cập nhật về tin ICT - Có thể filter để xem theo ngày | H7: Timestamp trong UI hiển thị published_date = bao nhiêu ngày trước | I7: - Quét theo timestamp hiển thị trên UI 1-8 ngày trước - Hoặc tự động gen URL bằng cách điều chỉnh trong URL sau /23-2-2026 theo từng ngày trong tuần tracking | J7: theo ngày | K7: https://genk.vn/tin-ict/ | L7: =B1 -> 46144 | M7: =DAY(L7) -> 2 | N7: =MONTH(L7) -> 5 | O7: =YEAR(L7) -> 2026
A8: 3 | B8: Market Purlse | C8: Báo tin tức | D8: Thị trường tiền tệ | E8: https://baotintuc.vn/thi-truong-tien-te-587ct128.htm | F8: =_xlfn.TEXTJOIN("-",TRUE,K8&M8,N8,O8)&".htm" -> https://baotintuc.vn/thi-truong-tien-te-587ct128/d2-5-2026.htm | G8: Trang chuyên mục riêng về thị trường tiền tệ | H8: Không có timestamp trên UI. Published_date có thể điều chỉnh tại timestamp trong URL với cấu trúc /d23-2-26 | I8: Gen URL bằng cách điều chỉnh slug /d23-2-26 theo từng ngày trong tuần tracking | J8: theo ngày | K8: https://baotintuc.vn/thi-truong-tien-te-587ct128/d | L8: =B1 -> 46144 | M8: =DAY(L8) -> 2 | N8: =MONTH(L8) -> 5 | O8: =YEAR(L8) -> 2026
A9: 4 | B9: Market Purlse | C9: VNEconomy | D9: Techconnect | E9: https://vneconomy.vn/techconnect/ | F9: =E9 -> https://vneconomy.vn/techconnect/ | G9: - Trang chuyên mục riêng về công nghệ - Tagging theo 3 chuyên mục con: Techtalk, Techlifstyle, Kính lúp công nghệ | H9: Timestap trong UI hiển thị published_date = hh:mm dd/mm/yyyy | I9: Quét theo timestamp hiển thị trên UI mãn thời gian tracking | J9: không filter
A10: 5 | B10: Market Purlse | C10: VNEconomy | D10: Techlifestyle | E10: https://vneconomy.vn/techconnect/tech-lifestyle.htm | F10: =E10 -> https://vneconomy.vn/techconnect/tech-lifestyle.htm | G10: Chuyên mục con chuyên chủ đề xoay quanh Techlifestyle | H10: Timestamp trong UI hiển thị published_date = hh:mm dd/mm/yyyy | I10: Quét theo timestamp hiển thị trên UI của trang chuyên mục thỏa mãn thời gian tracking | J10: không filter
A11: 6 | B11: Market Purlse | C11: VNEconomy | D11: Techtalk | E11: https://vneconomy.vn/techconnect/tech-talk.htm | F11: =E11 -> https://vneconomy.vn/techconnect/tech-talk.htm | G11: Chuyên mục con chuyên chủ đề xoay quanh TechTalk | H11: Timestamp trong UI hiển thị published_date = hh:mm dd/mm/yyyy | I11: Quét theo timestamp hiển thị trên UI của trang chuyên mục thỏa mãn thời gian tracking | J11: không filter
A12: 7 | B12: Market Purlse | C12: Dân Trí | D12: AI - Internet | E12: https://dantri.com.vn/cong-nghe/ai-internet/from/2026-02-23/to/2026-02-23.htm | F12: =K12&"from/"&N12&"/to/"&O12&".htm" -> https://dantri.com.vn/cong-nghe/ai-internet/from/2026-05-02/to/2026-05-08.htm | G12: - Trang chuyên mục riêng về AI - Cho phép filter theo ngày để lọc theo tuần | H12: Không có timestamp trên UI. Có thể điều chỉnh thời gian tracking trên URL tại /from/2026-02-23/to/2026-02-23 | I12: Gen URL qua query string trong URL /from/2026-02-23/to/2026-02-23 | J12: theo tuần | K12: https://dantri.com.vn/cong-nghe/ai-internet/ | L12: =B1 -> 46144 | M12: =L12+6 -> 46150 | N12: =TEXT(L12,"yyyy-mm-dd") -> 2026-05-02 | O12: =TEXT(M12,"yyyy-mm-dd") -> 2026-05-08
A13: 8 | B13: Market Purlse | C13: Dân Trí | D13: An ninh mạng | E13: https://dantri.com.vn/cong-nghe/an-ninh-mang.htm | F13: =K13&"from/"&N13&"/to/"&O13&".htm" -> https://dantri.com.vn/cong-nghe/an-ninh-mang/from/2026-05-02/to/2026-05-08.htm | G13: - Trang chuyên mục riêng về an ninh mạng - Cho phép filter theo ngày để lọc theo tuần | H13: Không có timestamp trên UI. Có thể điều chỉnh thời gian tracking trên URL tại /from/2026-02-23/to/2026-02-23 | I13: Gen URL qua query string trong URL /from/2026-02-23/to/2026-02-23 | J13: theo tuần | K13: https://dantri.com.vn/cong-nghe/an-ninh-mang/ | L13: =B1 -> 46144 | M13: =L13+6 -> 46150 | N13: =TEXT(L13,"yyyy-mm-dd") -> 2026-05-02 | O13: =TEXT(M13,"yyyy-mm-dd") -> 2026-05-08
A14: 9 | B14: Market Purlse | C14: VNExpress | D14: Khoa học công nghệ | E14: https://vnexpress.net/khoa-hoc-cong-nghe | F14: =K14&"fromdate/"&N14&"/todate/"&O14&"/allcate/1006219" -> https://vnexpress.net/category/day/cateid/1006219/fromdate/1777680000/todate/1778198400/allcate/1006219 | G14: - Trang chuyên mục riêng về khoa học công nghệ - Cho phép filter theo ngày để lọc theo tuần | H14: - Không có timestamp trên UI - Có thể điều chỉnh thời gian tracking trên URL tại /fromdate/1771804800/todate/1772323200/ - Timestamp trên URL hiển thị theo dạng Unix Timestamp | I14: Gen URL qua query string trong URL /fromdate/1771804800/todate/1772323200/ | J14: theo tuần | K14: https://vnexpress.net/category/day/cateid/1006219/ | L14: =B1 -> 46144 | M14: =L14+6 -> 46150 | N14: =(L14-DATE(1970,1,1))*86400 -> 1777680000 | O14: =(M14-DATE(1970,1,1))*86400 -> 1778198400
A15: 10 | B15: Market Purlse | C15: Bloomberg | D15: Consumer tech | E15: https://www.bloomberg.com/technology/consumer-tech | F15: =E15 -> https://www.bloomberg.com/technology/consumer-tech | G15: - Trang chuyên mục về những xu hướng công nghệ liên quan đến người dùng - AISAN edition | H15: Timestamp trong UI hiển thị published_date = Tháng Ngày, Năm | I15: - Quét theo timestamp hiển thị trên UI | J15: không filter
A16: 11 | B16: Market Purlse | C16: Tech in Asia | D16: Fintech | E16: https://www.techinasia.com/category/fintech | F16: =E16 -> https://www.techinasia.com/category/fintech | G16: - Trang chuyên mục về những xu hướng liên quan đến thị trường fintech | H16: Timestamp trong UI hiển thị published_date = Tháng Ngày, Năm | I16: - Quét theo timestamp hiển thị trên UI | J16: không filter
A17: 12 | B17: Market Purlse | C17: Tech Crunch | D17: Apps | E17: https://techcrunch.com/category/apps/ | F17: =E17 -> https://techcrunch.com/category/apps/ | G17: - Trang chuyên mục về những xu hướng liên quan đến App | H17: Timestamp trong UI hiển thị published_date = bao nhiêu ngày trước | I17: - Quét theo timestamp hiển thị trên UI 1-8 ngày trước | J17: không filter
A18: 13 | B18: Market Purlse | C18: Thư viện pháp luật | D18: Văn bản mới | E18: https://thuvienphapluat.vn/page/tim-van-ban.aspx?keyword=nhnn&area=0&type=0&status=0&lan=1&org=0&signer=0&match=True&sort=1&bdate=31/12/2025&edate=31/12/2025 | F18: =TEXT(K18&"&bdate="&N18&"&edate="&O18,0) -> https://thuvienphapluat.vn/page/tim-van-ban.aspx?keyword=nhnn&area=0&type=0&status=0&lan=1&org=0&signer=0&match=True&sort=1&bdate=02-05-2026&edate=08-05-2026 | G18: - Chuyên trang cập nhập các văn bản pháp luận mới - Cho phép filter theo khoảng thời gian ban hành, loại văn bản, cơ quan ban hành, keyword (lọc văn bản thuộc phạm trù nội dung mong muốn) | H18: - Không có timestamp trên UI - Điều chỉnh keyword tại keyword=nhnn - Có thể điều chỉnh thời gian tracking trên URL tại bdate=23-02-2026&edate=01-03-2026 | I18: - Gen URL qua query string trong URL bdate=23-02-2026&edate=01-03-2026 - Điều chỉnh query string để lọc từ khóa cần thiết keyword=nhnn | J18: theo tuần | K18: https://thuvienphapluat.vn/page/tim-van-ban.aspx?keyword=nhnn&area=0&type=0&status=0&lan=1&org=0&signer=0&match=True&sort=1 | L18: =B1 -> 46144 | M18: =L18+6 -> 46150 | N18: =TEXT(L18,"dd-mm-yyyy") -> 02-05-2026 | O18: =TEXT(M18,"dd-mm-yyyy") -> 08-05-2026
A19: 14 | B19: Market Purlse | C19: Luật Việt Nam | D19: Điểm tin chính sách | E19: https://luatvietnam.vn/ban-tin-luatvietnam/diem-tin-chinh-sach-moi-c559-article.html | F19: =E19 -> https://luatvietnam.vn/ban-tin-luatvietnam/diem-tin-chinh-sach-moi-c559-article.html | G19: - Chuyên trang tổng hợp chính sách mới hàng tháng bao gồm chính sách mới và danh sách văn bản có hiệu từng tháng - Hiển thị rõ ràng tháng trong UI - Trong trang danh sách văn bản có hiệu lực có ngày ban hành (BH), ngày hiệu lực (HL) đầy đủ và phân theo thể loại văn bản | H19: Có thông tin tháng ban hành trên UI | I19: - Tìm kiếm chính sách mới/danh sách văn bản theo tháng - Quét theo ngày hiệu lực (HL) và keyword liên quan để xem có chính sách nào mới sắp có hiệu lực trong tuần tiếp theo | J19: không filter
A20: 15 | B20: Market Purlse | C20: Luật Việt Nam | D20: Văn bản mới | E20: https://luatvietnam.vn/ban-tin-luatvietnam/diem-tin-van-ban-moi-c220-article.html | F20: =E20 -> https://luatvietnam.vn/ban-tin-luatvietnam/diem-tin-van-ban-moi-c220-article.html | G20: - Chuyên trang điểm tin văn bản mới hàng tuần theo từng số - Trong trang điểm tin được phân loại theo lĩnh vực | H20: Chỉ có thông tin số văn bản trên UI | I20: Tìm kiếm bản tin theo số văn bản mới nhất | J20: không filter
A21: 16 | B21: Players Movement | C21: ZaloPay website | D21: Tin tức | E21: https://zalopay.vn/tin-tuc | F21: =E21 -> https://zalopay.vn/tin-tuc
A22: 17 | B22: Players Movement | C22: ZaloPay website | D22: Khuyến mãi | E22: https://zalopay.vn/khuyen-mai | F22: =E22 -> https://zalopay.vn/khuyen-mai
A23: 18 | B23: Players Movement | C23: ZaloOA website | D23: Tin tức | E23: https://oa.zalo.me/home/resources/news | F23: =E23 -> https://oa.zalo.me/home/resources/news
A24: 19 | B24: Players Movement | C24: MoMo wesbite | D24: Tin tức | E24: https://www.momo.vn/tin-tuc | F24: =E24 -> https://www.momo.vn/tin-tuc
A25: 20 | B25: Players Movement | C25: WhatsApp website | D25: Blog | E25: https://blog.whatsapp.com/ | F25: =E25 -> https://blog.whatsapp.com/
A26: 21 | B26: Players Movement | C26: Telegram website | D26: Blog | E26: https://telegram.org/blog | F26: =E26 -> https://telegram.org/blog
A27: 22 | B27: Players Movement | C27: Shopee | D27: Blog | E27: https://banhang.shopee.vn/edu/category?sub_cat_id=1006 | F27: =E27 -> https://banhang.shopee.vn/edu/category?sub_cat_id=1006
A28: 23 | B28: Players Movement | C28: TiktokShop | D28: Blog | E28: https://seller-vn.tiktok.com/university/essay?knowledge_id=8858869405370113 | F28: =E28 -> https://seller-vn.tiktok.com/university/essay?knowledge_id=8858869405370113
A29: 24 | B29: Players Movement | C29: Grab Merchant | D29: Blog | E29: https://merchant.grab.com/vn-vn/blog | F29: =E29 -> https://merchant.grab.com/vn-vn/blog
A30: 25 | B30: Players Movement | C30: Grab Passenger | D30: Blog | E30: https://www.grab.com/vn/blog/ | F30: =E30 -> https://www.grab.com/vn/blog/
A31: 26 | B31: Market Purlse | C31: Techinasia | D31: Consumer tech | E31: https://www.techinasia.com/category/consumer-tech | F31: =E31 -> https://www.techinasia.com/category/consumer-tech
A32: 27 | B32: Market Purlse | C32: Techinasia | D32: E-commerce | E32: https://www.techinasia.com/category/e-commerce-social-commerce | F32: =E32 -> https://www.techinasia.com/category/e-commerce-social-commerce
A33: 28 | B33: Market Purlse | C33: SCMP | D33: Tech | E33: https://www.scmp.com/tech | F33: =E33 -> https://www.scmp.com/tech
A34: 29 | B34: Market Purlse | C34: VNExpress | D34: Kinh doanh | E34: https://vnexpress.net/kinh-doanh | F34: =K34&"fromdate/"&N34&"/todate/"&O34&"/allcate/1006219" -> https://vnexpress.net/category/day/cateid/1003159/fromdate/1777680000/todate/1778198400/allcate/1006219 | K34: https://vnexpress.net/category/day/cateid/1003159/ | L34: =B1 -> 46144 | M34: =L34+6 -> 46150 | N34: =(L34-DATE(1970,1,1))*86400 -> 1777680000 | O34: =(M34-DATE(1970,1,1))*86400 -> 1778198400
B37: Market Purlse | C37: Baotintuc | E37: https://baotintuc.vn/thi-truong-tien-te-587ct128.htm | F37: =_xlfn.TEXTJOIN("-",TRUE,K37&M37,N37,O37)&".htm" -> https://baotintuc.vn/thi-truong-tien-te-587ct128/d3-5-2026.htm | G37: Trang chuyên mục riêng về thị trường tiền tệ | H37: Không có timestamp trên UI. Published_date có thể điều chỉnh tại timestamp trong URL với cấu trúc /d23-2-26 | I37: - Tự động gen URL bằng cách điều chỉnh trong URL sau /d23-2-26 theo từng ngày trong tuần tracking - Quét và tổng hợp thông tin theo từng URL | K37: https://baotintuc.vn/thi-truong-tien-te-587ct128/d | L37: =B1+1 -> 46145 | M37: =DAY(L37) -> 3 | N37: =MONTH(L37) -> 5 | O37: =YEAR(L37) -> 2026
B38: Market Purlse | C38: Baotintuc | E38: https://baotintuc.vn/thi-truong-tien-te-587ct128.htm | F38: =_xlfn.TEXTJOIN("-",TRUE,K38&M38,N38,O38)&".htm" -> https://baotintuc.vn/thi-truong-tien-te-587ct128/d4-5-2026.htm | G38: Trang chuyên mục riêng về thị trường tiền tệ | H38: Không có timestamp trên UI. Published_date có thể điều chỉnh tại timestamp trong URL với cấu trúc /d23-2-26 | I38: - Tự động gen URL bằng cách điều chỉnh trong URL sau /d23-2-26 theo từng ngày trong tuần tracking - Quét và tổng hợp thông tin theo từng URL | K38: https://baotintuc.vn/thi-truong-tien-te-587ct128/d | L38: =L37+1 -> 46146 | M38: =DAY(L38) -> 4 | N38: =MONTH(L38) -> 5 | O38: =YEAR(L38) -> 2026
B39: Market Purlse | C39: Baotintuc | E39: https://baotintuc.vn/thi-truong-tien-te-587ct128.htm | F39: =_xlfn.TEXTJOIN("-",TRUE,K39&M39,N39,O39)&".htm" -> https://baotintuc.vn/thi-truong-tien-te-587ct128/d5-5-2026.htm | G39: Trang chuyên mục riêng về thị trường tiền tệ | H39: Không có timestamp trên UI. Published_date có thể điều chỉnh tại timestamp trong URL với cấu trúc /d23-2-26 | I39: - Tự động gen URL bằng cách điều chỉnh trong URL sau /d23-2-26 theo từng ngày trong tuần tracking - Quét và tổng hợp thông tin theo từng URL | K39: https://baotintuc.vn/thi-truong-tien-te-587ct128/d | L39: =L38+1 -> 46147 | M39: =DAY(L39) -> 5 | N39: =MONTH(L39) -> 5 | O39: =YEAR(L39) -> 2026
B40: Market Purlse | C40: Baotintuc | E40: https://baotintuc.vn/thi-truong-tien-te-587ct128.htm | F40: =_xlfn.TEXTJOIN("-",TRUE,K40&M40,N40,O40)&".htm" -> https://baotintuc.vn/thi-truong-tien-te-587ct128/d6-5-2026.htm | G40: Trang chuyên mục riêng về thị trường tiền tệ | H40: Không có timestamp trên UI. Published_date có thể điều chỉnh tại timestamp trong URL với cấu trúc /d23-2-26 | I40: - Tự động gen URL bằng cách điều chỉnh trong URL sau /d23-2-26 theo từng ngày trong tuần tracking - Quét và tổng hợp thông tin theo từng URL | K40: https://baotintuc.vn/thi-truong-tien-te-587ct128/d | L40: =L39+1 -> 46148 | M40: =DAY(L40) -> 6 | N40: =MONTH(L40) -> 5 | O40: =YEAR(L40) -> 2026
B41: Market Purlse | C41: Baotintuc | E41: https://baotintuc.vn/thi-truong-tien-te-587ct128.htm | F41: =_xlfn.TEXTJOIN("-",TRUE,K41&M41,N41,O41)&".htm" -> https://baotintuc.vn/thi-truong-tien-te-587ct128/d7-5-2026.htm | G41: Trang chuyên mục riêng về thị trường tiền tệ | H41: Không có timestamp trên UI. Published_date có thể điều chỉnh tại timestamp trong URL với cấu trúc /d23-2-26 | I41: - Tự động gen URL bằng cách điều chỉnh trong URL sau /d23-2-26 theo từng ngày trong tuần tracking - Quét và tổng hợp thông tin theo từng URL | K41: https://baotintuc.vn/thi-truong-tien-te-587ct128/d | L41: =L40+1 -> 46149 | M41: =DAY(L41) -> 7 | N41: =MONTH(L41) -> 5 | O41: =YEAR(L41) -> 2026
B42: Market Purlse | C42: Baotintuc | E42: https://baotintuc.vn/thi-truong-tien-te-587ct128.htm | F42: =_xlfn.TEXTJOIN("-",TRUE,K42&M42,N42,O42)&".htm" -> https://baotintuc.vn/thi-truong-tien-te-587ct128/d8-5-2026.htm | G42: Trang chuyên mục riêng về thị trường tiền tệ | H42: Không có timestamp trên UI. Published_date có thể điều chỉnh tại timestamp trong URL với cấu trúc /d23-2-26 | I42: - Tự động gen URL bằng cách điều chỉnh trong URL sau /d23-2-26 theo từng ngày trong tuần tracking - Quét và tổng hợp thông tin theo từng URL | K42: https://baotintuc.vn/thi-truong-tien-te-587ct128/d | L42: =L41+1 -> 46150 | M42: =DAY(L42) -> 8 | N42: =MONTH(L42) -> 5 | O42: =YEAR(L42) -> 2026
B43: Market Purlse | C43: GenK | E43: https://genk.vn/ai.chn | F43: =_xlfn.TEXTJOIN("-",TRUE,K43&M43,N43,O43)&".chn" -> https://genk.vn/ai/3-5-2026.chn | G43: - Trang chuyên mục riêng để cập nhật về AI (ai.html) - Có thể filter để xem theo ngày | H43: Timestamp trong UI hiển thị published_date = bao nhiêu ngày trước | I43: - Quét theo timestamp hiển thị trên UI 1-8 ngày trước - Hoặc tự động gen URL bằng cách điều chỉnh trong URL sau /23-2-2026 theo từng ngày trong tuần tracking | K43: https://genk.vn/ai/ | L43: =B1+1 -> 46145 | M43: =DAY(L43) -> 3 | N43: =MONTH(L43) -> 5 | O43: =YEAR(L43) -> 2026
B44: Market Purlse | C44: GenK | E44: https://genk.vn/ai.chn | F44: =_xlfn.TEXTJOIN("-",TRUE,K44&M44,N44,O44)&".chn" -> https://genk.vn/ai/4-5-2026.chn | K44: https://genk.vn/ai/ | L44: =L43+1 -> 46146 | M44: =DAY(L44) -> 4 | N44: =MONTH(L44) -> 5 | O44: =YEAR(L44) -> 2026
B45: Market Purlse | C45: GenK | E45: https://genk.vn/ai.chn | F45: =_xlfn.TEXTJOIN("-",TRUE,K45&M45,N45,O45)&".chn" -> https://genk.vn/ai/5-5-2026.chn | K45: https://genk.vn/ai/ | L45: =L44+1 -> 46147 | M45: =DAY(L45) -> 5 | N45: =MONTH(L45) -> 5 | O45: =YEAR(L45) -> 2026
B46: Market Purlse | C46: GenK | E46: https://genk.vn/ai.chn | F46: =_xlfn.TEXTJOIN("-",TRUE,K46&M46,N46,O46)&".chn" -> https://genk.vn/ai/6-5-2026.chn | K46: https://genk.vn/ai/ | L46: =L45+1 -> 46148 | M46: =DAY(L46) -> 6 | N46: =MONTH(L46) -> 5 | O46: =YEAR(L46) -> 2026
B47: Market Purlse | C47: GenK | E47: https://genk.vn/ai.chn | F47: =_xlfn.TEXTJOIN("-",TRUE,K47&M47,N47,O47)&".chn" -> https://genk.vn/ai/7-5-2026.chn | K47: https://genk.vn/ai/ | L47: =L46+1 -> 46149 | M47: =DAY(L47) -> 7 | N47: =MONTH(L47) -> 5 | O47: =YEAR(L47) -> 2026
B48: Market Purlse | C48: GenK | E48: https://genk.vn/ai.chn | F48: =_xlfn.TEXTJOIN("-",TRUE,K48&M48,N48,O48)&".chn" -> https://genk.vn/ai/8-5-2026.chn | K48: https://genk.vn/ai/ | L48: =L47+1 -> 46150 | M48: =DAY(L48) -> 8 | N48: =MONTH(L48) -> 5 | O48: =YEAR(L48) -> 2026
B49: Market Purlse | C49: GenK | E49: https://genk.vn/tin-ict.chn | F49: =_xlfn.TEXTJOIN("-",TRUE,K49&M49,N49,O49)&".chn" -> https://genk.vn/tin-ict/3-5-2026.chn | K49: https://genk.vn/tin-ict/ | L49: =B1+1 -> 46145 | M49: =DAY(L49) -> 3 | N49: =MONTH(L49) -> 5 | O49: =YEAR(L49) -> 2026
B50: Market Purlse | C50: GenK | E50: https://genk.vn/tin-ict.chn | F50: =_xlfn.TEXTJOIN("-",TRUE,K50&M50,N50,O50)&".chn" -> https://genk.vn/tin-ict/4-5-2026.chn | K50: https://genk.vn/tin-ict/ | L50: =L49+1 -> 46146 | M50: =DAY(L50) -> 4 | N50: =MONTH(L50) -> 5 | O50: =YEAR(L50) -> 2026
B51: Market Purlse | C51: GenK | E51: https://genk.vn/tin-ict.chn | F51: =_xlfn.TEXTJOIN("-",TRUE,K51&M51,N51,O51)&".chn" -> https://genk.vn/tin-ict/5-5-2026.chn | K51: https://genk.vn/tin-ict/ | L51: =L50+1 -> 46147 | M51: =DAY(L51) -> 5 | N51: =MONTH(L51) -> 5 | O51: =YEAR(L51) -> 2026
B52: Market Purlse | C52: GenK | E52: https://genk.vn/tin-ict.chn | F52: =_xlfn.TEXTJOIN("-",TRUE,K52&M52,N52,O52)&".chn" -> https://genk.vn/tin-ict/6-5-2026.chn | K52: https://genk.vn/tin-ict/ | L52: =L51+1 -> 46148 | M52: =DAY(L52) -> 6 | N52: =MONTH(L52) -> 5 | O52: =YEAR(L52) -> 2026
B53: Market Purlse | C53: GenK | E53: https://genk.vn/tin-ict.chn | F53: =_xlfn.TEXTJOIN("-",TRUE,K53&M53,N53,O53)&".chn" -> https://genk.vn/tin-ict/7-5-2026.chn | K53: https://genk.vn/tin-ict/ | L53: =L52+1 -> 46149 | M53: =DAY(L53) -> 7 | N53: =MONTH(L53) -> 5 | O53: =YEAR(L53) -> 2026
B54: Market Purlse | C54: GenK | E54: https://genk.vn/tin-ict.chn | F54: =_xlfn.TEXTJOIN("-",TRUE,K54&M54,N54,O54)&".chn" -> https://genk.vn/tin-ict/8-5-2026.chn | K54: https://genk.vn/tin-ict/ | L54: =L53+1 -> 46150 | M54: =DAY(L54) -> 8 | N54: =MONTH(L54) -> 5 | O54: =YEAR(L54) -> 2026

Sheet Source_Crawl_Data (2)
A1: week_start | B1: 46130
A2: week_end | B2: 46136 | C2: 17
A4: no | B4: priority | C4: source_name | D4: chuyên mục | E4: original_source_url
A5: 1 | B5: 0 | C5: Grab Merchant | D5: Blog | E5: https://merchant.grab.com/vn-vn/blog
A6: 2 | B6: 0 | C6: Grab Passenger | D6: Blog | E6: https://www.grab.com/vn/blog/
A7: 3 | B7: 0 | C7: Grab Passenger | D7: Inside Grab | E7: https://www.grab.com/inside-grab/
A8: 4 | B8: 0 | C8: MoMo wesbite | D8: Tin tức | E8: https://www.momo.vn/tin-tuc
A9: 5 | B9: 0 | C9: Shopee | D9: Blog | E9: https://banhang.shopee.vn/edu/category?sub_cat_id=1006
A10: 6 | B10: 0 | C10: Telegram website | D10: Blog | E10: https://telegram.org/blog
A11: 7 | B11: 0 | C11: TiktokShop | D11: Blog | E11: https://seller-vn.tiktok.com/university/essay?knowledge_id=8858869405370113
A12: 8 | B12: 0 | C12: WhatsApp website | D12: Blog | E12: https://blog.whatsapp.com/
A13: 9 | B13: 0 | C13: ZaloOA website | D13: Tin tức | E13: https://oa.zalo.me/home/resources/news
A14: 10 | B14: 0 | C14: ZaloPay website | D14: Tin tức | E14: https://zalopay.vn/tin-tuc
A15: 11 | B15: 0 | C15: ZaloPay website | D15: Khuyến mãi | E15: https://zalopay.vn/khuyen-mai
A16: 12 | B16: 1 | C16: Bloomberg | D16: Consumer tech | E16: https://www.bloomberg.com/technology/consumer-tech
... A38: 34 | B38: 3 | C38: The Information | D38: Tech | E38: https://www.theinformation.com/technology?view=recent

Sheet Scanning
A1: KEY WORDS SCAN TITLE/SHORT DESCRIPTION
A2: Title/ short description cần chưa ít nhất 1 keywords thuộc 1 trong 2 cluster dưới và không match với bất kỳ exclude pattern nào
A4: Cluster 1 - Players
A5: Tracked players: | B5: MoMo; Zalo; ZaloPay; Grab; Traveloka; Shopee; TikTok Shop; WhatsApp; Telegram; WeChat; AliPay
A6: Adjacent players: | B6: GoTo; Gojek; Sea; Lazada; Tiki; Sendo; Be; Xanh SM; Green SM; ViettelPay; VNPAY; ShopeePay; Apple Pay; Google Pay; WeChat Pay; Ant; Stripe; PayPal; Uber; DoorDash; Bolt; Meta; Threads; Instagram; ByteDance; Anthropic; OpenAI; Google; Apple
A8: Cluster 2 - Vertical keywords
A9: Vertical | B9: Keywords
A10: E-wallet | B10: ví điện tử; e-wallet; payment; thanh toán; QR; thanh toán quốc tế; QR quốc tế; BNPL; trả sau; kiều hối; remittance; fintech; mobile payment; tích hợp crypto; tích hợp tiền mã hóa;
A11: Ride / Delivery | B11: ride-hailing; gọi xe; food delivery; giao đồ ăn; mobility; last-mile; courier; gig economy
A12: TMĐT | B12: e-commerce; TMĐT; marketplace; seller fee; GMV; social commerce; D2C
A13: AI | B13: AI agent; LLM; GenAI; chatbot AI; voice AI; ChatGPT; Gemini; Claude; DeepSeek; AI assistant
A14: Chat | B14: messenger; chat app; social chat; super-app chat; mini app; mini program
A15: Travel | B15: OTA; booking; khách sạn; vé máy bay; tour; du lịch; travel; hotel
A16: Ticket | B16: nền tảng bán vé; hợp tác bán vé; Ticketbox; TicketMaster; Ticketgo; CTTicket
A18: EXCLUDE PATTERNS
A19: Pattern | B19: Ví dụ
A20: HR/layoff thuần, không gắn product | B20: "Startup AI sa thải 25% nhân sự để 'thuần AI'" → loại. (Có chữ AI nhưng không có lesson cho TA)
A21: AI research / paper academic | B21: "Mô hình mới đạt 92% benchmark MMLU", "DeepMind công bố paper về chain-of-thought"
A22: Dev tooling thuần B2D | B22: "OpenAI Agents SDK update", "LangChain v0.3 ra mắt", API/SDK release không có B2C app
A23: Stock price / earnings | B23: "Cổ phiếu Y tăng 5% sau Q2 earnings" Tin tài chính/đầu tư thuần túy (stocks, earnings không liên quan platform)
A24: Personality/celeb news không kèm action | B24: "CEO Z phát biểu tại hội nghị X" — trừ khi công bố roadmap
A25: Tech review consumer gadget | B25: "iPhone 18 review", "Samsung Galaxy S26 unboxing" — trừ khi feature ảnh hưởng super-app
A26: Entertainment/ Spports | B26: Tin giải trí/thể thao không có góc platform/tech

Sheet Grading
A1: Bảng tính điểm
A2: Score | B2: Level
A3: 4.21 – 5.00 | B3: 5 – Industry disruption
A4: 3.41 – 4.20 | B4: 4 – Strategic shift
A5: 2.51 – 3.40 | B5: 3 – Market signal
A6: 1.61 – 2.50 | B6: 2 – Minor signal
A7: ≤ 1.60 | B7: 1 – Noise
A9: Công thức tính
A10: signal_score = D1 × 0.6 + D2 × 0.4
A12: R1 - Impact | B12: 0.6 | C12: TA có thể action được gì từ tin này không? | E12: R2 - Relevance | F12: 0.4 | G12: Tin này có thuộc liên quan đến các vertical không
A13: Score | B13: 5 | C13: Regulation đã ban hành áp lên vertical TA đang vận hành Đối thủ trực tiếp launch product/pricing change đụng vertical TA Infrastructure/tool TA đang dùng có breaking change | E13: Score | F13: 5 | G13: Liên quan 2+ vertical core + content actionable
B14: 4 | C14: Đối thủ peer launch feature mới (chưa cùng vertical TA, có pattern apply) Tool / infrastructure mới TA có thể adopt (Stripe Link, Ant AMP...) Banking/fintech entry tạo lựa chọn mới Regulation precedent ở SEA/TQ — sắp đến VN | F14: 4 | G14: Liên quan đến 1+ vertical core + cotent actionable
B15: 3 | C15: AI tech advance không trực tiếp super-app (DeepSeek V4, GPT update) Corporate news ngành (CEO turnover, earnings có nuance) Routine player promo / feature minor (Grab promo tuần) Regulation distant / proposed-not-enacted | F15: 3 | G15: Adjacent: banking partner, regulatory precedent, 1 vertical thin / cross-vertical signal
B16: 2 | C16: Niche partnership cho use case nhỏ (kiều hối routine) Vertical mới chưa scale (insurance digital VN) Trend gián tiếp | F16: 2 | G16: Background signal — xu hướng gián tiếp, chưa có actor cụ thể
B17: 1 | C17: Dev tooling thuần (OpenAI Agents SDK) HR/AI hype không product implication B2G/B2D không tạo precedent | F17: 1 | G17: Hoàn toàn ngoài HST scope
A18: Modifiers cho D1 | B18: Market Pulse | C18: TQ event với precedent rõ cho VN → cộng 0.3–0.5 Quốc tế (US/EU) chỉ là "tin tham khảo" → giảm 0.3–0.5
B19: Market Pulse | C19: Tin đồn/leak chưa confirm → cap D1 ≤ 3 B2B/enterprise solutions (dù có AI) → cap D1 ≤ 2
B20: Players Movement | C20: Promo định kỳ → cap D1 ≤ 3.5 Product launch/Pricing/M&A/ Feature update → D1 ≥ 4

Sheet Updating-Scoring
A1: Impact score framework
A2: Score | B2: Range | C2: Min | D2: Meaning | E2: Mô tả
A3: 1 | B3: 1-1.8 | C3: 1 | D3: 1 - Noise | E3: Định nghĩa: Tin viral hoặc thú vị nhưng không có giá trị chiến lược. Không tạo ra insight gì về thị trường. Tiêu chí nhận diện: - Câu chuyện consumer/viral không phản ánh xu hướng thị trường - Sản phẩm/feature niche, không có relevance với VN/SEA - Nội dung hành chính/thủ tục không ảnh hưởng đến doanh nghiệp tư nhân - Ví dụ: MacBook warranty hack viral; Ứng dụng kết bạn tại Mỹ; HanoiWork OKR/KPI; United Airlines TSA wait times; Beehiiv mở rộng sang podcast
A4: 2 | B4: 1.81 - 3.0 | C4: 1.81 | D4: 2 - Minor signal | E4: Định nghĩa: Tin tức liên quan, cung cấp context hữu ích nhưng không tạo áp lực thay đổi gì. Người đọc có thể bỏ qua mà không ảnh hưởng đến quyết định. Tiêu chí nhận diện: - Product update, feature launch không thay đổi competitive landscape - Số liệu tham khảo từ thị trường khác, liên quan gián tiếp - Regulatory/legal ở giai đoạn dự thảo hoặc thị trường ngoài - Ví dụ: ElevenLabs AI music app; Rakuten rebrand DeepSeek V3; CMC đặt mục tiêu 20%; VNEID traffic reporting feature; Facebook Messenger web đóng
A5: 3 | B5: 3.01 - 3.4 | C5: 3.01 | D5: 3 - Market signal | E5: Định nghĩa: Tín hiệu đáng theo dõi, phản ánh xu hướng hoặc sự kiện có tác động đến thị trường nhưng chưa tạo ra hành động ngay. Người đọc cần biết để chuẩn bị, không cần phản ứng ngay. Tiêu chí nhận diện: - Dữ liệu thị trường quan trọng nhưng chưa là bước ngoặt - Nghiên cứu/báo cáo cung cấp insight mới về hành vi user hoặc ngành - Sự kiện tạo precedent quan trọng (pháp lý, kỹ thuật, chính sách) - Ví dụ: MIT AI confirmation bias research; 82% Indonesia AI shopping; DeepSeek outage 7h; Cuộc đua AI video sau Sora; Bitget crypto Visa APAC; Luật SHTT sửa đổi
A6: 4 | B6: 3.41-4.20 | C6: 3.41 | D6: 4 - Strategic shift | E6: Định nghĩa: Hành động cụ thể của một player có trọng lượng, buộc các đối thủ hoặc ngành phải phản ứng. Phân biệt với 5: tác động chưa thay đổi toàn bộ cấu trúc, nhưng đã rõ ràng và cụ thể. Tiêu chí nhận diện: - Một công ty lớn thực hiện bước đi chiến lược rõ ràng (launch, partnership cụ thể, M&A) - Quy định/pháp lý tạo ra hành động bắt buộc ngay (không phải định hướng xa) - Tác động cạnh tranh rõ ràng lên ít nhất một nhóm player - Ví dụ: Shinsegae hợp tác OpenAI AI Commerce; Meta thử nghiệm Instagram Plus; Google AI viết lại SERP title; AI tấn công 1M+ doanh nghiệp Việt; Bộ KH&CN xây danh mục AI rủi ro cao
A7: 5 | B7: 4.21 - 5.0 | C7: 4.21 | D7: 5 - Industry disruption | E7: Định nghĩa: Thay đổi căn bản cách một ngành/thị trường vận hành tại VN/SEA. Không phải tin lớn toàn cầu – phải là structural change ảnh hưởng trực tiếp đến người dùng hoặc doanh nghiệp trong nước. Tiêu chí nhận diện: - Cấu trúc thị trường VN/SEA thay đổi (ai thắng/thua thị phần, ngành mới hình thành) - Buộc nhiều player phải thay đổi mô hình kinh doanh đồng thời - Dữ liệu/số liệu thể hiện bước ngoặt thực sự (không chỉ tăng trưởng thông thường) - Ví dụ: TikTok Shop/Shopee chiếm 70%+ beauty TMĐT VN; TMĐT +34% nhưng toàn ngành không có lãi; Alibaba AI agents cho hàng triệu merchant; MobiFone vào hạ tầng thanh toán lõi
A9: Impact score decision table
B10: Criteria | C10: Low | D10: Medium | E10: High
B11: Market Scope | C11: company | D11: country | E11: global
B12: Industry Impact | C12: niche | D12: sector | E12: multi-sector
B13: Time Horizon | C13: short-term | D13: medium | E13: structural
B14: Strategic Relevance | C14: tactical | D14: strategic | E14: paradigm shift
A16: Impact scoring logic
B17: Impact score = average (market_scope, industry_impact, time_horizon, strategic_revlevance)
A19: Rule chọn tin bài phù hợp/ liên quan
A20: No | B20: Rule | C20: Weight | D20: Details | E20: Description
A21: Rule 1 | B21: Strategic relevance | C21: 0.4 | D21: - Fintech - payment/ wallet - Technology - AI/ chatbot - Platform ecosystem - Superapp - Regulation - Fintech / AI - Digital infrastructure - Indentiy/ Payment rails | E21: Mức độ tác động trực tiếp đến cách doanh nghiệp cạnh tranh trong thị trường VN/SEA. Không phải tầm quan trọng toàn cầu hay chính sách vĩ mô. - 5: Thay đổi cấu trúc cạnh tranh ngay lập tức tại VN/SEA (ai thắng/thua thị phần) - 4: Buộc player trong ngành phải điều chỉnh chiến lược - 3: Ảnh hưởng đến 1-2 mảng kinh doanh cụ thể - 2: Tín hiệu chiến lược nhưng chưa rõ tác động - 1: Không liên quan đến VN/SEA market
A22: Rule 2 | B22: Market impact | C22: 0.25 | D22: - Ảnh hưởng đến ngành - Ảnh hưởng đến nhiều công ty - Ảnh hưởng đến pháp lý - Ảnh hưởng đến hạ tầng nền tảng | E22: Quy mô người dùng/merchant/doanh nghiệp thực sự bị ảnh hưởng. Tính theo breadth (bao nhiêu người) × depth (ảnh hưởng sâu đến đâu). - 5: Ảnh hưởng toàn bộ thị trường (triệu users hoặc toàn ngành) - 4: Ảnh hưởng phân khúc lớn hoặc nhiều ngành - 3: Ảnh hưởng một nhóm rõ ràng (e.g. merchant, fintech startup) - 2: Ảnh hưởng hẹp hoặc gián tiếp - 1: Tác động không đáng kể
A23: Rule 3 | B23: Competitive intelligence | C23: 0.2 | D23: - Momo - Zalopay - BigTech | E23: Mức độ thay đổi thế cạnh tranh giữa các player, bao gồm cả competitive threat với doanh nghiệp trong nước. Tính theo: ai được lợi, ai bị đe dọa. - 5: Một player giành hoặc mất lợi thế cạnh tranh lớn ngay lập tức - 4: Tạo áp lực cạnh tranh rõ ràng lên các đối thủ hiện tại - 3: Mở ra hoặc đóng cửa một mảng cạnh tranh - 2: Tín hiệu cạnh tranh nhưng chưa có hành động cụ thể - 1: Không ảnh hưởng đến landscape cạnh tranh
A24: Rule 4 | B24: Technology inflection | C24: 0.15 | D24: - AI infrastructure - AI superapp - AI productization | E24: Mức độ công nghệ kích hoạt hành vi mới hoặc làm lỗi thời cách làm cũ. Không chỉ là innovation thuần kỹ thuật — behavioral shift, platform shift, và infrastructure shift đều tính. - 5: Tạo ra category mới hoặc làm lỗi thời một cách làm cũ hoàn toàn - 4: Shift rõ ràng trong cách user/business tương tác với technology - 3: Nâng cấp đáng kể khả năng hiện tại - 2: Cải tiến incremental, không thay đổi cơ bản - 1: Không có tech inflection
A26: Phân tích logic lọc bài của bạn
A28: 1. Tiêu chí nguồn (Source tier)
A30: Tier | B30: Nguồn | C30: Vai trò
A31: Domestic tech | B31: GenK, VNExpress, Dân Trí, VNEconomy TechConnect | C31: Thị trường VN
A32: Regulatory | B32: Luật Việt Nam | C32: Compliance/chính sách
A33: Regional | B33: TechInAsia | C33: SEA context
A34: Global | B34: TechCrunch, Bloomberg | C34: Xu hướng quốc tế
A36: → Logic: Bao phủ đa tầng — VN nội địa + SEA + Global, không lọc theo nguồn mà lọc theo nội dung.
A40: 2. Tiêu chí chủ đề (Topic relevance)
A42: Nhìn vào các bài được qualified, có thể thấy 5 nhóm chủ đề được chấp nhận:
A44: Nhóm | B44: Ví dụ trong list | C44: Liên quan super-app
A45: AI tools & platform | B45: OpenClaw, ChatGPT, Gemini, OpenAI superapp | C45: V-AI, cạnh tranh assistant
A46: Mobile/app ecosystem | B46: iOS 27, Apple Dev metrics, WhatsApp AI | C46: App development context
A47: Payments & fintech | B47: TT30/NHNN, FOMO Pay AI soundbox, Indonesia QR | C47: VPoint, thanh toán
A48: Platform & e-commerce | B48: Meta shopping AI, TikTok ads, Shopee/TikTok couriers | C48: Ecosystem cạnh tranh
A49: Vietnam regulations | B49: Smartphone safety, AI governance law, TT18 hộ KD | C49: Compliance
A52: 3. Tiêu chí loại trừ (Disqualified)
A54: Các bài không có trong list của bạn thường rơi vào:
A56: Tin tài chính/đầu tư thuần túy (stocks, earnings không liên quan platform)
A57: Tin giải trí/thể thao không có góc platform/tech
A58: Tin sản phẩm consumer hardware không liên quan ecosystem
A62: 4. Signal grading logic (suy luận)
A64: Level | B64: Label | C64: Tiêu chí (suy luận)
A65: 5 | B65: Industry disruption | C65: Thay đổi căn bản cách người dùng/thị trường hoạt động — đe dọa hoặc cơ hội lớn cho super-app
A66: 4 | B66: Strategic shift | C66: Đối thủ/platform lớn thay đổi chiến lược có thể ảnh hưởng đến positioning
A67: 3 | B67: Market signal | C67: Xu hướng thị trường đáng theo dõi, chưa rõ impact
A68: 2 | B68: Minor signal | C68: Thông tin nền, cập nhật nhỏ, liên quan gián tiếp
A69: 1 | B69: Noise | C69: Lọt qua vì nguồn qualified nhưng nội dung không liên quan
A71: → Hai bài level 1 (eSports Nations Cup, Robinhood buyback) nhiều khả năng là false positive — lọt qua vì nguồn/keyword nhưng không có giá trị thực cho Market Pulse.

Sheet Coding
A1: Bước 1: Lựa chọn source | K1: Strategy | L1: Product | M1: Feature | N1: Partnerhsip | O1: User activation | P1: User engagement | Q1: User acquisition | R1: Transaction growth
A2: Source
A3: code | B3: source_name
A4: 1 | B4: GenK
A5: 2 | B5: Báo tin tức
A6: 3 | B6: VNEconomy
A7: 4 | B7: Dân Trí
A8: 5 | B8: VNExpress
A9: 6 | B9: Thư viện pháp luật
A10: 7 | B10: Luật Việt Nam
A11: 8 | B11: ZaloPay website
A12: 9 | B12: ZaloPay fanpage
A13: 10 | B13: MoMo wesbite
A14: 11 | B14: MoMo fanpage
A16: Nguyên tắc phân loại Bước 2 - Bài viết là hành động chủ động của 1 players thuộc list bên dưới và hiệu lực/ được áp dụng tại Việt Nam: Players Movement - Bài viết còn lại (tin thị trường, regulation, peer global, players): Market Pulse - Sub_topic_group trong Market Pulse là phạm vi của sự kiện trong bài viết xảy ra - Sub_topic_group trong Players Movement tách riêng Zalo, ZaloPay: + Action/Event liên quan thanh toán, payment, QR, ví điện tử, kiều hối, BNPL → ZaloPay + Action/Event liên quan chat, mini app, social, OA, AI assistant trong Zalo → Zalo
A17: Bước 2: Phân loại theo topic_group
A18: Topic Group
A19: no_1 | B19: topic_group | C19: no_2 | D19: sub_topic_group | E19: no_final | F19: topic_aggregrate
A20: 1 | B20: Market Pulse | C20: =COUNTIF($B$20:B20,B20) -> 1 | D20: Quốc tế | E20: =_xlfn.TEXTJOIN(".",TRUE,A20,C20) -> 1.1 | F20: =_xlfn.TEXTJOIN(" | ",TRUE,B20,D20) -> Market Pulse | Quốc tế
A21: 1 | B21: Market Pulse | C21: =COUNTIF($B$20:B21,B21) -> 2 | D21: Trung quốc | E21: =_xlfn.TEXTJOIN(".",TRUE,A21,C21) -> 1.2 | F21: =_xlfn.TEXTJOIN(" | ",TRUE,B21,D21) -> Market Pulse | Trung quốc
A22: 1 | B22: Market Pulse | C22: =COUNTIF($B$20:B22,B22) -> 3 | D22: SEA | E22: =_xlfn.TEXTJOIN(".",TRUE,A22,C22) -> 1.3 | F22: =_xlfn.TEXTJOIN(" | ",TRUE,B22,D22) -> Market Pulse | SEA
A23: 1 | B23: Market Pulse | C23: =COUNTIF($B$20:B23,B23) -> 4 | D23: Trong nước | E23: =_xlfn.TEXTJOIN(".",TRUE,A23,C23) -> 1.4 | F23: =_xlfn.TEXTJOIN(" | ",TRUE,B23,D23) -> Market Pulse | Trong nước
A24: 2 | B24: Players Movement | C24: =COUNTIF($B$20:B24,B24) -> 1 | D24: MoMo | E24: =_xlfn.TEXTJOIN(".",TRUE,A24,C24) -> 2.1 | F24: =_xlfn.TEXTJOIN(" | ",TRUE,B24,D24) -> Players Movement | MoMo
A25: 2 | B25: Players Movement | C25: =COUNTIF($B$20:B25,B25) -> 2 | D25: Zalo | E25: =_xlfn.TEXTJOIN(".",TRUE,A25,C25) -> 2.2 | F25: =_xlfn.TEXTJOIN(" | ",TRUE,B25,D25) -> Players Movement | Zalo
A26: 2 | B26: Players Movement | C26: =COUNTIF($B$20:B26,B26) -> 3 | D26: Zalopay | E26: =_xlfn.TEXTJOIN(".",TRUE,A26,C26) -> 2.3 | F26: =_xlfn.TEXTJOIN(" | ",TRUE,B26,D26) -> Players Movement | Zalopay
A27: 2 | B27: Players Movement | C27: =COUNTIF($B$20:B27,B27) -> 4 | D27: Traveloka | E27: =_xlfn.TEXTJOIN(".",TRUE,A27,C27) -> 2.4 | F27: =_xlfn.TEXTJOIN(" | ",TRUE,B27,D27) -> Players Movement | Traveloka
A28: 2 | B28: Players Movement | C28: =COUNTIF($B$20:B28,B28) -> 5 | D28: WhatsApp | E28: =_xlfn.TEXTJOIN(".",TRUE,A28,C28) -> 2.5 | F28: =_xlfn.TEXTJOIN(" | ",TRUE,B28,D28) -> Players Movement | WhatsApp
A29: 2 | B29: Players Movement | C29: =COUNTIF($B$20:B29,B29) -> 6 | D29: Telegram | E29: =_xlfn.TEXTJOIN(".",TRUE,A29,C29) -> 2.6 | F29: =_xlfn.TEXTJOIN(" | ",TRUE,B29,D29) -> Players Movement | Telegram
A30: 2 | B30: Players Movement | C30: =COUNTIF($B$20:B30,B30) -> 7 | D30: Shopee | E30: =_xlfn.TEXTJOIN(".",TRUE,A30,C30) -> 2.7 | F30: =_xlfn.TEXTJOIN(" | ",TRUE,B30,D30) -> Players Movement | Shopee
A31: 2 | B31: Players Movement | C31: =COUNTIF($B$20:B31,B31) -> 8 | D31: TiktokShop | E31: =_xlfn.TEXTJOIN(".",TRUE,A31,C31) -> 2.8 | F31: =_xlfn.TEXTJOIN(" | ",TRUE,B31,D31) -> Players Movement | TiktokShop
A32: 2 | B32: Players Movement | C32: =COUNTIF($B$20:B32,B32) -> 9 | D32: Grab | E32: =_xlfn.TEXTJOIN(".",TRUE,A32,C32) -> 2.9 | F32: =_xlfn.TEXTJOIN(" | ",TRUE,B32,D32) -> Players Movement | Grab
A34: Nguyên tắc phân loại Bước 3 - Phân biệt Product vs Feature: Product là "1 sản phẩm mới có thể đứng độc lập" (Ví Trả Sau, Gói Thành Viên). Feature là "thêm chức năng trong sản phẩm có sẵn" (chuyển khoản nhanh, OTP mới, UX redesign) - Phân biệt Marketing vs Strategy: Marketing là campaign có thời hạn (voucher, mã giảm, livestream tuần). Strategy là tuyên bố/lộ trình dài hạn (mở rộng quốc gia, mua lại startup, AI roadmap)
A35: Bước 3: Phân loại content theo category_group
A36: Category Group
A37: no_1 | B37: topic_group | C37: no_3 | D37: category_group | E37: definition
A38: 1 | B38: Market Pulse | C38: =COUNTIF($B$38:B38,B38) -> 1 | D38: Political | E38: Chính sách, sắc lệnh, chiến lược quốc gia, geopolitics
A39: 1 | B39: Market Pulse | C39: =COUNTIF($B$38:B39,B39) -> 2 | D39: Economic | E39: Funding, M&A, mở rộng thị trường, đổi mô hình kinh doanh, sáng kiến chính phủ về kinh tế
A40: 1 | B40: Market Pulse | C40: =COUNTIF($B$38:B40,B40) -> 3 | D40: Social | E40: Hành vi người dùng, thói quen thanh toán số, chấp nhận AI,…
A41: 1 | B41: Market Pulse | C41: =COUNTIF($B$38:B41,B41) -> 4 | D41: Technology | E41: AI, blockchain, open banking, cloud, cybersecurity, platform policy
A42: 1 | B42: Market Pulse | C42: =COUNTIF($B$38:B42,B42) -> 5 | D42: Legal | E42: Luật, Thông tư, Nghị định, Quyết định
A43: 2 | B43: Players Movement | C43: =COUNTIF($B$38:B43,B43) -> 1 | D43: Product | E43: Ra mắt, sửa đổi, phát hành, thử nghiệm, đóng 1 sản phẩm hoặc đổi pricing/T&C
A44: 2 | B44: Players Movement | C44: =COUNTIF($B$38:B44,B44) -> 2 | D44: Feature | E44: Cải tiến, cập nhật, bổ sung, hủy bỏ tính năng/bảo mật/ quyền riêng tư
A45: 2 | B45: Players Movement | C45: =COUNTIF($B$38:B45,B45) -> 3 | D45: Marketing | E45: Liên quan đến các chương trình khuyến mãi, chiến dịch truyền thông về sản phẩm/ dịch vụ/ theo sự kiện
A46: 2 | B46: Players Movement | C46: =COUNTIF($B$38:B46,B46) -> 4 | D46: Partnership | E46: Hợp tác với bên ngoài (bank, merchant, telco, tech provider, transport)
A47: 2 | B47: Players Movement | C47: =COUNTIF($B$38:B47,B47) -> 5 | D47: CSR/ Community | E47: Hoạt động vì cộng đồng, Gây quỹ, Marathon
A48: 2 | B48: Players Movement | C48: =COUNTIF($B$38:B48,B48) -> 6 | D48: Strategy | E48: Mở rộng thị trường, hệ sinh thái, đầu tư công ty, mua startup, lộ trình AI
A50: Bước 4: Phân loại content chi tiết hơn theo sub_category_group
A51: Sub Category group
A52: no_3 | B52: category_group | C52: no_4 | D52: sub_category_group | E52: no_final | F52: topic_aggregrate
A53: =_xlfn.XLOOKUP(B53,$D$38:$D$48,$C$38:$C$48) -> 1 | B53: Political | C53: =COUNTIF($B$53:B53,B53) -> 1 | D53: New poilicy | E53: =_xlfn.TEXTJOIN(".",TRUE,A53,C53) -> 1.1 | F53: =_xlfn.TEXTJOIN(" | ",TRUE,B53,D53) -> Political | New poilicy
A54: =_xlfn.XLOOKUP(B54,$D$38:$D$48,$C$38:$C$48) -> 1 | B54: Political | C54: =COUNTIF($B$53:B54,B54) -> 2 | D54: Technology policy | E54: =_xlfn.TEXTJOIN(".",TRUE,A54,C54) -> 1.2 | F54: =_xlfn.TEXTJOIN(" | ",TRUE,B54,D54) -> Political | Technology policy
A55: =_xlfn.XLOOKUP(B55,$D$38:$D$48,$C$38:$C$48) -> 1 | B55: Political | C55: =COUNTIF($B$53:B55,B55) -> 3 | D55: Geopolitical tension | E55: =_xlfn.TEXTJOIN(".",TRUE,A55,C55) -> 1.3 | F55: =_xlfn.TEXTJOIN(" | ",TRUE,B55,D55) -> Political | Geopolitical tension
A56: =_xlfn.XLOOKUP(B56,$D$38:$D$48,$C$38:$C$48) -> 1 | B56: Political | C56: =COUNTIF($B$53:B56,B56) -> 4 | D56: National digital strategy | E56: =_xlfn.TEXTJOIN(".",TRUE,A56,C56) -> 1.4 | F56: =_xlfn.TEXTJOIN(" | ",TRUE,B56,D56) -> Political | National digital strategy
A57: =_xlfn.XLOOKUP(B57,$D$38:$D$48,$C$38:$C$48) -> 1 | B57: Political | C57: =COUNTIF($B$53:B57,B57) -> 5 | D57: Others | E57: =_xlfn.TEXTJOIN(".",TRUE,A57,C57) -> 1.5 | F57: =_xlfn.TEXTJOIN(" | ",TRUE,B57,D57) -> Political | Others
A58: =_xlfn.XLOOKUP(B58,$D$38:$D$48,$C$38:$C$48) -> 2 | B58: Economic | C58: =COUNTIF($B$53:B58,B58) -> 1 | D58: Funding/ investment | E58: =_xlfn.TEXTJOIN(".",TRUE,A58,C58) -> 2.1 | F58: =_xlfn.TEXTJOIN(" | ",TRUE,B58,D58) -> Economic | Funding/ investment
A59: =_xlfn.XLOOKUP(B59,$D$38:$D$48,$C$38:$C$48) -> 2 | B59: Economic | C59: =COUNTIF($B$53:B59,B59) -> 2 | D59: M&A activity | E59: =_xlfn.TEXTJOIN(".",TRUE,A59,C59) -> 2.2 | F59: =_xlfn.TEXTJOIN(" | ",TRUE,B59,D59) -> Economic | M&A activity
A60: =_xlfn.XLOOKUP(B60,$D$38:$D$48,$C$38:$C$48) -> 2 | B60: Economic | C60: =COUNTIF($B$53:B60,B60) -> 3 | D60: Market growth/market size | E60: =_xlfn.TEXTJOIN(".",TRUE,A60,C60) -> 2.3 | F60: =_xlfn.TEXTJOIN(" | ",TRUE,B60,D60) -> Economic | Market growth/market size
A61: =_xlfn.XLOOKUP(B61,$D$38:$D$48,$C$38:$C$48) -> 2 | B61: Economic | C61: =COUNTIF($B$53:B61,B61) -> 4 | D61: Business model change | E61: =_xlfn.TEXTJOIN(".",TRUE,A61,C61) -> 2.4 | F61: =_xlfn.TEXTJOIN(" | ",TRUE,B61,D61) -> Economic | Business model change
A62: =_xlfn.XLOOKUP(B62,$D$38:$D$48,$C$38:$C$48) -> 2 | B62: Economic | C62: =COUNTIF($B$53:B62,B62) -> 5 | D62: Government initiative | E62: =_xlfn.TEXTJOIN(".",TRUE,A62,C62) -> 2.5 | F62: =_xlfn.TEXTJOIN(" | ",TRUE,B62,D62) -> Economic | Government initiative
A63: =_xlfn.XLOOKUP(B63,$D$38:$D$48,$C$38:$C$48) -> 3 | B63: Social | C63: =COUNTIF($B$53:B63,B63) -> 1 | D63: Consumer behavior | E63: =_xlfn.TEXTJOIN(".",TRUE,A63,C63) -> 3.1 | F63: =_xlfn.TEXTJOIN(" | ",TRUE,B63,D63) -> Social | Consumer behavior
A64: =_xlfn.XLOOKUP(B64,$D$38:$D$48,$C$38:$C$48) -> 3 | B64: Social | C64: =COUNTIF($B$53:B64,B64) -> 2 | D64: Digital adoption | E64: =_xlfn.TEXTJOIN(".",TRUE,A64,C64) -> 3.2 | F64: =_xlfn.TEXTJOIN(" | ",TRUE,B64,D64) -> Social | Digital adoption
... A110: =_xlfn.XLOOKUP(B110,$D$38:$D$48,$C$38:$C$48) -> 6 | B110: Strategy | C110: =COUNTIF($B$53:B110,B110) -> 5 | D110: Platform / AI strategy | E110: =_xlfn.TEXTJOIN(".",TRUE,A110,C110) -> 6.5 | F110: =_xlfn.TEXTJOIN(" | ",TRUE,B110,D110) -> Strategy | Platform / AI strategy
A112: Nguyên tắc phân loại Bước 5 - Bài regulation: Gán theo vertical mà regulation áp lên - Bài chạm 2 vertical, AI là enabler thì gán theo vertical mà AI được áp dụng. Ví dụ "Snapchat đưa quảng cáo hội thoại bằng AI" => MXH/ Chat
A113: Bước 5: Phân loại theo related-vertical
A114: no | B114: related-vertical
A115: 1 | B115: AI
A116: 2 | B116: MXH/ Chat
A117: 3 | B117: E - Commerce
A118: 4 | B118: Ride/ Food Delivery
A119: 5 | B119: Fintech / E-wallet
A120: 6 | B120: Travel / Ticket
A121: 7 | B121: Smart city

Sheet Database
A1: Auto | B1: Fill | D1: Drop_down list | E1: Auto | F1: Auto | G1: Fill | H1: Fill | I1: Fill | J1: Drop_down list | K1: Drop_down list | L1: Drop_down list | M1: Drop_down list | O1: Fill | P1: Fill | Q1: Fill | R1: Fill | S1: Fill | T1: 0.4 | U1: 0.25 | V1: 0.2 | W1: 0.15 | X1: Calculation
T2: 0.6 | U2: 0.4
A3: id | B3: url | C3: hyperlink | D3: source_name | E3: signal_level | F3: week | G3: crawl_date | H3: title_raw | I3: publish_date | J3: topic_group | K3: sub_topic_group | L3: category | M3: subcategory | N3: merged_category | O3: title_normalized | P3: summary | Q3: start_date | R3: end_date | S3: tags | T3: R1 | U3: R2 | V3: R3 | W3: R4 | X3: signal_score | Y3: related _vertical | Z3: related_product_2
A4: =ROW()-3 -> 1 | B4: https://thuvienphapluat.vn/van-ban/Tien-te-Ngan-hang/Thong-tu-77-2025-TT-NHNN-sua-doi-Thong-tu-50-2024-TT-NHNN-688630.aspx | C4: =HYPERLINK(B4,O4) -> Thông tư 77/2025/TT-NHNN ngày 31/12/2025 có hiệu lực từ 1/3/2026 | D4: Thư viện pháp luật | E4: =VLOOKUP(X4,'Updating-Scoring'!$C$2:$D$7,2,TRUE) -> 5 - Industry disruption | F4: =WEEKNUM(G4,2) -> 9 | G4: 46082 | H4: Ứng dụng Mobile Banking sẽ tự thoát khi điện thoại không bảo mật từ 01/3/2026 | I4: 46022 | J4: Market Pulse | K4: Trong nước | L4: Legal | M4: Banking / Fintech | N4: =L4&" | "&M4 -> Legal | Banking / Fintech | O4: Thông tư 77/2025/TT-NHNN ngày 31/12/2025 có hiệu lực từ 1/3/2026 | P4: Thông tư bổ sung nhiều yêu cầu mới về an toàn, bảo mật ứng dụng Mobile Banking, từ kiểm soát phiên bản phần mềm đến phòng chống tấn công mạng và gian lận bằng công nghệ cao. Ứng dụng Mobile Banking phải tự động thoát hoặc dừng hoạt động và thông báo cho khách hàng lý do nếu phát hiện các dấu hiệu mất an toàn Các giải pháp phát hiện giả mạo sinh trắc học phải đạt chuẩn quốc tế ISO 30107 cấp độ 2 Siết chặt quản lý phiên bản ứng dụng Mobile Banking. Theo quy định mới, tối thiểu 3 tháng một lần, các tổ chức tín dụng phải tổ chức đánh giá mức độ an toàn, bảo mật đối với các phiên bản ứng dụng đang được phép cài đặt, sử dụng, qua đó kịp thời phát hiện lỗ hổng và nguy cơ bị tội phạm mạng can thiệp | Q4: 46082 | S4: Luật; Thông tư; NHNN; Mobile Banking | T4: 5 | U4: 5 | V4: 5 | W4: 5 | X4: =IF(G4<DATE(2026,4,30),T4*$T$1+U4*$U$1+V4*$V$1+W4*$W$1,T4*$T$2+U4*$U$2) -> 5
A5: =ROW()-3 -> 2 | B5: https://thuvienphapluat.vn/van-ban/Cong-nghe-thong-tin/Luat-Tri-tue-nhan-tao-2025-so-134-2025-QH15-679013.aspx | C5: =HYPERLINK(B5,O5) -> Luật Trí tuệ nhân tạo số 134/2025/QH15 do Quốc hội ban hành chính thức áp dụng từ 1/3/2026 | D5: Thư viện pháp luật | E5: =VLOOKUP(X5,'Updating-Scoring'!$C$2:$D$7,2,TRUE) -> 5 - Industry disruption | F5: =WEEKNUM(G5,2) -> 9 | G5: 46082 | H5: Luật Trí tuệ nhân tạo 2025 số 134/2025/QH15 áp dụng năm 2026 | I5: 45942 | J5: Market Pulse | K5: Trong nước | L5: Legal | M5: AI | N5: =L5&" | "&M5 -> Legal | AI | O5: Luật Trí tuệ nhân tạo số 134/2025/QH15 do Quốc hội ban hành chính thức áp dụng từ 1/3/2026 | P5: Các hệ thống AI tương tác trực tiếp với con người phải được thiết kế để người dùng biết mình đang làm việc với máy. Đồng thời, nội dung dạng âm thanh, hình ảnh hoặc video do AI tạo ra phải được đánh dấu bằng dấu hiệu nhận biết theo quy định của Chính phủ Phân loại và quản trị hệ thống trí tuệ nhân tạo theo rủi ro để áp dụng biện pháp phù hợp, khuyến khích đổi mới nhưng ưu tiên bảo vệ quyền lợi người bị ảnh hưởng | Q5: 46082 | S5: Luật; Trí tuệ nhân tạo | T5: 5 | U5: 5 | V5: 5 | W5: 5 | X5: =IF(G5<DATE(2026,4,30),T5*$T$1+U5*$U$1+V5*$V$1+W5*$W$1,T5*$T$2+U5*$U$2) -> 5
A6: =ROW()-3 -> 3 | B6: https://genk.vn/chi-dao-moi-nghien-cuu-tich-hop-mang-xa-hoi-vao-vneid-de-dinh-danh-nguoi-dung-ngay-trong-nam-2026-165260222142344609.chn | C6: =HYPERLINK(B6,O6) -> Nghiên cứu tích hợp mạng xã hội vào VNeID để định danh người dùng ngay trong Quý III/2026 | D6: GenK | E6: =VLOOKUP(X6,'Updating-Scoring'!$C$2:$D$7,2,TRUE) -> 5 - Industry disruption | F6: =WEEKNUM(G6,2) -> 9 | G6: 46082 | H6: Chỉ đạo mới: Nghiên cứu tích hợp mạng xã hội vào VNeID để định danh người dùng ngay trong năm 2026 | I6: 46075 | J6: Market Pulse | K6: Trong nước | L6: Political | M6: Natinal digital strategy | N6: =L6&" | "&M6 -> Political | Natinal digital strategy | O6: Nghiên cứu tích hợp mạng xã hội vào VNeID để định danh người dùng ngay trong Quý III/2026 | P6: Theo chương trình công tác năm 2026, Ban Chỉ đạo Trung ương về phát triển khoa học, công nghệ, đổi mới sáng tạo và chuyển đổi số giao Chính phủ rà soát, nghiên cứu giải pháp kỹ thuật liên kết, tích hợp các dịch vụ mạng xã hội với hệ thống VNeID Việc tích hợp nhằm phục vụ xác thực và định danh người dùng trên không gian mạng, bảo đảm tuân thủ quy định pháp luật trong nước cũng như các cam kết quốc tế mà Việt Nam tham gia Theo kế hoạch, nhiệm vụ này cần hoàn tất trong quý III năm nay. | Q6: 46081 | R6: 46296 | S6: VNeID; tích hợp; mạng xã hội | T6: 5 | U6: 5 | V6: 5 | W6: 5 | X6: =IF(G6<DATE(2026,4,30),T6*$T$1+U6*$U$1+V6*$V$1+W6*$W$1,T6*$T$2+U6*$U$2) -> 5
A7: =ROW()-3 -> 4 | B7: https://baotintuc.vn/thi-truong-tien-te/doanh-nghiep-tang-toc-chuan-bi-cho-thi-diem-san-giao-dich-tai-san-ma-hoa-20260226191937609.htm | C7: =HYPERLINK(B7,O7) -> Thị trường giao dịch tài sản mã hóa sẽ được đưa vào vận hành thí điểm trước ngày 28/2/2026 | D7: Báo tin tức | E7: =VLOOKUP(X7,'Updating-Scoring'!$C$2:$D$7,2,TRUE) -> 5 - Industry disruption | F7: =WEEKNUM(G7,2) -> 9 | G7: 46082 | H7: Doanh nghiệp tăng tốc chuẩn bị cho thí điểm sàn giao dịch tài sản mã hóa | I7: 46079 | J7: Market Pulse | K7: Trong nước | L7: Legal | M7: Digital money | N7: =L7&" | "&M7 -> Legal | Digital money | O7: Thị trường giao dịch tài sản mã hóa sẽ được đưa vào vận hành thí điểm trước ngày 28/2/2026 | P7: Các doanh nghiệp Việt Nam đang đẩy nhanh chuẩn bị, tăng vốn và hoàn thiện hệ thống để tham gia thí điểm sàn giao dịch tài sản mã hóa. CAEX và các công ty khác tập trung vào an toàn, bảo mật, quản trị rủi ro theo chuẩn quốc tế, trong bối cảnh khung pháp lý đang hoàn thiện với yêu cầu vốn điều lệ tối thiểu và cơ cấu cổ đông phù hợp | Q7: 46023 | R7: 46080 | S7: Kinh tế; Vận hành thí điểm; Sàn giao dịch; Tiền mã khóa | T7: 5 | U7: 5 | V7: 5 | W7: 5 | X7: =IF(G7<DATE(2026,4,30),T7*$T$1+U7*$U$1+V7*$V$1+W7*$W$1,T7*$T$2+U7*$U$2) -> 5
A8: =ROW()-3 -> 5 | B8: https://baomoi.com/google-ra-mat-nano-banana-2-cai-tien-toc-do-va-kha-nang-tao-anh-ai-chat-luong-4k-c54567264.epi | C8: =HYPERLINK(B8,O8) -> Google ra mắt mô hình tạo ảnh mới Nano Banana 2, tham vọng phủ sóng toàn hệ sinh thái AI | D8: Báo mới | E8: =VLOOKUP(X8,'Updating-Scoring'!$C$2:$D$7,2,TRUE) -> 5 - Industry disruption | F8: =WEEKNUM(G8,2) -> 9 | G8: 46082 | H8: Google ra mắt mô hình tạo ảnh mới Nano Banana 2, tham vọng phủ sóng toàn hệ sinh thái AI | I8: 46080 | J8: Market Pulse | K8: Quốc tế | L8: Technology | M8: AI/ Gen AI | N8: =L8&" | "&M8 -> Technology | AI/ Gen AI | O8: Google ra mắt mô hình tạo ảnh mới Nano Banana 2, tham vọng phủ sóng toàn hệ sinh thái AI | P8: Nano Banana 2 có tên chính thức là Gemini 3.1 Flash Image. Theo Google, mô hình này kết hợp khả năng suy luận chuyên sâu của biến thể Pro trước đó với độ phản hồi nhanh của Gemini Flash. Hệ thống được cho là có thể khai thác kiến thức thực tế và tham chiếu thông tin web cập nhật để tái hiện chính xác các chủ thể cụ thể. Nhờ đó, người dùng có thể tạo ra infographic chi tiết, sơ đồ có cấu trúc rõ ràng và các hình ảnh dựa trên dữ liệu với độ chính xác ngữ cảnh được cải thiện | S8: AI; Google; Nano Banana 2; Gemini Flash | T8: 5 | U8: 5 | V8: 5 | W8: 5 | X8: =IF(G8<DATE(2026,4,30),T8*$T$1+U8*$U$1+V8*$V$1+W8*$W$1,T8*$T$2+U8*$U$2) -> 5
A9: =ROW()-3 -> 6 | B9: https://baomoi.com/5-xu-huong-ai-se-dinh-hinh-chien-luoc-lanh-dao-nam-2026-c54541582.epi | C9: =HYPERLINK(B9,O9) -> Sự tăng tốc của các hệ sinh thái super-app “AI-FIRST” | D9: Báo mới | E9: =VLOOKUP(X9,'Updating-Scoring'!$C$2:$D$7,2,TRUE) -> 5 - Industry disruption | F9: =WEEKNUM(G9,2) -> 9 | G9: 46082 | H9: 5 xu hướng AI sẽ định hình chiến lược lãnh đạo năm 2026 | I9: 46077 | J9: Market Pulse | K9: Quốc tế | L9: Technology | M9: AI/ Gen AI | N9: =L9&" | "&M9 -> Technology | AI/ Gen AI | O9: Sự tăng tốc của các hệ sinh thái super-app “AI-FIRST” | P9: AI đang chuyển từ vai trò “công cụ hỗ trợ” sang trở thành một tầng vận hành chiến lược của doanh nghiệp, nơi các tác nhân AI (agentic AI) có khả năng tự lập kế hoạch, điều phối quy trình và thay đổi cấu trúc lãnh đạo truyền thống. Năm 2026, các super-app AI‑first và hệ sinh thái AI bản địa hóa sẽ trở thành lợi thế cạnh tranh cốt lõi, buộc lãnh đạo doanh nghiệp phải tái thiết kế lực lượng lao động, mô hình tổ chức và phương thức ra quyết định. | S9: AI; Tác nhân AI; Agent; Xu hướng | T9: 5 | U9: 5 | V9: 5 | W9: 5 | X9: =IF(G9<DATE(2026,4,30),T9*$T$1+U9*$U$1+V9*$V$1+W9*$W$1,T9*$T$2+U9*$U$2) -> 5
A10: =ROW()-3 -> 7 | B10: https://vneconomy.vn/techconnect/cac-ong-lon-cong-nghe-trung-quoc-chay-dua-xay-dung-sieu-ung-dung-ai.htm | C10: =HYPERLINK(B10,O10) -> Alibaba, Baidu, ByteDance và Tencent đang chạy đua biến chatbot thành công cụ mua sắm | D10: VNEconomy | E10: =VLOOKUP(X10,'Updating-Scoring'!$C$2:$D$7,2,TRUE) -> 5 - Industry disruption | F10: =WEEKNUM(G10,2) -> 9 | G10: 46082 | H10: Các “ông lớn” công nghệ Trung Quốc chạy đua xây dựng siêu ứng dụng AI | I10: 46045 | J10: Market Pulse | K10: Trung quốc | L10: Technology | M10: AI/ Gen AI | N10: =L10&" | "&M10 -> Technology | AI/ Gen AI | O10: Alibaba, Baidu, ByteDance và Tencent đang chạy đua biến chatbot thành công cụ mua sắm | P10: Alibaba đã nâng cấp chatbot AI Qwen 3.5, cho phép người dùng hoàn tất giao dịch trực tiếp trong giao diện trò chuyện. Thông qua bản cập nhật này, người dùng có thể đặt đồ ăn, mua vé máy bay, so sánh sản phẩm, đặt phòng khách sạn và thanh toán – tất cả mà không cần rời khỏi chatbot Điểm khác biệt lớn nhất của Qwen phiên bản mới nằm ở khả năng kết nối sâu với toàn bộ hệ sinh thái thương mại của Alibaba. AI có thể truy xuất dữ liệu và đề xuất sản phẩm từ Taobao, Tmall, Fliggy (du lịch), các dịch vụ giao đồ ăn, rồi xử lý thanh toán qua Alipay Đầu tháng 2, chiến dịch tặng phiếu giảm giá khi đặt trà sữa qua AI Qwen của Alibaba với ngân sách 3 tỷ NDT đã giúp lượng người dùng hoạt động của Qwen tăng gấp 7 lần. Trước đó, Tencent khởi động chương trình phát lì xì trị giá 1 tỷ NDT (khoảng 140 triệu USD) thông qua trợ lý AI Yuanbao. Không lâu sau, Baidu tung ra gói 500 triệu NDT cho Wenxin (Wechat) AI | S10: AI; Agentic commerce; chatbot AI; Thương mại điện tử; Trung Quốc; AI Agent | T10: 5 | U10: 5 | V10: 5 | W10: 5 | X10: =IF(G10<DATE(2026,4,30),T10*$T$1+U10*$U$1+V10*$V$1+W10*$W$1,T10*$T$2+U10*$U$2) -> 5
A11: =ROW()-3 -> 8 | B11: https://genk.vn/galaxy-s26-series-co-7-tinh-nang-ai-moi-tu-mo-app-goi-xe-dat-do-an-chinh-anh-bang-loi-noi-tu-nghe-cuoc-goi-nguoi-la-16526022601523337.chn | C11: =HYPERLINK(B11,O11) -> Galaxy S26 series sẽ mang đến 7 nâng cấp AI mới, tập trung vào tự động hóa tác vụ đa bước,..triển khai trước tại Mỹ và Hàn Quốc | D11: GenK | E11: =VLOOKUP(X11,'Updating-Scoring'!$C$2:$D$7,2,TRUE) -> 5 - Industry disruption | F11: =WEEKNUM(G11,2) -> 9 | G11: 46082 | H11: Galaxy S26 series có 7 tính năng AI mới: Tự mở app gọi xe, đặt đồ ăn, chỉnh ảnh bằng lời nói, tự nghe cuộc gọi người lạ… | I11: 46079 | J11: Market Pulse | K11: Quốc tế | L11: Technology | M11: AI/ Gen AI | N11: =L11&" | "&M11 -> Technology | AI/ Gen AI | O11: Galaxy S26 series sẽ mang đến 7 nâng cấp AI mới, tập trung vào tự động hóa tác vụ đa bước,..triển khai trước tại Mỹ và Hàn Quốc | P11: Gemini được nâng cấp vượt khỏi mô hình chatbot truyền thống, trợ lý Agentic AI này có thể trực tiếp thao tác ứng dụng thay cho người dùng và xử lý các tác vụ nhiều bước vốn trước đây yêu cầu chuyển qua lại giữa 3 đến 4 app. Ở giai đoạn beta, tính năng này được triển khai trước tại Mỹ và Hàn Quốc. 3 nhóm tác vụ chính được hỗ trợ gồm đặt lại món quen trên DoorDash hoặc Uber Eats, so sánh và đặt xe giữa các nền tảng hỗ trợ, xây dựng giỏ hàng tạp hóa từ công thức nấu ăn hoặc lịch sử mua sắm thông qua các đối tác như Kroger và Walmart. Theo thông tin hiện tại, phiên bản Gemini agentic này chỉ có trên dòng Galaxy S26 và Pixel 10 | S11: AI; Galaxy AI | T11: 5 | U11: 5 | V11: 5 | W11: 5 | X11: =IF(G11<DATE(2026,4,30),T11*$T$1+U11*$U$1+V11*$V$1+W11*$W$1,T11*$T$2+U11*$U$2) -> 5
A12: =ROW()-3 -> 9 | B12: https://zalopay.vn/thong-bao-zalopay-nang-cap-bao-mat-theo-thong-tu-77-8302 | C12: =HYPERLINK(B12,O12) -> Zalopay nâng cấp bảo mật theo Thông tư 77/2025/TT-NHNN, tăng cường an toàn giao dịch cho người dùng | D12: ZaloPay Wesbite | E12: =VLOOKUP(X12,'Updating-Scoring'!$C$2:$D$7,2,TRUE) -> 5 - Industry disruption | F12: =WEEKNUM(G12,2) -> 9 | G12: 46082 | H12: Zalopay nâng cấp bảo mật theo Thông tư 77/2025/TT-NHNN, tăng cường an toàn giao dịch cho người dùng | I12: 46080 | J12: Players Movement | K12: Zalopay | L12: Feature | M12: Security / Privacy | N12: =L12&" | "&M12 -> Feature | Security / Privacy | O12: Zalopay nâng cấp bảo mật theo Thông tư 77/2025/TT-NHNN, tăng cường an toàn giao dịch cho người dùng | P12: Ứng dụng Zalopay sẽ tự động thoát hoặc dừng hoạt động và xuất hiện thông báo lý do trên màn hình để bảo vệ tài khoản và thông tin giao dịch của khách hàng nếu phát hiện thiết bị có dấu hiệu mất an toàn | Q12: 46082 | S12: Bảo mật thông tin; Tin tức | T12: 5 | U12: 5 | V12: 5 | W12: 5 | X12: =IF(G12<DATE(2026,4,30),T12*$T$1+U12*$U$1+V12*$V$1+W12*$W$1,T12*$T$2+U12*$U$2) -> 5
A13: =ROW()-3 -> 10 | B13: https://zalopay.vn/giam-den-50000d-khi-thanh-toan-home-credit-tren-zalopay-6686 | C13: =HYPERLINK(B13,O13) -> Giảm đến 50.000đ khi thanh toán Home Credit trên Zalopay | D13: ZaloPay Wesbite | E13: =VLOOKUP(X13,'Updating-Scoring'!$C$2:$D$7,2,TRUE) -> 5 - Industry disruption | F13: =WEEKNUM(G13,2) -> 9 | G13: 46082 | H13: Giảm đến 50.000đ khi thanh toán Home Credit trên Zalopay | I13: 46081 | J13: Players Movement | K13: Zalopay | L13: Marketing | M13: Ecosystem expansion | N13: =L13&" | "&M13 -> Marketing | Ecosystem expansion | O13: Giảm đến 50.000đ khi thanh toán Home Credit trên Zalopay | P13: Chương trình này cho thấy ZaloPay đang đẩy mạnh nhóm dịch vụ thanh toán tài chính – trả góp (FECredit, Home Credit). Việc yêu cầu mức thanh toán tối thiểu (500.000đ hoặc 1.000.000đ) giúp ZaloPay tăng giá trị giao dịch bình quân | Q13: 46054 | R13: 46112 | S13: Khuyến mãi; Ưu đãi thanh toán hóa đơn; Vay tiêu dùng; Dịch vụ vay tiêu dùng | T13: 5 | U13: 5 | V13: 5 | W13: 5 | X13: =IF(G13<DATE(2026,4,30),T13*$T$1+U13*$U$1+V13*$V$1+W13*$W$1,T13*$T$2+U13*$U$2) -> 5 | Y13: Tín dụng | Z13: Home Credit
A14: =ROW()-3 -> 11 | B14: https://zalopay.vn/giam-den-50000d-khi-thanh-toan-fe-credit-tren-zalopay-6941 | C14: =HYPERLINK(B14,O14) -> Giảm đến 50.000đ khi thanh toán FE Credit trên Zalopay | D14: ZaloPay Wesbite | E14: =VLOOKUP(X14,'Updating-Scoring'!$C$2:$D$7,2,TRUE) -> 5 - Industry disruption | F14: =WEEKNUM(G14,2) -> 9 | G14: 46082 | H14: Giảm đến 50.000đ khi thanh toán FE Credit trên Zalopay | I14: 46081 | J14: Players Movement | K14: Zalopay | L14: Marketing | M14: Ecosystem expansion | N14: =L14&" | "&M14 -> Marketing | Ecosystem expansion | O14: Giảm đến 50.000đ khi thanh toán FE Credit trên Zalopay | Q14: 46054 | R14: 46112 | S14: Khuyến mãi; Ưu đãi thanh toán hóa đơn; Vay tiêu dùng; Dịch vụ vay tiêu dùng | T14: 5 | U14: 5 | V14: 5 | W14: 5 | X14: =IF(G14<DATE(2026,4,30),T14*$T$1+U14*$U$1+V14*$V$1+W14*$W$1,T14*$T$2+U14*$U$2) -> 5 | Y14: Tín dụng | Z14: FE Credit
A15: =ROW()-3 -> 12 | B15: https://www.facebook.com/share/p/18EGxQ3xRn/?mibextid=wwXIfr | C15: =HYPERLINK(B15,O15) -> Đặt dịch vụ giao hàng SPX Express trên ZaloPay | D15: ZaloPay Fanpage | E15: =VLOOKUP(X15,'Updating-Scoring'!$C$2:$D$7,2,TRUE) -> 5 - Industry disruption | F15: =WEEKNUM(G15,2) -> 9 | G15: 46082 | H15: Đặt dịch vụ giao hàng SPX Express trên ZaloPay | I15: 46078 | J15: Players Movement | K15: Zalopay | L15: Marketing | M15: Ecosystem expansion | N15: =L15&" | "&M15 -> Marketing | Ecosystem expansion | O15: Đặt dịch vụ giao hàng SPX Express trên ZaloPay | P15: Truyền thông về dịch vụ đặt giao hàng của SPX trên ứng dụng Zalopay với giá ưu đãi hơn, từ 5.000đ/kg | Q15: 46078 | R15: 46095 | S15: Khuyến mãi; Ưu đãi thanh toán hóa đơn; Chuyển phát nhanh | T15: 5 | U15: 5 | V15: 5 | W15: 5 | X15: =IF(G15<DATE(2026,4,30),T15*$T$1+U15*$U$1+V15*$V$1+W15*$W$1,T15*$T$2+U15*$U$2) -> 5 | Y15: Thanh toán | Z15: SPX Express
A16: =ROW()-3 -> 13 | B16: https://www.momo.vn/tin-tuc/tin-tuc-su-kien/15h-17h59-23-02-giat-li-xi-mung-7-115000-bao-li-8491 | C16: =HYPERLINK(B16,O16) -> Giật Lì Xì Mùng 7: 115.000 bao lì xì đến 28k - 68k - 888k! | D16: MoMo Website | E16: =VLOOKUP(X16,'Updating-Scoring'!$C$2:$D$7,2,TRUE) -> 5 - Industry disruption | F16: =WEEKNUM(G16,2) -> 9 | G16: 46082 | H16: Giật Lì Xì Mùng 7: 115.000 bao lì xì đến 28k - 68k - 888k! | I16: 46066 | J16: Players Movement | K16: MoMo | L16: Marketing | M16: User engagement | N16: =L16&" | "&M16 -> Marketing | User engagement | O16: Giật Lì Xì Mùng 7: 115.000 bao lì xì đến 28k - 68k - 888k! | P16: Chiến dịch này tận dụng ngày Mùng 7 – thời điểm dân công sở quay lại làm việc để kích hoạt tương tác và tăng tỷ lệ mở app nối tiếp 2 chiến dịch Giật lì xì đêm Giao Thừa và Giật lì xì trong Mùng 1 Tết: - Hoàn thành nhiệm vụ “Nhận tiền từ ngân hàng về MoMo qua số điện thoại (tối thiểu 10.000đ) - 3 loại lì xì khác nhau vào 3 khung giờ khác nhau - Tổng ngân sách: 134 triệu | Q16: 46076.625 | R16: 46076.749 | S16: Khuyến mãi; Gamification; Lì xì mùng 7 | T16: 5 | U16: 5 | V16: 5 | W16: 5 | X16: =IF(G16<DATE(2026,4,30),T16*$T$1+U16*$U$1+V16*$V$1+W16*$W$1,T16*$T$2+U16*$U$2) -> 5 | Y16: Thanh toán | Z16: Nhận tiền từ ngân hàng qua SĐT Momo
A17: =ROW()-3 -> 14 | B17: https://www.momo.vn/tin-tuc/tin-tuc-su-kien/15h-17h59-26-02-giat-li-xi-ngay-than-tai-tong-8490 | C17: =HYPERLINK(B17,O17) -> Giật Lì Xì Ngày Thần Tài: Tổng hơn 879.000 bao lì xì đến 39k - 79k - 797k | D17: MoMo Website | E17: =VLOOKUP(X17,'Updating-Scoring'!$C$2:$D$7,2,TRUE) -> 5 - Industry disruption | F17: =WEEKNUM(G17,2) -> 9 | G17: 46082 | H17: Giật Lì Xì Ngày Thần Tài: Tổng hơn 879.000 bao lì xì đến 39k - 79k - 797k | I17: 46066 | J17: Players Movement | K17: MoMo | L17: Marketing | M17: User engagement | N17: =L17&" | "&M17 -> Marketing | User engagement | O17: Giật Lì Xì Ngày Thần Tài: Tổng hơn 879.000 bao lì xì đến 39k - 79k - 797k | P17: Chiến dịch đánh mạnh vào nhu cầu cầu may ngày Thần Tài từ để tăng tương tác và tỷ lệ mở app: - Hoàn thành nhiệm vụ “Kiểm tra/Chia sẻ nội dung khi kiểm tra điểm CIC trên Ứng dụng MoMo” - 6 loại lì xì khác nhau vào 6 khung giờ khác nhau - Tổng ngân sách: 265 triệu | Q17: 46079.625 | R17: 46079.874 | S17: Khuyến mãi; Gamification; Lì xì ngày thần tài | T17: 5 | U17: 5 | V17: 5 | W17: 5 | X17: =IF(G17<DATE(2026,4,30),T17*$T$1+U17*$U$1+V17*$V$1+W17*$W$1,T17*$T$2+U17*$U$2) -> 5 | Y17: Tín dụng | Z17: Kiểm tra CIC
A18: =ROW()-3 -> 15 | B18: https://www.momo.vn/tin-tuc/tin-tuc-su-kien/11h-15h-25-02-27-02-than-tai-li-xi-den-797979d-8498 | C18: =HYPERLINK(B18,O18) -> Thần Tài lì xì đến 797.979đ cùng hàng chục miếng vàng đến nửa chỉ tại Lắc Xì cùng quà Samsung tại FPTShop | D18: MoMo Website | E18: =VLOOKUP(X18,'Updating-Scoring'!$C$2:$D$7,2,TRUE) -> 5 - Industry disruption | F18: =WEEKNUM(G18,2) -> 9 | G18: 46082 | H18: Thần Tài lì xì đến 797.979đ cùng hàng chục miếng vàng đến nửa chỉ tại Lắc Xì | I18: 46078 | J18: Players Movement | K18: MoMo | L18: Marketing | M18: User engagement | N18: =L18&" | "&M18 -> Marketing | User engagement | O18: Thần Tài lì xì đến 797.979đ cùng hàng chục miếng vàng đến nửa chỉ tại Lắc Xì cùng quà Samsung tại FPTShop | P18: Chuỗi sự kiện đặc biệt nằm trong chiến dịch "Lắc xì 2026 - Săn Mã Rước Lộc" nhằm thu hút người dùng vào ứng dụng, sử dụng các sản phẩm dịch vụ của MoMo và đối tác để hoàn thành nhiệm vụ và thêm lượt giật lì xì - Nhận tiền chuyển từ ngân hàng vào MoMo bằng số điện thoại - Kiểm tra điểm CIC trên Ứng dụng MoMo - Đăng ký hội viên Nestle... | Q18: 46078.458 | R18: 46080.625 | S18: Sự kiện; Gamification; Lắc xì; Đối tác | T18: 5 | U18: 5 | V18: 5 | W18: 5 | X18: =IF(G18<DATE(2026,4,30),T18*$T$1+U18*$U$1+V18*$V$1+W18*$W$1,T18*$T$2+U18*$U$2) -> 5
A19: =ROW()-3 -> 16 | B19: https://www.momo.vn/tin-tuc/tin-tuc-su-kien/11h-15h-23-02-24-02-lac-xi-lay-10-mieng-vang-01-8484 | C19: =HYPERLINK(B19,O19) -> Lắc Xì: Lấy 10 miếng vàng 0,1 chỉ, 2 iPad Mini, quà sức khỏe từ Chubb (Hoàn 150k) | D19: MoMo Website | E19: =VLOOKUP(X19,'Updating-Scoring'!$C$2:$D$7,2,TRUE) -> 5 - Industry disruption | F19: =WEEKNUM(G19,2) -> 9 | G19: 46082 | H19: Lắc Xì: Lấy 10 miếng vàng 0,1 chỉ, 2 iPad Mini, quà sức khỏe từ Chubb | I19: 46066 | J19: Players Movement | K19: MoMo | L19: Marketing | M19: User engagement | N19: =L19&" | "&M19 -> Marketing | User engagement | O19: Lắc Xì: Lấy 10 miếng vàng 0,1 chỉ, 2 iPad Mini, quà sức khỏe từ Chubb (Hoàn 150k) | P19: Chuỗi sự kiện đặc biệt nằm trong chiến dịch "Lắc xì 2026 - Săn Mã Rước Lộc" nhằm thu hút người dùng vào ứng dụng, sử dụng các sản phẩm dịch vụ của MoMo và đối tác để hoàn thành nhiệm vụ và thêm lượt giật lì xì - Nhận tiền chuyển từ ngân hàng vào MoMo bằng số điện thoại - Kiểm tra điểm CIC trên Ứng dụng MoMo - Đăng ký hội viên Nestle... | Q19: 46076.458 | R19: 46077.625 | S19: Sự kiện; Gamification; Lắc xì; Đối tác | T19: 5 | U19: 5 | V19: 5 | W19: 5 | X19: =IF(G19<DATE(2026,4,30),T19*$T$1+U19*$U$1+V19*$V$1+W19*$W$1,T19*$T$2+U19*$U$2) -> 5
A20: =ROW()-3 -> 17 | B20: https://www.momo.vn/tin-tuc/khuyen-mai/mo-bat-2026-voi-3-ngay-vang-gioi-thieu-momo-nhan-8325 | C20: =HYPERLINK(B20,O20) -> Ngày Vàng Mời Bạn trở lại: 100% nhận thưởng 100K hoặc 999K tiền mặt khi giới thiệu MoMo | D20: MoMo Website | E20: =VLOOKUP(X20,'Updating-Scoring'!$C$2:$D$7,2,TRUE) -> 5 - Industry disruption | F20: =WEEKNUM(G20,2) -> 9 | G20: 46082 | H20: Ngày Vàng Mời Bạn trở lại: 100% nhận thưởng 100K hoặc 999K tiền mặt khi giới thiệu MoMo | I20: 46073 | J20: Players Movement | K20: MoMo | L20: Marketing | M20: User acquisition | N20: =L20&" | "&M20 -> Marketing | User acquisition | O20: Ngày Vàng Mời Bạn trở lại: 100% nhận thưởng 100K hoặc 999K tiền mặt khi giới thiệu MoMo | P20: Chiến dịch tập trung thúc đẩy tăng trưởng người dùng mới bằng cơ chế thưởng tiền mặt cho mỗi lượt giới thiệu trong khung giờ vàng, tạo động lực lan truyền mạnh mẽ giữa cộng đồng người dùng hiện hữu - Người được giới thiệu lần đầu nạp 10k vào MoMo trong khung giờ 11h-18h - Người giới thiệu: nhận 100k hoặc 999k - Người được giới thiệu: nhận 686k - Tổng ngân sách: 1 tỷ VND | Q20: 46078.458 | R20: 46080.75 | S20: Khuyến mãi; Thành viên mới | T20: 5 | U20: 5 | V20: 5 | W20: 5 | X20: =IF(G20<DATE(2026,4,30),T20*$T$1+U20*$U$1+V20*$V$1+W20*$W$1,T20*$T$2+U20*$U$2) -> 5
A21: =ROW()-3 -> 18 | B21: https://www.momo.vn/tin-tuc/khuyen-mai/dac-quyen-khi-thanh-toan-bang-nguon-tien-mbbank-8497 | C21: =HYPERLINK(B21,O21) -> MoMo x VPBank: Đặc quyền khi thanh toán bằng nguồn tiền VPBank trên MoMo: Giảm thẳng 10K mọi dịch vụ | D21: MoMo Website | E21: =VLOOKUP(X21,'Updating-Scoring'!$C$2:$D$7,2,TRUE) -> 5 - Industry disruption | F21: =WEEKNUM(G21,2) -> 9 | G21: 46082 | H21: Đặc quyền khi thanh toán bằng nguồn tiền VPBank trên MoMo: Giảm thẳng 10K mọi dịch vụ | I21: 46077 | J21: Players Movement | K21: MoMo | L21: Marketing | M21: Ecosystem expansion | N21: =L21&" | "&M21 -> Marketing | Ecosystem expansion | O21: MoMo x VPBank: Đặc quyền khi thanh toán bằng nguồn tiền VPBank trên MoMo: Giảm thẳng 10K mọi dịch vụ | P21: Đây là chiến dịch ưu đãi ngắn hạn, mang tính recurring, vì MoMo thường xuyên hợp tác ngân hàng để tung ưu đãi giảm giá tương tự. Mục tiêu là gia tăng giao dịch thanh toán bằng nguồn tiền MBBank/ VPBank | Q21: 46054 | R21: 46081 | S21: Khuyến mãi; Thanh toán qua ngân hàng | T21: 5 | U21: 5 | V21: 5 | W21: 5 | X21: =IF(G21<DATE(2026,4,30),T21*$T$1+U21*$U$1+V21*$V$1+W21*$W$1,T21*$T$2+U21*$U$2) -> 5 | Y21: Thanh toán | Z21: VPBank
A22: =ROW()-3 -> 19 | B22: https://www.momo.vn/tin-tuc/khuyen-mai/dac-quyen-khi-thanh-toan-bang-nguon-tien-vpbank-8496 | C22: =HYPERLINK(B22,O22) -> MoMo x Mbank: Đặc quyền khi thanh toán bằng nguồn tiền MBAnk trên MoMo: Giảm thẳng 10K mọi dịch vụ | D22: MoMo Website | E22: =VLOOKUP(X22,'Updating-Scoring'!$C$2:$D$7,2,TRUE) -> 5 - Industry disruption | F22: =WEEKNUM(G22,2) -> 9 | G22: 46082 | H22: Đặc quyền khi thanh toán bằng nguồn tiền MBAnk trên MoMo: Giảm thẳng 10K mọi dịch vụ | I22: 46077 | J22: Players Movement | K22: MoMo | L22: Marketing | M22: Ecosystem expansion | N22: =L22&" | "&M22 -> Marketing | Ecosystem expansion | O22: MoMo x Mbank: Đặc quyền khi thanh toán bằng nguồn tiền MBAnk trên MoMo: Giảm thẳng 10K mọi dịch vụ | P22: Đây là chiến dịch ưu đãi ngắn hạn, mang tính recurring, vì MoMo thường xuyên hợp tác ngân hàng để tung ưu đãi giảm giá tương tự. Mục tiêu là gia tăng giao dịch thanh toán bằng nguồn tiền MBBank/ VPBank | Q22: 46054 | R22: 46081 | S22: Khuyến mãi; Thanh toán qua ngân hàng | T22: 5 | U22: 5 | V22: 5 | W22: 5 | X22: =IF(G22<DATE(2026,4,30),T22*$T$1+U22*$U$1+V22*$V$1+W22*$W$1,T22*$T$2+U22*$U$2) -> 5 | Y22: Thanh toán | Z22: MBBank
A23: =ROW()-3 -> 20 | B23: https://genk.vn/con-ac-mong-cua-marketing-openclaw-co-the-lam-mat-dau-an-thuong-hieu-bien-app-thanh-vo-hinh-giao-dien-phan-mem-ui-ux-tro-nen-vo-dung-165260323082541686.chn | C23: =HYPERLINK(B23,O23) -> AI Agent 'vô hình hóa' App & Brand — Kỷ nguyên Post-App bắt đầu | D23: GenK | E23: =VLOOKUP(X23,'Updating-Scoring'!$C$2:$D$7,2,TRUE) -> 5 - Industry disruption | F23: =WEEKNUM(G23,2) -> 14 | G23: 46111 | H23: Cơn ác mộng của marketing: OpenClaw có thể làm mất dấu ấn thương hiệu, biến App thành vô hình | I23: 46104 | J23: Market Pulse | K23: Quốc tế | L23: Technology | M23: AI/ Gen AI | N23: =L23&" | "&M23 -> Technology | AI/ Gen AI | O23: AI Agent 'vô hình hóa' App & Brand — Kỷ nguyên Post-App bắt đầu | P23: Theo báo cáo của Xtendedview, 72% quản lý mảng trải nghiệm khách hàng tin rằng AI agent sẽ trở thành “đại diện thương hiệu” trong tương lai. Tương tự, nghiên cứu của Zealous System cho thấy 70% người dùng sẵn sàng để AI đặt vé hoặc chọn khách sạn thay họ. AI Agent như OpenClaw có thể thay người dùng thao tác trực tiếp trên phần mềm, khiến ứng dụng và giao diện dần trở nên “vô hình”. Điều này làm suy yếu vai trò của UI/UX và giảm giá trị nhận diện thương hiệu trong marketing | S23: OpenClaw; AI agent; post-app era; super-app; brand loyalty; UI UX; marketing digital | T23: 5 | U23: 4 | V23: 3 | W23: 5 | X23: =IF(G23<DATE(2026,4,30),T23*$T$1+U23*$U$1+V23*$V$1+W23*$W$1,T23*$T$2+U23*$U$2) -> 4.35
A24: =ROW()-3 -> 21 | B24: https://techcrunch.com/2026/03/26/whatsapp-can-now-draft-ai-generated-responses-based-on-your-conversations/ | C24: =HYPERLINK(B24,O24) -> WhatsApp ra mắt trả lời gợi ý bằng AI – Xu hướng AI hóa nhắn tin cá nhân | D24: Tech Crunch | E24: =VLOOKUP(X24,'Updating-Scoring'!$C$2:$D$7,2,TRUE) -> 5 - Industry disruption | F24: =WEEKNUM(G24,2) -> 14 | G24: 46111 | H24: WhatsApp can now draft AI-generated responses based on your conversations | I24: 46107 | J24: Market Pulse | K24: Quốc tế | L24: Technology | M24: AI/ Gen AI | N24: =L24&" | "&M24 -> Technology | AI/ Gen AI | O24: WhatsApp ra mắt trả lời gợi ý bằng AI – Xu hướng AI hóa nhắn tin cá nhân | P24: WhatsApp ra mắt 'Writing Help' mới tự động gợi ý phản hồi dựa trên ngữ cảnh cuộc trò chuyện. Ngoài ra, bổ sung tính năng xóa file lớn trong chat, chỉnh sửa ảnh bằng Meta AI, chuyển lịch sử chat giữa iOS-Android, và đăng nhập hai tài khoản đồng thời trên iOS. | S24: WhatsApp; Meta AI; AI reply; Writing Help; messaging app; AI features; chat export | T24: 5 | U24: 3 | V24: 5 | W24: 4 | X24: =IF(G24<DATE(2026,4,30),T24*$T$1+U24*$U$1+V24*$V$1+W24*$W$1,T24*$T$2+U24*$U$2) -> 4.35
A25: =ROW()-3 -> 22 | B25: https://dantri.com.vn/cong-nghe/tai-dien-chieu-tro-lua-dao-chiem-doat-tai-khoan-telegram-tai-viet-nam-20260324155052293.htm | C25: =HYPERLINK(B25,O25) -> Lừa đảo chiếm đoạt tài khoản Telegram tái bùng phát tại Việt Nam | D25: Dân Trí | E25: =VLOOKUP(X25,'Updating-Scoring'!$C$2:$D$7,2,TRUE) -> 3 - Market signal | F25: =WEEKNUM(G25,2) -> 14 | G25: 46111 | H25: Tái diễn chiêu trò lừa đảo chiếm đoạt tài khoản Telegram tại Việt Nam | I25: 46105 | J25: Market Pulse | K25: Trong nước | L25: Social | M25: Digital adoption | N25: =L25&" | "&M25 -> Social | Digital adoption | O25: Lừa đảo chiếm đoạt tài khoản Telegram tái bùng phát tại Việt Nam | P25: Chiêu trò mạo danh “Trung tâm an toàn” hoặc “Telegram” gửi cảnh báo khóa tài khoản quay trở lại, dụ người dùng truy cập link giả mạo rồi nhập số điện thoại và mã OTP, từ đó bị chiếm quyền tài khoản. Kẻ gian lợi dụng cơ chế chỉ cần OTP là đăng nhập được nếu chưa bật 2FA, khiến nhiều nạn nhân bị mất tài khoản ngay lập tức Việc ưu tiên bảo mật mặc định và cảnh báo chủ động in-app benner/ notification khi phát hiện hành vi bất thường là cần thiết để bảo vệ người dùng khi sử dụng ứng dụng nhắn tin | S25: Telegram; lừa đảo; phishing; OTP; chiếm đoạt tài khoản; an ninh mạng; Việt Nam | T25: 4 | U25: 3 | V25: 4 | W25: 1 | X25: =IF(G25<DATE(2026,4,30),T25*$T$1+U25*$U$1+V25*$V$1+W25*$W$1,T25*$T$2+U25*$U$2) -> 3.3
A26: =ROW()-3 -> 23 | B26: https://genk.vn/chatgpt-sap-cho-phep-noi-dung-nhay-cam-day-lo-ngai-lo-du-lieu-ca-nhan-165260322073640315.chn | C26: =HYPERLINK(B26,O26) -> ChatGPT thêm nội dung nhạy cảm: Rủi ro dữ liệu cá nhân trong AI tiêu dùng | D26: GenK | E26: =VLOOKUP(X26,'Updating-Scoring'!$C$2:$D$7,2,TRUE) -> 2 - Minor signal | F26: =WEEKNUM(G26,2) -> 14 | G26: 46111 | H26: ChatGPT sắp cho phép nội dung nhạy cảm, dấy lo ngại lộ dữ liệu cá nhân | I26: 46103 | J26: Market Pulse | K26: Quốc tế | L26: Legal | M26: Data privacy | N26: =L26&" | "&M26 -> Legal | Data privacy | O26: ChatGPT thêm nội dung nhạy cảm: Rủi ro dữ liệu cá nhân trong AI tiêu dùng | P26: ChatGPT có thể mở rộng cho phép nội dung nhạy cảm hơn, gây lo ngại về quyền riêng tư và kiểm soát dữ liệu. Việc nới lỏng policy cho thấy áp lực cạnh tranh và nhu cầu tăng trưởng người dùng. Tuy nhiên, rủi ro pháp lý và trust từ người dùng cũng gia tăng. | S26: ChatGPT; OpenAI; nội dung nhạy cảm; dữ liệu cá nhân; data privacy; AI safety | T26: 3 | U26: 3 | V26: 3 | W26: 2 | X26: =IF(G26<DATE(2026,4,30),T26*$T$1+U26*$U$1+V26*$V$1+W26*$W$1,T26*$T$2+U26*$U$2) -> 2.85
A27: =ROW()-3 -> 24 | B27: https://genk.vn/openai-len-ke-hoach-ra-mat-sieu-ung-dung-tren-may-tinh-165260322073417885.chn | C27: =HYPERLINK(B27,O27) -> OpenAI hợp nhất thành Super-App PC: ChatGPT + Codex + Browser — AI-first hội tụ | D27: GenK | E27: =VLOOKUP(X27,'Updating-Scoring'!$C$2:$D$7,2,TRUE) -> 2 - Minor signal | F27: =WEEKNUM(G27,2) -> 14 | G27: 46111 | H27: OpenAI lên kế hoạch ra mắt 'siêu ứng dụng' trên máy tính | I27: 46103 | J27: Market Pulse | K27: Quốc tế | L27: Technology | M27: AI/ Gen AI | N27: =L27&" | "&M27 -> Technology | AI/ Gen AI | O27: OpenAI hợp nhất thành Super-App PC: ChatGPT + Codex + Browser — AI-first hội tụ | P27: OpenAI đang hướng tới xây dựng “super app” trên desktop, tích hợp nhiều workflow AI trong một nền tảng. Chiến lược này nhằm tăng lock-in và mở rộng use case beyond chatbot. Đây là bước đi cạnh tranh trực tiếp với OS và productivity ecosystem. | S27: OpenAI; super app; siêu ứng dụng; ChatGPT; Codex; AI agent; Greg Brockman | T27: 2 | U27: 4 | V27: 2 | W27: 5 | X27: =IF(G27<DATE(2026,4,30),T27*$T$1+U27*$U$1+V27*$V$1+W27*$W$1,T27*$T$2+U27*$U$2) -> 2.95
A28: =ROW()-3 -> 25 | B28: https://techcrunch.com/2026/03/25/meta-turns-to-ai-to-make-shopping-easier-on-instagram-and-facebook/ | C28: =HYPERLINK(B28,O28) -> Meta tung AI Shopping Pop-up – Tăng chuyển đổi ngay trong Facebook & Instagram | D28: Tech Crunch | E28: =VLOOKUP(X28,'Updating-Scoring'!$C$2:$D$7,2,TRUE) -> 5 - Industry disruption | F28: =WEEKNUM(G28,2) -> 14 | G28: 46111 | H28: Meta turns to AI to make shopping easier on Instagram and Facebook | I28: 46106 | J28: Market Pulse | K28: Quốc tế | L28: Technology | M28: AI/ Gen AI | N28: =L28&" | "&M28 -> Technology | AI/ Gen AI | O28: Meta tung AI Shopping Pop-up – Tăng chuyển đổi ngay trong Facebook & Instagram | P28: Bắt đầu thử nghiệm AI shopping pop‑up trên Facebook và Instagram, tự động tóm tắt review, mô tả sản phẩm và gợi ý khuyến mãi ngay khi người dùng bấm vào quảng cáo hoặc link sản phẩm. Tính năng mới còn bổ sung AI tổng hợp “what people are saying”, gợi ý sản phẩm liên quan và cho phép thêm vào giỏ trực tiếp trong app, giảm rủi ro rời phiên. Tích hợp checkout 1 chạm với Stripe và PayPal để hoàn tất mua hàng ngay trong nền tảng, đồng thời mở rộng mạng lưới affiliate với Amazon, eBay, Shopee… để tăng doanh thu từ creator commerce. Động thái cho thấy Meta đang đẩy mạnh chiến lược biến mạng xã hội thành hệ sinh thái thương mại liền mạch, cạnh tranh trực diện với TikTok Shop và Amazon. | S28: Meta; Instagram; Facebook; AI shopping; social commerce; checkout; Stripe; PayPal | T28: 5 | U28: 4 | V28: 4 | W28: 4 | X28: =IF(G28<DATE(2026,4,30),T28*$T$1+U28*$U$1+V28*$V$1+W28*$W$1,T28*$T$2+U28*$U$2) -> 4.4
A29: =ROW()-3 -> 26 | B29: https://genk.vn/openclaw-khien-30-nam-kinh-nghiem-excel-tro-nen-vo-nghia-day-co-phai-ngay-tan-cua-ky-nang-su-dung-may-tinh-van-phong-165260323082818451.chn | C29: =HYPERLINK(B29,O29) -> AI Agent thay thế kỹ năng văn phòng — 'AI Delegation' là năng lực cốt lõi mới | D29: GenK | E29: =VLOOKUP(X29,'Updating-Scoring'!$C$2:$D$7,2,TRUE) -> 2 - Minor signal | F29: =WEEKNUM(G29,2) -> 14 | G29: 46111 | H29: OpenClaw khiến 30 năm kinh nghiệm Excel trở nên vô nghĩa | I29: 46104 | J29: Market Pulse | K29: Quốc tế | L29: Technology | M29: AI/ Gen AI | N29: =L29&" | "&M29 -> Technology | AI/ Gen AI | O29: AI Agent thay thế kỹ năng văn phòng — 'AI Delegation' là năng lực cốt lõi mới | P29: AI agent như OpenClaw tự thực hiện mọi thao tác trên máy tính thay người dùng, khiến kỹ năng 'thành thạo tin học văn phòng' mất giá trị. Kỹ năng cốt lõi mới là 'AI Delegation' - khả năng giao việc, định nghĩa nhiệm vụ và điều phối AI agent hiệu quả. | S29: OpenClaw; AI agent; kỹ năng văn phòng; Excel; AI delegation; tương lai công việc; automation | T29: 1 | U29: 3 | V29: 1 | W29: 4 | X29: =IF(G29<DATE(2026,4,30),T29*$T$1+U29*$U$1+V29*$V$1+W29*$W$1,T29*$T$2+U29*$U$2) -> 1.95
A30: =ROW()-3 -> 27 | B30: https://genk.vn/mot-doanh-nghiep-cong-nghe-viet-lot-top-35-nha-cung-cap-dich-vu-phat-trien-ung-dung-ai-toan-cau-16526240315321592.chn | C30: =HYPERLINK(B30,O30) -> FPT lọt Top 35 AI App Development toàn cầu — Đối tác AI nội địa tiềm năng | D30: GenK | E30: =VLOOKUP(X30,'Updating-Scoring'!$C$2:$D$7,2,TRUE) -> 2 - Minor signal | F30: =WEEKNUM(G30,2) -> 14 | G30: 46111 | H30: Một doanh nghiệp công nghệ Việt lọt Top 35 nhà cung cấp dịch vụ phát triển ứng dụng AI toàn cầu | I30: 46105 | J30: Market Pulse | K30: Trong nước | L30: Technology | M30: AI/ Gen AI | N30: =L30&" | "&M30 -> Technology | AI/ Gen AI | O30: FPT lọt Top 35 AI App Development toàn cầu — Đối tác AI nội địa tiềm năng | P30: FPT Software lần đầu được Everest Group xếp hạng Major Contender trong báo cáo AI Application Development Services PEAK Matrix 2025, nằm trong top 35 toàn cầu. FPT nổi bật với nền tảng IvyHub (agentic AI) và hợp tác với NVIDIA, IBM, Meta. | S30: FPT; FPT Software; AI; Everest Group; IvyHub; agentic AI; NVIDIA; AI application development | T30: 4 | U30: 2 | V30: 2 | W30: 3 | X30: =IF(G30<DATE(2026,4,30),T30*$T$1+U30*$U$1+V30*$V$1+W30*$W$1,T30*$T$2+U30*$U$2) -> 2.95
A31: =ROW()-3 -> 28 | B31: https://genk.vn/openai-dot-ngot-khai-tu-ung-dung-sora-sau-4-thang-disney-ngo-ngang-khi-thoa-thuan-1-ty-usd-bay-mau-165260325083415473.chn | C31: =HYPERLINK(B31,O31) -> OpenAI đóng cửa Sora, xoay trục B2B & IPO — Tái định vị AI Product Strategy | D31: GenK | E31: =VLOOKUP(X31,'Updating-Scoring'!$C$2:$D$7,2,TRUE) -> 2 - Minor signal | F31: =WEEKNUM(G31,2) -> 14 | G31: 46111 | H31: OpenAI đột ngột khai tử công cụ tạo video Sora sau 4 tháng, Disney 'ngỡ ngàng' | I31: 46106 | J31: Market Pulse | K31: Quốc tế | L31: Economic | M31: M&A activity | N31: =L31&" | "&M31 -> Economic | M&A activity | O31: OpenAI đóng cửa Sora, xoay trục B2B & IPO — Tái định vị AI Product Strategy | P31: OpenAI đột ngột đóng cửa Sora chỉ 4 tháng sau khi ra mắt, làm thất bại thỏa thuận 1 tỷ USD với Disney. Lý do: tài nguyên tính toán khổng lồ và tập trung ưu tiên cho sản phẩm doanh nghiệp và lập trình trước thềm IPO. Sự kiện này cho thấy AI video generation chưa đủ kinh tế để duy trì. | S31: OpenAI; Sora; Disney; video AI; IPO; khai tử sản phẩm; AI video generation | T31: 3 | U31: 3 | V31: 3 | W31: 3 | X31: =IF(G31<DATE(2026,4,30),T31*$T$1+U31*$U$1+V31*$V$1+W31*$W$1,T31*$T$2+U31*$U$2) -> 3
A32: =ROW()-3 -> 29 | B32: https://genk.vn/tin-vui-cho-35-ty-nguoi-dung-google-chrome-16526032408203803.chn | C32: =HYPERLINK(B32,O32) -> Google Chrome: Gemini Nano Anti-Phishing On-device — AI Security tích hợp hệ thống | D32: GenK | E32: =VLOOKUP(X32,'Updating-Scoring'!$C$2:$D$7,2,TRUE) -> 2 - Minor signal | F32: =WEEKNUM(G32,2) -> 14 | G32: 46111 | H32: Tin vui cho 3,5 tỷ người dùng Google Chrome | I32: 46105 | J32: Market Pulse | K32: Quốc tế | L32: Technology | M32: AI/ Gen AI | N32: =L32&" | "&M32 -> Technology | AI/ Gen AI | O32: Google Chrome: Gemini Nano Anti-Phishing On-device — AI Security tích hợp hệ thống | P32: Google tích hợp Gemini Nano vào Chrome và Android để phát hiện lừa đảo theo thời gian thực, chặn 20x trang web lừa đảo so với trước. AI phân tích nội dung trang web ngay trên thiết bị, tăng gấp đôi bảo vệ so với chế độ tiêu chuẩn. | S32: Google Chrome; Gemini Nano; bảo mật; anti-phishing; AI security; Android | T32: 3 | U32: 3 | V32: 3 | W32: 3 | X32: =IF(G32<DATE(2026,4,30),T32*$T$1+U32*$U$1+V32*$V$1+W32*$W$1,T32*$T$2+U32*$U$2) -> 3
A33: =ROW()-3 -> 30 | B33: https://luatvietnam.vn/thue/thong-tu-18-2026-tt-btc-quy-dinh-ho-so-thu-tuc-quan-ly-thue-cho-ho-kinh-doanh-427777-d1.html | C33: =HYPERLINK(B33,O33) -> Trước 20/4/2026, HKD phải thông báo tài khoản ngân hàng | D33: Luật Việt Nam | E33: =VLOOKUP(X33,'Updating-Scoring'!$C$2:$D$7,2,TRUE) -> 2 - Minor signal | F33: =WEEKNUM(G33,2) -> 14 | G33: 46111 | H33: Trước 20/4/2026, HKD phải thông báo tài khoản ngân hàng | I33: 46086 | J33: Market Pulse | K33: Trong nước | L33: Legal | M33: Fintech/ Wallet | N33: =L33&" | "&M33 -> Legal | Fintech/ Wallet | O33: Trước 20/4/2026, HKD phải thông báo tài khoản ngân hàng | P33: Thông tư 18/2026/TT-BTC (hiệu lực 5/3/2026) quy định hộ kinh doanh phải thông báo số tài khoản ngân hàng hoặc số hiệu ví điện tử cho cơ quan thuế (deadline 20/4/2026 cho doanh thu ≤500 triệu) | S33: Thông tư 18/2026; ví điện tử; thuế hộ kinh doanh; số tài khoản; Bộ Tài chính; kê khai thuế | T33: 2 | U33: 5 | V33: 2 | W33: 1 | X33: =IF(G33<DATE(2026,4,30),T33*$T$1+U33*$U$1+V33*$V$1+W33*$W$1,T33*$T$2+U33*$U$2) -> 2.6
A34: =ROW()-3 -> 31 | B34: https://luatvietnam.vn/tai-chinh/thong-tu-30-2025-tt-nhnn-sua-doi-thong-tu-15-2024-ve-dich-vu-thanh-toan-khong-dung-tien-mat-413828-d1.html | C34: =HYPERLINK(B34,O34) -> Các ngân hàng sẽ chấm dứt dịch vụ đặt biệt danh cho tài khoản từ 01/04/2026 | D34: Luật Việt Nam | E34: =VLOOKUP(X34,'Updating-Scoring'!$C$2:$D$7,2,TRUE) -> 3 - Market signal | F34: =WEEKNUM(G34,2) -> 14 | G34: 46111 | H34: Thông tư 30/2025/TT-NHNN sửa đổi về dịch vụ thanh toán không dùng tiền mặt | I34: 45930 | J34: Market Pulse | K34: Trong nước | L34: Legal | M34: Payment | N34: =L34&" | "&M34 -> Legal | Payment | O34: Các ngân hàng sẽ chấm dứt dịch vụ đặt biệt danh cho tài khoản từ 01/04/2026 | P34: Từ 1/4/2026, tất cả tài khoản thanh toán phải đồng nhất tên thật theo CCCD/Thẻ căn cước; ngân hàng sẽ chấm dứt hoàn toàn dịch vụ nickname/iNick để tránh nhầm lẫn và tăng minh bạch. Các ngân hàng phải kiểm tra & hiển thị đầy đủ tên thật + số tài khoản trên mọi chứng từ và giao dịch. Quy định mới nhằm giảm rủi ro chuyển nhầm tiền, tăng chuẩn KYC và an toàn hệ thống thanh toán không tiền mặt. Thông tư cũng yêu cầu ngân hàng tố giác giao dịch có dấu hiệu tội phạm, cập nhật quy trình tra soát cho khách hàng | Q34: 46113 | S34: Thông tư 30/2025; NHNN; thanh toán không dùng tiền mặt; tên thật; tài khoản; CCCD; ngân hàng | T34: 3 | U34: 5 | V34: 3 | W34: 1 | X34: =IF(G34<DATE(2026,4,30),T34*$T$1+U34*$U$1+V34*$V$1+W34*$W$1,T34*$T$2+U34*$U$2) -> 3.2
A35: =ROW()-3 -> 32 | B35: https://dantri.com.vn/cong-nghe/ios-27-se-giup-tro-ly-ao-siri-lot-xac-20260325124237776.htm | C35: =HYPERLINK(B35,O35) -> Apple iOS 27: Siri tái thiết với AI — Cuộc đua AI Assistant toàn diện leo thang | D35: Dân Trí | E35: =VLOOKUP(X35,'Updating-Scoring'!$C$2:$D$7,2,TRUE) -> 4 - Strategic shift | F35: =WEEKNUM(G35,2) -> 14 | G35: 46111 | H35: iOS 27 sẽ giúp trợ lý ảo Siri 'lột xác' | I35: 46106 | J35: Market Pulse | K35: Quốc tế | L35: Technology | M35: AI/ Gen AI | N35: =L35&" | "&M35 -> Technology | AI/ Gen AI | O35: Apple iOS 27: Siri tái thiết với AI — Cuộc đua AI Assistant toàn diện leo thang | P35: Apple dự kiến nâng cấp Siri trên iOS 27 với AI mạnh hơn, chuyển từ trợ lý phản hồi sang chủ động hỗ trợ người dùng. Đây là bước tiến nhằm cạnh tranh trực tiếp với các AI assistant như ChatGPT và Gemini. Xu hướng assistant trở thành interface chính của hệ điều hành ngày càng rõ rệt. | S35: iOS 27; Siri; Apple Intelligence; AI assistant; trợ lý ảo; Apple; WWDC 2026 | T35: 4 | U35: 3 | V35: 3 | W35: 4 | X35: =IF(G35<DATE(2026,4,30),T35*$T$1+U35*$U$1+V35*$V$1+W35*$W$1,T35*$T$2+U35*$U$2) -> 3.55
A36: =ROW()-3 -> 33 | B36: https://techcrunch.com/2026/03/25/apple-overhauls-its-app-developer-platform-with-100-new-metrics-more-tools/ | C36: =HYPERLINK(B36,O36) -> Apple App Store 100+ Metrics & Cohort API — Nâng cấp hạ tầng phân tích App | D36: Tech Crunch | E36: =VLOOKUP(X36,'Updating-Scoring'!$C$2:$D$7,2,TRUE) -> 4 - Strategic shift | F36: =WEEKNUM(G36,2) -> 14 | G36: 46111 | H36: Apple overhauls its app developer platform with 100 new metrics, more tools | I36: 46106 | J36: Market Pulse | K36: Quốc tế | L36: Technology | M36: Open banking/ API | N36: =L36&" | "&M36 -> Technology | Open banking/ API | O36: Apple App Store 100+ Metrics & Cohort API — Nâng cấp hạ tầng phân tích App | P36: Apple đại tu App Store Connect với hơn 100 chỉ số mới về monetization, subscription, cohort analytics và peer group benchmarks. Dữ liệu có thể export qua API và được bảo vệ bằng differential privacy, giúp developer tối ưu chiến lược tăng trưởng. | S36: Apple; App Store Connect; developer metrics; subscription analytics; cohort; App Store | T36: 4 | U36: 4 | V36: 3 | W36: 2 | X36: =IF(G36<DATE(2026,4,30),T36*$T$1+U36*$U$1+V36*$V$1+W36*$W$1,T36*$T$2+U36*$U$2) -> 3.5
A37: =ROW()-3 -> 34 | B37: https://techcrunch.com/2026/03/24/apple-music-partners-with-ticketmaster-to-power-its-concert-discovery-feature/ | C37: =HYPERLINK(B37,O37) -> Apple Music × Ticketmaster: Concert Discovery tích hợp — Mô hình Ecosystem Ticketing | D37: Tech Crunch | E37: =VLOOKUP(X37,'Updating-Scoring'!$C$2:$D$7,2,TRUE) -> 2 - Minor signal | F37: =WEEKNUM(G37,2) -> 14 | G37: 46111 | H37: Apple Music partners with Ticketmaster to power its concert discovery feature | I37: 46105 | J37: Market Pulse | K37: Quốc tế | L37: Economic | M37: M&A activity | N37: =L37&" | "&M37 -> Economic | M&A activity | O37: Apple Music × Ticketmaster: Concert Discovery tích hợp — Mô hình Ecosystem Ticketing | P37: Apple Music hợp tác với Ticketmaster và Bandsintown để tích hợp khám phá concert dựa trên thói quen nghe nhạc. Mở rộng phủ sóng sang Maps, Shazam, Photos iOS 26. Cạnh tranh trực tiếp với Spotify-SeatGeek. | S37: Apple Music; Ticketmaster; concert discovery; live events; Bandsintown; Spotify; tickets | T37: 4 | U37: 2 | V37: 3 | W37: 1 | X37: =IF(G37<DATE(2026,4,30),T37*$T$1+U37*$U$1+V37*$V$1+W37*$W$1,T37*$T$2+U37*$U$2) -> 2.85
A38: =ROW()-3 -> 35 | B38: https://techcrunch.com/2026/03/24/tiktok-ads-are-about-to-get-a-tad-more-disruptive/ | C38: =HYPERLINK(B38,O38) -> TikTok Logo Takeover & Prime Time Ads — Định dạng quảng cáo thế hệ mới | D38: Tech Crunch | E38: =VLOOKUP(X38,'Updating-Scoring'!$C$2:$D$7,2,TRUE) -> 4 - Strategic shift | F38: =WEEKNUM(G38,2) -> 14 | G38: 46111 | H38: TikTok ads are about to get a tad more disruptive | I38: 46105 | J38: Market Pulse | K38: Quốc tế | L38: Social | M38: Ads strategy | N38: =L38&" | "&M38 -> Social | Ads strategy | O38: TikTok Logo Takeover & Prime Time Ads — Định dạng quảng cáo thế hệ mới | P38: TikTok ra mắt 3 định dạng quảng cáo mới: Logo Takeover (co-brand logo ngay khi mở app), Prime Time (3 quảng cáo liên tiếp trong 15 phút), Top Reach (TopView + TopFeed). Cùng với đó là công cụ Pulse Mentions gắn quảng cáo vào xu hướng nội dung. | S38: TikTok; quảng cáo; Logo Takeover; Prime Time; Top Reach; Pulse Mentions; ad format | T38: 5 | U38: 3 | V38: 4 | W38: 1 | X38: =IF(G38<DATE(2026,4,30),T38*$T$1+U38*$U$1+V38*$V$1+W38*$W$1,T38*$T$2+U38*$U$2) -> 3.7
A39: =ROW()-3 -> 36 | B39: https://vneconomy.vn/techconnect/esports-nations-cup-2026-cong-bo-viresa-la-doi-tac-quoc-gia-tai-viet-nam.htm | C39: =HYPERLINK(B39,O39) -> VIRESA là Đối tác ENC 2026 — Esports Quốc gia VN gia nhập mạng lưới toàn cầu | D39: VNEconomy | E39: =VLOOKUP(X39,'Updating-Scoring'!$C$2:$D$7,2,TRUE) -> 1 - Noise | F39: =WEEKNUM(G39,2) -> 14 | G39: 46111 | H39: Esports Nations Cup 2026 công bố VIRESA là Đối tác Quốc gia tại Việt Nam | I39: 46107 | J39: Market Pulse | K39: Trong nước | L39: Social | M39: Digital lifestyle | N39: =L39&" | "&M39 -> Social | Digital lifestyle | O39: VIRESA là Đối tác ENC 2026 — Esports Quốc gia VN gia nhập mạng lưới toàn cầu | P39: Esports Foundation bổ nhiệm VIRESA làm Đối tác Quốc gia tại Việt Nam cho giải ENC 2026 tại Riyadh (2-29/11/2026). VIRESA sẽ thành lập đội tuyển quốc gia ở nhiều bộ môn và tham gia mạng lưới 100+ quốc gia. | S39: VIRESA; esports; Esports Nations Cup 2026; ENC; đội tuyển quốc gia; gaming; Riyadh | T39: 1 | U39: 1 | V39: 1 | W39: 1 | X39: =IF(G39<DATE(2026,4,30),T39*$T$1+U39*$U$1+V39*$V$1+W39*$W$1,T39*$T$2+U39*$U$2) -> 1
A40: =ROW()-3 -> 37 | B40: https://vneconomy.vn/techconnect/con-sot-ai-agent-dang-thuc-day-cuoc-dua-ha-tang-tinh-toan-toan-cau.htm | C40: =HYPERLINK(B40,O40) -> AI Agent x6400% Token Consumption — Cuộc đua Compute & Hạ tầng AI toàn cầu | D40: VNEconomy | E40: =VLOOKUP(X40,'Updating-Scoring'!$C$2:$D$7,2,TRUE) -> 2 - Minor signal | F40: =WEEKNUM(G40,2) -> 14 | G40: 46111 | H40: Cơn sốt AI Agent đang thúc đẩy cuộc đua hạ tầng tính toán toàn cầu | I40: 46106 | J40: Market Pulse | K40: Trung Quốc | L40: Technology | M40: Cloud/ Infrastructure | N40: =L40&" | "&M40 -> Technology | Cloud/ Infrastructure | O40: AI Agent x6400% Token Consumption — Cuộc đua Compute & Hạ tầng AI toàn cầu | P40: AI agent đang khiến tiêu thụ token tăng 6.400% so với AI truyền thống, tạo ra làn sóng đầu tư hạ tầng tính toán toàn cầu. Hong Kong tăng tốc đầu tư AI computing, lợi thế cạnh tranh mới là chi phí token thấp nhất chứ không phải năng lực tính toán nhiều nhất. | S40: AI agent; hạ tầng tính toán; compute; token; Hong Kong; GPU; Moore Threads; AI infrastructure | T40: 2 | U40: 4 | V40: 2 | W40: 4 | X40: =IF(G40<DATE(2026,4,30),T40*$T$1+U40*$U$1+V40*$V$1+W40*$W$1,T40*$T$2+U40*$U$2) -> 2.8
A41: =ROW()-3 -> 38 | B41: https://vnexpress.net/sap-ap-dung-quy-chuan-an-toan-cho-smartphone-tai-viet-nam-5054879.html | C41: =HYPERLINK(B41,O41) -> VN áp chuẩn SAR Smartphone từ 1/7 — Quy định thiết bị di động & thị trường | D41: VNExpress | E41: =VLOOKUP(X41,'Updating-Scoring'!$C$2:$D$7,2,TRUE) -> 2 - Minor signal | F41: =WEEKNUM(G41,2) -> 14 | G41: 46111 | H41: Sắp áp dụng quy chuẩn an toàn cho smartphone tại Việt Nam | I41: 46108 | J41: Market Pulse | K41: Trong nước | L41: Legal | M41: New policy | N41: =L41&" | "&M41 -> Legal | New policy | O41: VN áp chuẩn SAR Smartphone từ 1/7 — Quy định thiết bị di động & thị trường | P41: Từ 1/7/2026, điện thoại di động bán tại Việt Nam phải tuân thủ quy chuẩn SAR (mức hấp thụ sóng vô tuyến). Thông tư 19/2024 có hiệu lực 15/2/2025 cho thử nghiệm, áp dụng bắt buộc từ 1/7 với smartphone, tablet/laptop từ 1/7/2027. | S41: SAR; quy chuẩn smartphone; Bộ KHCN; sóng vô tuyến; điện thoại di động; Apple; Samsung; quy chuẩn kỹ thuật | T41: 2 | U41: 3 | V41: 2 | W41: 1 | X41: =IF(G41<DATE(2026,4,30),T41*$T$1+U41*$U$1+V41*$V$1+W41*$W$1,T41*$T$2+U41*$U$2) -> 2.1
A42: =ROW()-3 -> 39 | B42: https://vnexpress.net/viet-nam-quan-ly-ai-the-nao-theo-luat-moi-5054752.html | C42: =HYPERLINK(B42,O42) -> Luật AI VN 3/2026: Khung pháp lý AI sớm nhất khu vực — Tác động toàn hệ thống | D42: VNExpress | E42: =VLOOKUP(X42,'Updating-Scoring'!$C$2:$D$7,2,TRUE) -> 2 - Minor signal | F42: =WEEKNUM(G42,2) -> 14 | G42: 46111 | H42: Việt Nam quản lý AI thế nào theo luật mới? | I42: 46107 | J42: Market Pulse | K42: Trong nước | L42: Legal | M42: New policy | N42: =L42&" | "&M42 -> Legal | New policy | O42: Luật AI VN 3/2026: Khung pháp lý AI sớm nhất khu vực — Tác động toàn hệ thống | P42: Luật Trí tuệ nhân tạo của Việt Nam có hiệu lực từ tháng 3/2026, đưa Việt Nam vào nhóm ít quốc gia sớm có khung pháp lý riêng về AI. Luật phân loại rủi ro AI, quy định trách nhiệm cung cấp AI, bảo vệ dữ liệu và thúc đẩy phát triển AI quốc gia. | S42: Luật AI; trí tuệ nhân tạo; Việt Nam; khung pháp lý; AI regulation; quản lý AI | T42: 2 | U42: 3 | V42: 3 | W42: 4 | X42: =IF(G42<DATE(2026,4,30),T42*$T$1+U42*$U$1+V42*$V$1+W42*$W$1,T42*$T$2+U42*$U$2) -> 2.75
A43: =ROW()-3 -> 40 | B43: https://www.bloomberg.com/news/articles/2026-03-26/google-gemini-adds-tool-to-make-it-easier-to-switch-from-chatgpt?srnd=phx-technology-consumer-tech | C43: =HYPERLINK(B43,O43) -> Google Gemini Import ChatGPT History — Chiến tranh giữ User AI escalates | D43: Bloomberg | E43: =VLOOKUP(X43,'Updating-Scoring'!$C$2:$D$7,2,TRUE) -> 2 - Minor signal | F43: =WEEKNUM(G43,2) -> 14 | G43: 46111 | H43: Google Gemini adds tool to make it easier to switch from ChatGPT | I43: 46107 | J43: Market Pulse | K43: Quốc tế | L43: Technology | M43: AI/ Gen AI | N43: =L43&" | "&M43 -> Technology | AI/ Gen AI | O43: Google Gemini Import ChatGPT History — Chiến tranh giữ User AI escalates | P43: Google ra mắt 'switching tools' cho Gemini: nhập lịch sử chat từ ChatGPT/Claude qua file ZIP và chuyển memories/preferences. Gemini đạt 750 triệu MAU tháng 2/2026, vẫn kém ChatGPT 900 triệu WAU. Đây là chiến lược giảm switching cost để gia tăng thị phần. | S43: Google Gemini; ChatGPT; switching tools; AI migration; chat history import; memory transfer | T43: 2 | U43: 4 | V43: 2 | W43: 4 | X43: =IF(G43<DATE(2026,4,30),T43*$T$1+U43*$U$1+V43*$V$1+W43*$W$1,T43*$T$2+U43*$U$2) -> 2.8
A44: =ROW()-3 -> 41 | B44: https://www.bloomberg.com/news/articles/2026-03-23/samsung-phones-can-now-share-with-iphones-using-apple-s-airdrop-protocol?srnd=phx-technology-consumer-tech | C44: =HYPERLINK(B44,O44) -> Samsung Galaxy S26 hỗ trợ AirDrop — Interoperability Android↔iOS tiến xa | D44: Bloomberg | E44: =VLOOKUP(X44,'Updating-Scoring'!$C$2:$D$7,2,TRUE) -> 2 - Minor signal | F44: =WEEKNUM(G44,2) -> 14 | G44: 46111 | H44: Samsung phones can now share with iPhones using Apple's AirDrop protocol | I44: 46104 | J44: Market Pulse | K44: Quốc tế | L44: Technology | M44: Open banking/ API | N44: =L44&" | "&M44 -> Technology | Open banking/ API | O44: Samsung Galaxy S26 hỗ trợ AirDrop — Interoperability Android↔iOS tiến xa | P44: Samsung Galaxy S26 series tích hợp giao thức AirDrop của Apple (qua AWDL) vào Quick Share, cho phép chia sẻ file trực tiếp với iPhone/iPad/Mac không cần app bên thứ ba. Roll out từ Hàn Quốc ngày 23/3, sau đó toàn cầu. | S44: Samsung; Galaxy S26; AirDrop; Quick Share; Apple; interoperability; AWDL; iOS Android | T44: 3 | U44: 3 | V44: 3 | W44: 2 | X44: =IF(G44<DATE(2026,4,30),T44*$T$1+U44*$U$1+V44*$V$1+W44*$W$1,T44*$T$2+U44*$U$2) -> 2.85
A45: =ROW()-3 -> 42 | B45: https://www.techinasia.com/solving-mid-market-finance-pain-with-ai-agents | C45: =HYPERLINK(B45,O45) -> AI Agent giải Finance Pain Mid-Market SEA — Cơ hội Embedded Finance tích hợp | D45: Techinasia | E45: =VLOOKUP(X45,'Updating-Scoring'!$C$2:$D$7,2,TRUE) -> 2 - Minor signal | F45: =WEEKNUM(G45,2) -> 14 | G45: 46111 | H45: Solving mid-market finance pain with AI agents | I45: 46106 | J45: Market Pulse | K45: SEA | L45: Technology | M45: AI/ Gen AI | N45: =L45&" | "&M45 -> Technology | AI/ Gen AI | O45: AI Agent giải Finance Pain Mid-Market SEA — Cơ hội Embedded Finance tích hợp | P45: Bài viết phân tích cách AI agent đang giải quyết điểm đau tài chính cho doanh nghiệp tầm trung tại SEA: tự động hóa reconciliation, cash flow forecasting, báo cáo tài chính. Nhấn mạnh cơ hội thị trường lớn khi SME ở SEA còn thiếu giải pháp tài chính tích hợp. | S45: AI agent; fintech; mid-market; SME; tài chính doanh nghiệp; SEA; automation finance | T45: 2 | U45: 3 | V45: 2 | W45: 4 | X45: =IF(G45<DATE(2026,4,30),T45*$T$1+U45*$U$1+V45*$V$1+W45*$W$1,T45*$T$2+U45*$U$2) -> 2.55
A46: =ROW()-3 -> 43 | B46: https://www.techinasia.com/news/fomo-pay-launches-ai-soundbox-for-unified-payments | C46: =HYPERLINK(B46,O46) -> FOMO Pay ra mắt AI Soundbox – Hợp nhất thanh toán & mở đường cho “agentic commerce” | D46: Techinasia | E46: =VLOOKUP(X46,'Updating-Scoring'!$C$2:$D$7,2,TRUE) -> 4 - Strategic shift | F46: =WEEKNUM(G46,2) -> 14 | G46: 46111 | H46: FOMO Pay launches AI Soundbox for unified payments | I46: 46106 | J46: Market Pulse | K46: SEA | L46: Technology | M46: Payment | N46: =L46&" | "&M46 -> Technology | Payment | O46: FOMO Pay ra mắt AI Soundbox – Hợp nhất thanh toán & mở đường cho “agentic commerce” | P46: FOMO Pay giới thiệu AI Soundbox, thiết bị POS hợp nhất thẻ, QR, e‑wallets và stablecoin vào một đầu chấp nhận duy nhất, giúp merchant xử lý thanh toán liền mạch thay vì dùng nhiều thiết bị rời rạc Soundbox được tích hợp micro và lớp AI merchant‑intelligence đang phát triển, cho phép chủ cửa hàng truy vấn dữ liệu bán hàng bằng ngôn ngữ tự nhiên trong tương lai. Sản phẩm thể hiện chiến lược của FOMO Pay: trở thành nền tảng thanh toán thế hệ mới hỗ trợ cả off‑chain & on‑chain, đáp ứng xu hướng AI agents tự động thực hiện giao dịch trong thương mại | S46: FOMO Pay; AI Soundbox; payment terminal; QR payment; stablecoin; Singapore fintech; merchant intelligence | T46: 5 | U46: 4 | V46: 3 | W46: 4 | X46: =IF(G46<DATE(2026,4,30),T46*$T$1+U46*$U$1+V46*$V$1+W46*$W$1,T46*$T$2+U46*$U$2) -> 4.2
... A52: =ROW()-3 -> 49 | B52: https://www.techinasia.com/news/alibaba-net-income-drops-66-quick-commerce-investment-rises | C52: =HYPERLINK(B52,O52) -> Alibaba lợi nhuận -66%, đổ vốn Quick Commerce — Dịch chuyển mô hình e-commerce | D52: Techinasia | E52: =VLOOKUP(X52,'Updating-Scoring'!$C$2:$D$7,2,TRUE) -> 3 - Market signal | F52: =WEEKNUM(G52,2) -> 14 | G52: 46111 | H52: Alibaba net income drops 66%, quick commerce investment rises | I52: 46106 | J52: Market Pulse | K52: Trung Quốc | L52: Economic | M52: Market growth/market size | N52: =L52&" | "&M52 -> Economic | Market growth/market size | O52: Alibaba lợi nhuận -66%, đổ vốn Quick Commerce — Dịch chuyển mô hình e-commerce | P52: Alibaba báo cáo lợi nhuận ròng giảm 66% do tăng đầu tư vào quick commerce (giao hàng nhanh). Chiến lược này nhằm cạnh tranh với Pinduoduo và JD.com trong phân khúc giao hàng 30 phút. Tín hiệu dịch chuyển mô hình kinh doanh từ marketplace sang logistics tích hợp. | S52: Alibaba; net income; quick commerce; giao hàng nhanh; Pinduoduo; JD.com; China e-commerce | T52: 3 | U52: 4 | V52: 4 | W52: 2 | X52: =IF(G52<DATE(2026,4,30),T52*$T$1+U52*$U$1+V52*$V$1+W52*$W$1,T52*$T$2+U52*$U$2) -> 3.3
A53: =ROW()-3 -> 50 | B53: https://www.momo.vn/tin-tuc/thong-bao/ban-tin-gop-y-va-tinh-nang-moi-thang-2-2026-8554 | C53: =HYPERLINK(B53,O53) -> MoMo phát triển tính năng mới trong tháng 2 nhằm cải thiện trải nghiệm người dùng | D53: MoMo Website | E53: =VLOOKUP(X53,'Updating-Scoring'!$C$2:$D$7,2,TRUE) -> 4 - Strategic shift | F53: =WEEKNUM(G53,2) -> 14 | G53: 46111 | H53: Bản tin Góp ý và Tính năng mới tháng 2/2026 | I53: 46093 | J53: Players Movement | K53: MoMo | L53: Feature | M53: New feature | N53: =L53&" | "&M53 -> Feature | New feature | O53: MoMo phát triển tính năng mới trong tháng 2 nhằm cải thiện trải nghiệm người dùng | P53: MoMo ra mắt QR thanh toán quốc tế (quét QR nước ngoài bằng VND, tỷ giá real-time minh bạch) tại Bangkok, Seoul và các thị trường SEA. Tích hợp thêm AirAsia + Scoot vào MoMo Travel. Đây là dấu mốc cross-border payment đầu tiên của MoMo. Ngoài ra MoMo cũng đang triển khai những tính năng mới sắp ra mắt: - Tự động nạp tiền điện thoại - Tự động gia hạn gói cước - Chuyển đổi giao dịch trả sau thành trả góp | Q53: 46054 | S53: QR quốc tế; cross-border payment; AirAsia; Scoot; tỷ giá; VND; Bangkok; Seoul; MoMo Travel | T53: 5 | U53: 2 | V53: 5 | W53: 2 | X53: =IF(G53<DATE(2026,4,30),T53*$T$1+U53*$U$1+V53*$V$1+W53*$W$1,T53*$T$2+U53*$U$2) -> 3.8
A54: =ROW()-3 -> 51 | B54: https://www.momo.vn/tin-tuc/khuyen-mai/ban-moi-nhap-ma-chonmomo-co-qua-500000d-giam-8225 | C54: =HYPERLINK(B54,O54) -> Ví trả sau: MoMo Mã VITRASAU: Onboarding Bạn Mới gắn Ví Trả Sau — Bundle quà 500k + thưởng 1 triệu | D54: MoMo Website | E54: =VLOOKUP(X54,'Updating-Scoring'!$C$2:$D$7,2,TRUE) -> 3 - Market signal | F54: =WEEKNUM(G54,2) -> 14 | G54: 46111 | H54: Bạn mới nhập mã VITRASAU: Có quà 500.000đ giảm nhiều dịch vụ, thêm tiền thưởng đến 1 triệu | I54: 45789 | J54: Players Movement | K54: MoMo | L54: Marketing | M54: User acquisition | N54: =L54&" | "&M54 -> Marketing | User acquisition | O54: Ví trả sau: MoMo Mã VITRASAU: Onboarding Bạn Mới gắn Ví Trả Sau — Bundle quà 500k + thưởng 1 triệu | P54: Chương trình dành cho KH lần đầu tiên liên kết NH x MoMo. Sau khi nhập mã VITRASAU, KH sẽ nhận được bộ quà 500k (voucher giảm giá thanh toán, ví trả sau và các dịch vụ trên MoMo) | Q54: 46082 | R54: 46112 | S54: VITRASAU; bạn mới; user acquisition; Ví Trả Sau; BNPL; onboarding; voucher bundle | T54: 4 | U54: 2 | V54: 5 | W54: 2 | X54: =IF(G54<DATE(2026,4,30),T54*$T$1+U54*$U$1+V54*$V$1+W54*$W$1,T54*$T$2+U54*$U$2) -> 3.4 | Y54: Thanh toán | Z54: Liên kết tài khoản ngân hàng
A55: =ROW()-3 -> 52 | B55: https://www.momo.vn/tin-tuc/khuyen-mai/don-hoa-no-san-deal-xin-giam-den-500000d-tren-8588 | C55: =HYPERLINK(B55,O55) -> MoMo Travel Deal Tháng 3: Giảm 500k — Duy trì nhịp khuyến mãi Travel hàng tháng | D55: MoMo Website | E55: =VLOOKUP(X55,'Updating-Scoring'!$C$2:$D$7,2,TRUE) -> 2 - Minor signal | F55: =WEEKNUM(G55,2) -> 14 | G55: 46111 | H55: Đón hoa nở - Săn deal xịn giảm đến 500.000đ trên MoMo Travel | I55: 46106 | J55: Players Movement | K55: MoMo | L55: Marketing | M55: User engagement | N55: =L55&" | "&M55 -> Marketing | User engagement | O55: MoMo Travel Deal Tháng 3: Giảm 500k — Duy trì nhịp khuyến mãi Travel hàng tháng | P55: Chương trình khuyến mãi định kỳ của MoMo Travel với deal giảm đến 500k áp dụng cho vé máy bay, xe khách, khách sạn. Chiến lược duy trì frequency tương tác trên travel vertical. | Q55: 46098 | S55: MoMo Travel; deal tháng 3; vé máy bay; khách sạn; giảm giá; travel promotion | T55: 3 | U55: 2 | V55: 3 | W55: 2 | X55: =IF(G55<DATE(2026,4,30),T55*$T$1+U55*$U$1+V55*$V$1+W55*$W$1,T55*$T$2+U55*$U$2) -> 2.6 | Y55: Thanh toán | Z55: Du lịch đi lại
A56: =ROW()-3 -> 53 | B56: https://www.momo.vn/tin-tuc/thong-bao/momo-ra-mat-tinh-nang-cap-nhat-so-dien-thoai-8571 | C56: =HYPERLINK(B56,O56) -> MoMo ra mắt tính năng cập nhật số điện thoại | D56: MoMo Website | E56: =VLOOKUP(X56,'Updating-Scoring'!$C$2:$D$7,2,TRUE) -> 4 - Strategic shift | F56: =WEEKNUM(G56,2) -> 14 | G56: 46111 | H56: MoMo ra mắt tính năng 'Cập nhật số điện thoại': Chuyển tài khoản MoMo sang số điện thoại mới | I56: 46099 | J56: Players Movement | K56: MoMo | L56: Feature | M56: New feature | N56: =L56&" | "&M56 -> Feature | New feature | O56: MoMo ra mắt tính năng cập nhật số điện thoại | P56: MoMo ra mắt tính năng cập nhật số điện thoại tự động (hoàn tất dưới 1 phút): giữ nguyên số dư, lịch sử 6 tháng, eKYC/NFC data khi đổi SIM. Bảo mật đa lớp: PIN + sinh trắc + OTP. Giải quyết pain point lớn giảm churn khi user đổi số. | Q56: 46099 | S56: cập nhật số điện thoại; đổi SIM; account migration; UX; churn reduction; eKYC; NFC; security | T56: 5 | U56: 2 | V56: 5 | W56: 2 | X56: =IF(G56<DATE(2026,4,30),T56*$T$1+U56*$U$1+V56*$V$1+W56*$W$1,T56*$T$2+U56*$U$2) -> 3.8 | Y56: VAS | Z56: Cập nhật số điện thoại tự động
A57: =ROW()-3 -> 54 | B57: https://www.momo.vn/tin-tuc/khuyen-mai/uu-dai-hoi-nhat-thang-giam-den-45k-mua-icloud-luu-8558 | C57: =HYPERLINK(B57,O57) -> MoMo × Apple Store: Giảm đến 45K mua iCloud+, lưu mọi ảnh, dữ liệu | D57: MoMo Website | E57: =VLOOKUP(X57,'Updating-Scoring'!$C$2:$D$7,2,TRUE) -> 3 - Market signal | F57: =WEEKNUM(G57,2) -> 14 | G57: 46111 | H57: Ưu đãi hội nhất tháng: Giảm đến 45k khi mua iCloud lưu trữ trên MoMo | I57: 46094 | J57: Players Movement | K57: MoMo | L57: Marketing | M57: User activation | N57: =L57&" | "&M57 -> Marketing | User activation | O57: MoMo × Apple Store: Giảm đến 45K mua iCloud+, lưu mọi ảnh, dữ liệu | P57: Ưu đãi nhằm tăng adoption việc liên kết tài khoản Apple với MoMo để biến MoMo thành PTTT mặc định cho các dịch vụ qua Apple. MoMo cung cấp ưu đãi giảm 45k khi mua gói iCloud qua MoMo: - Khách hàng lần đầu liên kết tài khoản Apple với MoMo, nhận thẻ quà giảm 20.000đ cho lần thanh toán. - Trong thời gian từ 14/02 - 22/03, nếu tổng giá trị thanh toán App Store qua MoMo đạt từ 400.000đ trở lên, bạn sẽ nhận thêm 1 thẻ quà 25.000đ để thanh toán ở tháng lần tiếp theo. | Q57: 46093 | R57: 46103 | S57: iCloud; Apple; subscription; digital services; technology partnership; App Store | T57: 4 | U57: 2 | V57: 5 | W57: 2 | X57: =IF(G57<DATE(2026,4,30),T57*$T$1+U57*$U$1+V57*$V$1+W57*$W$1,T57*$T$2+U57*$U$2) -> 3.4 | Y57: Thanh toán | Z57: Liên kết Apple Pay
A58: =ROW()-3 -> 55 | B58: https://www.momo.vn/tin-tuc/khuyen-mai/lan-dau-co-tren-momo-giam-den-45k-khi-dang-ky-8557 | C58: =HYPERLINK(B58,O58) -> MoMo x Apple Store: Giảm đến 45K khi đăng ký YouTube Premium | D58: MoMo Website | E58: =VLOOKUP(X58,'Updating-Scoring'!$C$2:$D$7,2,TRUE) -> 3 - Market signal | F58: =WEEKNUM(G58,2) -> 14 | G58: 46111 | H58: Lần đầu có trên MoMo: Giảm đến 45k khi đăng ký dịch vụ mới | I58: 46093 | J58: Players Movement | K58: MoMo | L58: Marketing | M58: User activation | N58: =L58&" | "&M58 -> Marketing | User activation | O58: MoMo x Apple Store: Giảm đến 45K khi đăng ký YouTube Premium | P58: Ưu đãi nhằm tăng adoption việc liên kết tài khoản Apple với MoMo để biến MoMo thành PTTT mặc định cho các dịch vụ qua Apple. MoMo cung cấp ưu đãi giảm 45k khi mua gói Youtube Premium in-app qua MoMo: - Khách hàng lần đầu liên kết tài khoản Apple với MoMo, nhận thẻ quà giảm 20.000đ cho lần thanh toán. - Trong thời gian từ 14/02 - 22/03, nếu tổng giá trị thanh toán App Store qua MoMo đạt từ 400.000đ trở lên, bạn sẽ nhận thêm 1 thẻ quà 25.000đ để thanh toán ở tháng lần tiếp theo. | Q58: 46093 | R58: 46103 | S58: lần đầu sử dụng; first-time; discount; user acquisition; trial; new services | T58: 4 | U58: 2 | V58: 5 | W58: 2 | X58: =IF(G58<DATE(2026,4,30),T58*$T$1+U58*$U$1+V58*$V$1+W58*$W$1,T58*$T$2+U58*$U$2) -> 3.4 | Y58: Thanh toán | Z58: Liên kết Apple Pay
A59: =ROW()-3 -> 56 | B59: https://www.momo.vn/tin-tuc/khuyen-mai/mien-phi-ngay-1-lit-xang-khi-nhan-thich-muc-tra-8561 | C59: =HYPERLINK(B59,O59) -> Miễn phí ngay 1 lít xăng khi nhấn thích mục Tra cứu phạt nguội trên MoMo | D59: MoMo Website | E59: =VLOOKUP(X59,'Updating-Scoring'!$C$2:$D$7,2,TRUE) -> 3 - Market signal | F59: =WEEKNUM(G59,2) -> 14 | G59: 46111 | H59: Miễn phí ngay 1 lít xăng khi nhận thích Mức trả sau trên MoMo | I59: 46095 | J59: Players Movement | K59: MoMo | L59: Marketing | M59: User activation | N59: =L59&" | "&M59 -> Marketing | User activation | O59: Miễn phí ngay 1 lít xăng khi nhấn thích mục Tra cứu phạt nguội trên MoMo | P59: Mini-promotion dựa trên thực tế "giá xăng tăng" kết hợp mục tiêu tăng mức độ biết tới Tra cứu phạt nguội trên MoMo từ đó thúc đẩy hành vi người dùng tính năng - Cách thức: Người dùng ấn thích tính năng Tra cứu phạt nguội - Ưu đãi: Quà tặng tương đương 1 lít xăng - HDS 1 ngày sau khi nhận ưu đãi | Q59: 46093 | R59: 46112 | S59: Ví Trả Sau; BNPL; xăng miễn phí; user activation; incentive; MoMo wallet | T59: 4 | U59: 2 | V59: 5 | W59: 2 | X59: =IF(G59<DATE(2026,4,30),T59*$T$1+U59*$U$1+V59*$V$1+W59*$W$1,T59*$T$2+U59*$U$2) -> 3.4 | Y59: VAS | Z59: Cảnh báo phạt nguội
A60: =ROW()-3 -> 57 | B60: https://www.momo.vn/tin-tuc/thong-cao-bao-chi/momo-cap-nhat-moi-nhat-ve-giai-phap-nhan-tien-8587 | C60: =HYPERLINK(B60,O60) -> MoMo cập nhật mới nhất về giải pháp nhận tiền dành cho hộ kinh doanh, hỗ trợ chuẩn hóa thông tin theo quy định mới | D60: MoMo Website | E60: =VLOOKUP(X60,'Updating-Scoring'!$C$2:$D$7,2,TRUE) -> 2 - Minor signal | F60: =WEEKNUM(G60,2) -> 14 | G60: 46111 | H60: MoMo cập nhật mới nhất về giải pháp nhận tiền dành cho hộ kinh doanh, hỗ trợ chuẩn hóa thông tin theo quy định mới | I60: 46101 | J60: Players Movement | K60: MoMo | L60: Product | M60: T&C change | N60: =L60&" | "&M60 -> Product | T&C change | O60: MoMo cập nhật mới nhất về giải pháp nhận tiền dành cho hộ kinh doanh, hỗ trợ chuẩn hóa thông tin theo quy định mới | P60: MoMo công bố Tài khoản Đối tác MoMo đáp ứng Thông tư 25/2025, TT30/2025 và TT18/2026 về định danh tài khoản. Triển khai tính năng liên kết Loa báo với tài khoản ngân hàng hộ kinh doanh từ 19/3. MoMo dự kiến tiếp tục triển khai các tính năng hỗ trợ đối tác cập nhật thông tin định danh, bao gồm việc điều chỉnh tên Tài khoản MoMo trùng với thông tin trên Giấy phép đăng ký kinh doanh (GPKD), tải tờ khai thuế với sẵn đầy đủ thông tin của hộ kinh doanh, giúp tiết kiệm thời gian và giảm bớt thao tác khi thực hiện các thủ tục, góp phần hoàn thiện hơn lớp thông tin tài khoản phục vụ hoạt động kinh doanh | Q60: 46100 | S60: hộ kinh doanh; TT30/2025; TT18/2026; Tài khoản Đối tác; định danh; compliance; Loa MoMo; tờ khai thuế | T60: 3 | U60: 2 | V60: 5 | W60: 2 | X60: =IF(G60<DATE(2026,4,30),T60*$T$1+U60*$U$1+V60*$V$1+W60*$W$1,T60*$T$2+U60*$U$2) -> 3 | Y60: HKD | Z60: Giải pháp nhận tiền
A61: =ROW()-3 -> 58 | B61: https://www.momo.vn/tin-tuc/khuyen-mai/mua-shopee-qua-tinh-nang-hoan-tien-mua-sam-hoan-8563 | C61: =HYPERLINK(B61,O61) -> MoMo × Shopee: Hoàn tiền đến 30% & tặng thêm 20K cho lần đầu đặt đơn | D61: MoMo Website | E61: =VLOOKUP(X61,'Updating-Scoring'!$C$2:$D$7,2,TRUE) -> 3 - Market signal | F61: =WEEKNUM(G61,2) -> 14 | G61: 46111 | H61: Mua Shopee qua tính năng Hoàn tiền Mua sắm - hoàn thêm tiền khi mua | I61: 46096 | J61: Players Movement | K61: MoMo | L61: Marketing | M61: User activation | N61: =L61&" | "&M61 -> Marketing | User activation | O61: MoMo × Shopee: Hoàn tiền đến 30% & tặng thêm 20K cho lần đầu đặt đơn | P61: Ưu đãi nhằm thúc đẩy adoption cho tính năng "Hoàn tiền mua sắm" của MoMo - Đối tượng: (1) lần đầu tạo đơn thông qua tính năng Hoàn Tiền Mua Sắm trên MoMo và mua hàng Shopee (2) Khách hàng cần vào thu thập thẻ quà Hoàn Tiền Mua Sắm tại mục Ưu đãi trên MoMo hoặc trong miniapp Hoàn Tiền Mua Sắm trước khi thực hiện đặt đơn - Ưu đãi: Hoàn đến 30% giá trị đơn Shopee + Tặng thêm 20.000đ cho lần đầu tạo đơn Shopee qua MoMo (10k bạn mới của Hoàn tiền và 10k cho đơn đầu tiên Shopee qua MoMo | Q61: 46096 | R61: 46112 | S61: Shopee; cashback; Hoàn tiền Mua sắm; e-commerce; merchant integration; ShopeePay | T61: 4 | U61: 2 | V61: 5 | W61: 2 | X61: =IF(G61<DATE(2026,4,30),T61*$T$1+U61*$U$1+V61*$V$1+W61*$W$1,T61*$T$2+U61*$U$2) -> 3.4 | Y61: Thanh toán | Z61: Hoàn tiền mua sắm
A62: =ROW()-3 -> 59 | B62: https://www.momo.vn/tin-tuc/khuyen-mai/uu-dai-hoi-nhat-thang-giam-den-45k-nap-game-leo-8556 | C62: =HYPERLINK(B62,O62) -> MoMo x Apple Store: Giảm đến 45K nạp game | D62: MoMo Website | E62: =VLOOKUP(X62,'Updating-Scoring'!$C$2:$D$7,2,TRUE) -> 3 - Market signal | F62: =WEEKNUM(G62,2) -> 14 | G62: 46111 | H62: Ưu đãi hội nhất tháng: Giảm đến 45k nạp game leo thang | I62: 46093 | J62: Players Movement | K62: MoMo | L62: Marketing | M62: User activation | N62: =L62&" | "&M62 -> Marketing | User activation | O62: MoMo x Apple Store: Giảm đến 45K nạp game | P62: Ưu đãi nhằm tăng adoption việc liên kết tài khoản Apple với MoMo để biến MoMo thành PTTT mặc định cho các dịch vụ qua Apple. MoMo cung cấp ưu đãi giảm 45k khi nạp game trên App Store bằng MoMo: - Khách hàng lần đầu liên kết tài khoản Apple với MoMo, nhận thẻ quà giảm 20.000đ cho lần thanh toán. - Trong thời gian từ 14/02 - 22/03, nếu tổng giá trị thanh toán App Store qua MoMo đạt từ 400.000đ trở lên, bạn sẽ nhận thêm 1 thẻ quà 25.000đ để thanh toán ở tháng lần tiếp theo. | Q62: 46093 | R62: 46103 | S62: nạp game; gaming; cashback; entertainment; game publisher; vertical expansion | T62: 4 | U62: 2 | V62: 5 | W62: 2 | X62: =IF(G62<DATE(2026,4,30),T62*$T$1+U62*$U$1+V62*$V$1+W62*$W$1,T62*$T$2+U62*$U$2) -> 3.4 | Y62: Thanh toán | Z62: Liên kết Apple Pay
A63: =ROW()-3 -> 60 | B63: https://www.momo.vn/tin-tuc/khuyen-mai/19-3-31-3-hoan-ngay-4k-khi-chuyen-2k-tu-ngan-hang-8572 | C63: =HYPERLINK(B63,O63) -> Nhận tiền từ ngân hàng qua SĐT MoMo: Hoàn đến 8.888đ khi chuyển 2k từ ngân hàng đến MoMo của bản thân | D63: MoMo Website | E63: =VLOOKUP(X63,'Updating-Scoring'!$C$2:$D$7,2,TRUE) -> 3 - Market signal | F63: =WEEKNUM(G63,2) -> 14 | G63: 46111 | H63: 19/3 - 31/3: Hoàn ngay 4k khi chuyển 2k từ ngân hàng | I63: 46100 | J63: Players Movement | K63: MoMo | L63: Marketing | M63: User activation | N63: =L63&" | "&M63 -> Marketing | User activation | O63: Nhận tiền từ ngân hàng qua SĐT MoMo: Hoàn đến 8.888đ khi chuyển 2k từ ngân hàng đến MoMo của bản thân | P63: Ưu đãi nhằm thúc đẩy adoption cho hành vi sử dụng tính năng "Nhận tiền từ ngân hàng qua sđt MoMo" - Đối tượng: (1) Người lần đầu tiên sử dụng tính năng “Nhận tiền từ Ngân hàng qua số điện thoại MoMo (2 Người dùng chưa từng tự chuyển tiền từ Ngân hàng cá nhân về số điện thoại MoMo của mình (3) Người nhưng chưa sử dụng dịch vụ trong tháng 3/2026 - Hoàn 8.888đ cho nhóm 1,2 và 4.444đ cho nhóm 3 | Q63: 46100.625 | R63: 46112.999 | S63: chuyển tiền ngân hàng; cashback; nạp ví; transaction growth; incentive; MoMo wallet | T63: 4 | U63: 2 | V63: 5 | W63: 2 | X63: =IF(G63<DATE(2026,4,30),T63*$T$1+U63*$U$1+V63*$V$1+W63*$W$1,T63*$T$2+U63*$U$2) -> 3.4 | Y63: Ví | Z63: Nhận tiền từ ngân hàng qua SĐT Momo
A64: =ROW()-3 -> 61 | B64: https://www.momo.vn/tin-tuc/thong-bao/di-lam-tien-loi-tiet-kiem-hon-quet-momo-di-metro-8578 | C64: =HYPERLINK(B64,O64) -> MoMo x Metro: Quét QR thanh toán vé Metro bằng MoMo - Nhận voucher giảm 50% giá xe công nghệ | D64: MoMo Website | E64: =VLOOKUP(X64,'Updating-Scoring'!$C$2:$D$7,2,TRUE) -> 4 - Strategic shift | F64: =WEEKNUM(G64,2) -> 14 | G64: 46111 | H64: Đi làm tiện lợi, tiết kiệm hơn: Quét MoMo đi Metro | I64: 46103 | J64: Players Movement | K64: MoMo | L64: Marketing | M64: User activation | N64: =L64&" | "&M64 -> Marketing | User activation | O64: MoMo x Metro: Quét QR thanh toán vé Metro bằng MoMo - Nhận voucher giảm 50% giá xe công nghệ | P64: Ưu đãi dành cho người dùng khi quét mã MoMo để thanh toán qua trạm Metro hoặc mua vé Metro qua ứng dụng MoMo - Tặng voucher giảm 50% tối đa 10K khi đặt Grab/Xanh SM/Be - Voucher được tặng sau khi thanh toán vé Metro thành công với MoMo | Q64: 46101 | R64: 46139 | S64: Metro TP.HCM; vé tàu điện; transportation payment; QR payment; mobility; urban transit | T64: 5 | U64: 2 | V64: 5 | W64: 2 | X64: =IF(G64<DATE(2026,4,30),T64*$T$1+U64*$U$1+V64*$V$1+W64*$W$1,T64*$T$2+U64*$U$2) -> 3.8 | Y64: Thanh toán | Z64: QR thanh toán
A65: =ROW()-3 -> 62 | B65: https://www.momo.vn/tin-tuc/khuyen-mai/rut-thong-diep-mo-yeu-thuong-khui-kho-qua-500-8570 | C65: =HYPERLINK(B65,O65) -> Gamification: Rút Thông Điệp - Mở Yêu Thương: Khui Kho Quà 500 Triệu Cùng Hàng Loạt Ưu Đãi Khủng | D65: MoMo Website | E65: =VLOOKUP(X65,'Updating-Scoring'!$C$2:$D$7,2,TRUE) -> 4 - Strategic shift | F65: =WEEKNUM(G65,2) -> 14 | G65: 46111 | H65: Rút thông điệp mở yêu thương - Khui kho quà 500 phần thưởng | I65: 46099 | J65: Players Movement | K65: MoMo | L65: Marketing | M65: User engagement | N65: =L65&" | "&M65 -> Marketing | User engagement | O65: Gamification: Rút Thông Điệp - Mở Yêu Thương: Khui Kho Quà 500 Triệu Cùng Hàng Loạt Ưu Đãi Khủng | P65: Gamification campaign tăng DAU truy cập ứng dụng và sử dụng tính năng, dịch vụ của MoMo - Phần thưởng: (1) 200 triệu tiền mặt qua bao lì xì 147đ - 1314đ - 9312đ - 51020đ - 30k - 100k (2) 200 triệu xu MoMo (3) 100 triệu ưu đãi các dịch vụ MoMo - Cách thức: Người dùng thực hiện nhiệm vụ để có lượt rút giải thưởng, trong đó có 2 khung giờ vàng giải thưởng tới 300 triệu (10h - 15h ngày 20/3 và 01/04) - Nhiệm vụ: nạp tiền điện thoại/data; mua sum; mua vé Metro; truy cập Du lịch-đi lại; etc. | Q65: 46101 | R65: 46127 | S65: gamification; viral marketing; thông điệp yêu thương; engagement; MoMo promotion; payment; du lịch; | T65: 5 | U65: 2 | V65: 5 | W65: 2 | X65: =IF(G65<DATE(2026,4,30),T65*$T$1+U65*$U$1+V65*$V$1+W65*$W$1,T65*$T$2+U65*$U$2) -> 3.8
A66: =ROW()-3 -> 63 | B66: https://www.momo.vn/tin-tuc/khuyen-mai/tich-ngay-500-xu-khi-tai-ma-qr-nhan-tien-8582 | C66: =HYPERLINK(B66,O66) -> QR nhận tiền: MoMo thưởng 500 Xu cho user tải và lưu mã QR Nhận Tiền về điện thoại | D66: MoMo Website | E66: =VLOOKUP(X66,'Updating-Scoring'!$C$2:$D$7,2,TRUE) -> 4 - Strategic shift | F66: =WEEKNUM(G66,2) -> 14 | G66: 46111 | H66: Tích ngay 500 Xu khi tải mã QR Nhận Tiền | I66: 46104 | J66: Players Movement | K66: MoMo | L66: Marketing | M66: User activation | N66: =L66&" | "&M66 -> Marketing | User activation | O66: QR nhận tiền: MoMo thưởng 500 Xu cho user tải và lưu mã QR Nhận Tiền về điện thoại | P66: MoMo thưởng 500 Xu cho user tải và lưu mã QR Nhận Tiền về điện thoại. - Đối tượng: Khách hàng đã từng nhận tiền qua QR MoMo trong 2 tháng gần đây nhất, và chưa từng tải mã QR MoMo nhận tiền giao diện mới - Mục tiêu: Gia tăng hành vi “chia sẻ QR – nhận tiền” với QR giao diện mới từ MoMo | Q66: 46104 | R66: 46112 | S66: QR Nhận Tiền; 500 Xu; merchant QR; incentive; payment behavior; gamification | T66: 5 | U66: 2 | V66: 5 | W66: 2 | X66: =IF(G66<DATE(2026,4,30),T66*$T$1+U66*$U$1+V66*$V$1+W66*$W$1,T66*$T$2+U66*$U$2) -> 3.8 | Y66: Thanh toán | Z66: QR nhận tiền
A67: =ROW()-3 -> 64 | B67: https://www.momo.vn/tin-tuc/khuyen-mai/nhan-canh-bao-phat-hien-nguy-co-lua-dao-khi-8568 | C67: =HYPERLINK(B67,O67) -> Nhãn cảnh báo phát hiện nguy cơ lừa đảo khi chuyển tiền trên MoMo | D67: MoMo Website | E67: =VLOOKUP(X67,'Updating-Scoring'!$C$2:$D$7,2,TRUE) -> 2 - Minor signal | F67: =WEEKNUM(G67,2) -> 14 | G67: 46111 | H67: Nhãn cảnh báo phát hiện nguy cơ lừa đảo khi chuyển tiền trên MoMo | I67: 46098 | J67: Players Movement | K67: MoMo | L67: Feature | M67: Security / Privacy | N67: =L67&" | "&M67 -> Feature | Security / Privacy | O67: Nhãn cảnh báo phát hiện nguy cơ lừa đảo khi chuyển tiền trên MoMo | P67: Khi chuyển tiền MoMo: - Người dùng sẽ được cảnh báo về độ tin cậy của tài khoản (Xanh lá - An toàn, Vàng - Cần cân nhắc, Đỏ - Nguy hiểm). Danh sách tài khoản cảnh báo từ hệ thống thông tin hỗ trợ quản lý, giám sát và phòng ngừa rủi ro gian lận trong hoạt động thanh toán của Ngân hàng Nhà nước (SIMO) hoặc từ khiếu nại của người dùng - Tính năng Báo cáo tài khoản nghi ngờ lừa đảo Động thái này cho thấy chiến lược phòng chống gian lận cũng như tăng đô tin cậy của người dùng với sản phẩm tài chỉnh số | Q67: 46213 | S67: cảnh báo lừa đảo; fraud detection; AI security; chuyển tiền; anti-fraud; trust & safety | T67: 1 | U67: 2 | V67: 5 | W67: 2 | X67: =IF(G67<DATE(2026,4,30),T67*$T$1+U67*$U$1+V67*$V$1+W67*$W$1,T67*$T$2+U67*$U$2) -> 2.2 | Y67: VAS | Z67: Nhãn cảnh báo tài khoản lừa đảo
A68: =ROW()-3 -> 65 | B68: https://www.momo.vn/tin-tuc/khuyen-mai/sieu-sale-sinh-nhat-lazada-hoan-tien-gap-3-lan-8583 | C68: =HYPERLINK(B68,O68) -> MoMo × Lazada: Siêu sale sinh nhật - Hoàn tiền gấp 3 lần, bạn mới Lazada nhận thêm 5K tiền hoàn | D68: MoMo Website | E68: =VLOOKUP(X68,'Updating-Scoring'!$C$2:$D$7,2,TRUE) -> 4 - Strategic shift | F68: =WEEKNUM(G68,2) -> 14 | G68: 46111 | H68: Siêu sale sinh nhật Lazada - Hoàn tiền gấp 3 lần, bạn mới Lazada nhận thêm 5K tiền hoàn | I68: 46104 | J68: Players Movement | K68: MoMo | L68: Marketing | M68: User activation | N68: =L68&" | "&M68 -> Marketing | User activation | O68: MoMo × Lazada: Siêu sale sinh nhật - Hoàn tiền gấp 3 lần, bạn mới Lazada nhận thêm 5K tiền hoàn | P68: Ưu đãi nhằm thúc đẩy adoption cho tính năng "Hoàn tiền mua sắm" trên ứng dụng MoMo, từ đó tăng doanh thu Affiliate - Cách thức: Người dùng thực hiện mua sắm theo đối tác trên "Hoàn tiền mua sắm" hoặc dán link sản phẩm từ Lazada - Từ 24 - 31/3: người dùng lần đầu có đơn Lazada trên Hoàn tiền mua sắm, nhận thêm 5K tiền hoàn về Túi Thần Tài - Từ 24 - 27/3: người dùng mua sắm nhận đến gấp 3 tiền hoàn cho các đơn hàng Lazada - Bạn mới với Hoàn tiền mua sắm: Nhận thêm 10k cho đơn đầu tiên | Q68: 46105 | R68: 46112 | S68: Lazada; cashback; sinh nhật Lazada; e-commerce; hoàn tiền; merchant partnership | T68: 5 | U68: 2 | V68: 5 | W68: 2 | X68: =IF(G68<DATE(2026,4,30),T68*$T$1+U68*$U$1+V68*$V$1+W68*$W$1,T68*$T$2+U68*$U$2) -> 3.8 | Y68: Thanh toán | Z68: Hoàn tiền mua sắm
A69: =ROW()-3 -> 66 | B69: https://www.momo.vn/tin-tuc/khuyen-mai/sale-cuoi-thang-duy-nhat-253-combo-du-lich-le-8577 | C69: =HYPERLINK(B69,O69) -> MoMo Travel: Sale cuối tháng - duy nhất 25.3: Combo du lịch lễ giảm đến 2 triệu trên MoMo Travel! | D69: MoMo Website | E69: =VLOOKUP(X69,'Updating-Scoring'!$C$2:$D$7,2,TRUE) -> 4 - Strategic shift | F69: =WEEKNUM(G69,2) -> 14 | G69: 46111 | H69: Sale cuối tháng duy nhất 25/3: Combo du lịch lễ 30/4 - 1/5 | I69: 46106 | J69: Players Movement | K69: MoMo | L69: Marketing | M69: Transaction growth | N69: =L69&" | "&M69 -> Marketing | Transaction growth | O69: MoMo Travel: Sale cuối tháng - duy nhất 25.3: Combo du lịch lễ giảm đến 2 triệu trên MoMo Travel! | P69: Chiến dịch Flash sale một ngày duy nhất 25/3 thúc đẩy adoption và retention cho tính năng "Du lịch - đi lại" trên MoMo. - Phạm vi: toàn bộ dịch vụ du lịch - Ưu đãi: 3% - 20% cho bạn mới, 2 - 10% cho khách thân quen | Q69: 46106 | R69: 46106 | S69: flash sale; 30/4; du lịch; combo travel; MoMo Travel; urgency; booking | T69: 5 | U69: 2 | V69: 5 | W69: 2 | X69: =IF(G69<DATE(2026,4,30),T69*$T$1+U69*$U$1+V69*$V$1+W69*$W$1,T69*$T$2+U69*$U$2) -> 3.8 | Y69: Thanh toán | Z69: Du lịch đi lại
A70: =ROW()-3 -> 67 | B70: https://www.momo.vn/tin-tuc/khuyen-mai/sale-44-combo-ve-du-lich-giam-den-50-san-ve-choi-8590 | C70: =HYPERLINK(B70,O70) -> MoMo Travel Sale 4.4: Combo vé du lịch giảm 50% — Kích hoạt travel segment trước dịp 30/4 | D70: MoMo Website | E70: =VLOOKUP(X70,'Updating-Scoring'!$C$2:$D$7,2,TRUE) -> 4 - Strategic shift | F70: =WEEKNUM(G70,2) -> 14 | G70: 46111 | H70: Sale 4.4 - Combo vé du lịch giảm đến 50%: Săn vé chơi chơi lễ lớn! | I70: 46108 | J70: Players Movement | K70: MoMo | L70: Marketing | M70: Transaction growth | N70: =L70&" | "&M70 -> Marketing | Transaction growth | O70: MoMo Travel Sale 4.4: Combo vé du lịch giảm 50% — Kích hoạt travel segment trước dịp 30/4 | P70: Chiến dịch Sale 4.4 – Combo vé du lịch giảm đến 50% của MoMo Travel diễn ra trong 1 ngày duy nhất 04/04/2026, khai thác nhu cầu săn vé cho kỳ nghỉ lễ 30/4 bằng loạt ưu đãi mạnh trên nhiều dịch vụ du lịch như vé máy bay, xe khách, tàu hỏa và vé khu vui chơi - Giảm 5-50% cho bạn mới - Giảm 3-10% cho bạn thân | Q70: 46116 | R70: 46116 | S70: MoMo Travel; sale 4.4; vé du lịch; giảm 50%; combo vé; khuyến mãi | T70: 5 | U70: 2 | V70: 5 | W70: 2 | X70: =IF(G70<DATE(2026,4,30),T70*$T$1+U70*$U$1+V70*$V$1+W70*$W$1,T70*$T$2+U70*$U$2) -> 3.8 | Y70: Thanh toán | Z70: Du lịch đi lại
A71: =ROW()-3 -> 68 | B71: https://www.momo.vn/tin-tuc/khuyen-mai/gio-nghi-trai-nghiem-coca-cola-mien-phi-tai-cvs-8585 | C71: =HYPERLINK(B71,O71) -> MoMo × Coca-Cola × CVS: Activation tại điểm bán — Giao lưu FMCG & Chuỗi tiện lợi | D71: MoMo Website | E71: =VLOOKUP(X71,'Updating-Scoring'!$C$2:$D$7,2,TRUE) -> 4 - Strategic shift | F71: =WEEKNUM(G71,2) -> 14 | G71: 46111 | H71: Giờ nghỉ, trải nghiệm Coca-Cola miễn phí tại CVS cùng MoMo | I71: 46105 | J71: Players Movement | K71: MoMo | L71: Partnership | M71: Merchant partnership | N71: =L71&" | "&M71 -> Partnership | Merchant partnership | O71: MoMo × Coca-Cola × CVS: Activation tại điểm bán — Giao lưu FMCG & Chuỗi tiện lợi | P71: Chương trình offline activation kết hợp MoMo–Coca-Cola–CVS: user quét MoMo tại CVS nhận Coca-Cola miễn phí. Mô hình merchant activation thúc đẩy offline payment tại chuỗi tiện lợi. | Q71: 46108 | R71: 46131 | S71: Chương trình mini-promo để kích thích người dùng thanh toán bằng Momo tại Cửa hàng tiện lợi khi mua hàng trực tiếp tại một số khung giờ nhất định (09:00- 11:00 và từ 15:00-17:00 - Danh sách cửa hàng: CircleK; Ministop; GS25 - Mua 01 sản phẩm Coca-Cola có trong danh sách tại các cửa hàng tiện lợi và thanh toán bằng Ứng dụng MoMo - Nhận ngay voucher miễn phí 01 chai Coca-Cola 390ml vị Nguyên Bản; HSD 7 ngày trong mục "Ưu đãi" của MoMo | T71: 5 | U71: 2 | V71: 5 | W71: 2 | X71: =IF(G71<DATE(2026,4,30),T71*$T$1+U71*$U$1+V71*$V$1+W71*$W$1,T71*$T$2+U71*$U$2) -> 3.8 | Y71: Thanh toán | Z71: CVS
A72: =ROW()-3 -> 69 | B72: https://www.momo.vn/tin-tuc/khuyen-mai/tu-dong-canh-bao-phat-nguoi-khi-he-thong-phat-8586 | C72: =HYPERLINK(B72,O72) -> MoMo ra mắt gói Subscription: Cảnh Báo Phạt Nguội Tự Động 29k/năm | D72: MoMo Website | E72: =VLOOKUP(X72,'Updating-Scoring'!$C$2:$D$7,2,TRUE) -> 5 - Industry disruption | F72: =WEEKNUM(G72,2) -> 14 | G72: 46111 | H72: Tự động cảnh báo phạt nguội khi hệ thống phát hiện lỗi mới chỉ từ 2.500đ/tháng với MoMo | I72: 46105 | J72: Players Movement | K72: MoMo | L72: Product | M72: Product launch | N72: =L72&" | "&M72 -> Product | Product launch | O72: MoMo ra mắt gói Subscription: Cảnh Báo Phạt Nguội Tự Động 29k/năm | P72: MoMo tăng cường định vị “siêu ứng dụng tiện ích đời sống” bằng tính năng cảnh báo chủ động: Ưu đãi 85% khi mua gói năm và Giảm 10k nếu mua gói tháng Tính năng: Cảnh báo phạt nguội tự động từ hệ thống Cục CSGT hoặc Cục Đăng kiểm Việt Nam khi phát hiện lỗi; Nhắc hạn đăng kiểm; Tra cứu kết quả vi phạm Gói: Gói Bạc (199k/năm còn 29k/năm; 10k/tháng), Gói Vàng (299k/năm còn 39k/năm; 19k/tháng) - gói vàng được thêm ưu đãi 40% các loại hiểm ô tô | Q72: 46105 | S72: phạt nguội; cảnh báo tự động; subscription; giao thông; CSGT; MoMo services | T72: 5 | U72: 4 | V72: 5 | W72: 3 | X72: =IF(G72<DATE(2026,4,30),T72*$T$1+U72*$U$1+V72*$V$1+W72*$W$1,T72*$T$2+U72*$U$2) -> 4.45 | Y72: VAS | Z72: Cảnh báo phạt nguội
A73: =ROW()-3 -> 70 | B73: https://www.momo.vn/tin-tuc/khuyen-mai/thong-bao-thay-doi-phi-thanh-toan-toi-thieu-va-8573 | C73: =HYPERLINK(B73,O73) -> MoMo Ví Trả Sau: Tăng phí trả chậm & Phí Thanh toán tối thiểu từ 1/4 | D73: MoMo Website | E73: =VLOOKUP(X73,'Updating-Scoring'!$C$2:$D$7,2,TRUE) -> 4 - Strategic shift | F73: =WEEKNUM(G73,2) -> 14 | G73: 46111 | H73: Thông báo thay đổi phí thanh toán tối thiểu và phí trả chậm của Ví Trả Sau trên MoMo | I73: 46101 | J73: Players Movement | K73: MoMo | L73: Product | M73: Pricing change | N73: =L73&" | "&M73 -> Product | Pricing change | O73: MoMo Ví Trả Sau: Tăng phí trả chậm & Phí Thanh toán tối thiểu từ 1/4 | P73: MoMo tăng: - Phí chậm trả Ví Trả Sau tăng từ 0.25 - 1% - Phí thanh toán tối thiểu từ 6%→6.3% Đây là hành động được cho là để đảm bảo bù rủi ro nợ xấu và vận hành bền vững khi lượng người dùng tăng. Đây cũng là bước chuyển từ giai đoạn “đốt tiền để tăng trưởng” sang tối ưu doanh thu, đồng thời dùng phí để điều chỉnh hành vi, khuyến khích người dùng trả đúng hạn thay vì kéo dài dư nợ | Q73: 46113 | S73: Ví Trả Sau; BNPL; phí trả chậm; pricing change; phí thanh toán tối thiểu; MoMo wallet | T73: 5 | U73: 2 | V73: 5 | W73: 2 | X73: =IF(G73<DATE(2026,4,30),T73*$T$1+U73*$U$1+V73*$V$1+W73*$W$1,T73*$T$2+U73*$U$2) -> 3.8 | Y73: Ví trả sau | Z73: Phí trả chậm và phí thanh toán
A74: =ROW()-3 -> 71 | B74: https://www.facebook.com/share/p/1LoP4fCGTk/?mibextid=wwXIfr | C74: =HYPERLINK(B74,O74) -> Zalopay ngừng cập nhật cho iOS 14 và các phiên bản thấp hơn | D74: Zalopay Facebook | E74: =VLOOKUP(X74,'Updating-Scoring'!$C$2:$D$7,2,TRUE) -> 3 - Market signal | F74: =WEEKNUM(G74,2) -> 14 | G74: 46111 | H74: Zalopay ngừng cập nhật cho iOS 14 và các phiên bản thấp hơn | I74: 46097 | J74: Players Movement | K74: Zalopay | L74: Feature | M74: Feature upgrade | N74: =L74&" | "&M74 -> Feature | Feature upgrade | O74: Zalopay ngừng cập nhật cho iOS 14 và các phiên bản thấp hơn | P74: Từ ngày 19/03/2026, ứng dụng ZaloPay sẽ ngừng hỗ trợ cập nhật trên thiết bị sử dụng hệ điều hành iOS 14 và các phiên bản thấp hơn để tối ưu trải nghiệm người dùng, đảm bảo các tính năng mới hoạt động mượt mà và nâng cao độ bảo mật cho tài khoản | Q74: 46100 | S74: cập nhật iOS | T74: 4 | U74: 4 | V74: 2 | W74: 2 | X74: =IF(G74<DATE(2026,4,30),T74*$T$1+U74*$U$1+V74*$V$1+W74*$W$1,T74*$T$2+U74*$U$2) -> 3.3
A75: =ROW()-3 -> 72 | C75: =HYPERLINK(B75,O75) -> Quét QR thanh toán quốc tế - Giảm ngay 50% tối đa 50k cho giao dịch thanh toán lần đầu tiên | D75: Zalo App | E75: =VLOOKUP(X75,'Updating-Scoring'!$C$2:$D$7,2,TRUE) -> 3 - Market signal | F75: =WEEKNUM(G75,2) -> 14 | G75: 46111 | H75: Quét QR thanh toán quốc tế - Giảm ngay 50% tối đa 50.000 VNĐ cho giao dịch thanh toán lần đầu tiên | I75: 46082 | J75: Players Movement | K75: Zalopay | L75: Marketing | M75: User acquisition | N75: =L75&" | "&M75 -> Marketing | User acquisition | O75: Quét QR thanh toán quốc tế - Giảm ngay 50% tối đa 50k cho giao dịch thanh toán lần đầu tiên | P75: Zalo thúc đẩy khách hàng mới sử dụng tính năng "Quét QR thanh toán quốc tế" tận dụng thời điểm mùa du lịch đang đến gần. - Phạm vi áp dụng: Quét QR tại hàng quán và cửa hàng địa phương tại Singapore, Malaysia, Hàn Quốc, Nhật Bản - Đối tượng áp dụng: Khách hàng lần đầu thanh toán quốc tế với Zalopay - Ưu đãi: Giảm đến 50% - tối đa 50k - đơn tối thiểu 10k | Q75: 46100 | R75: 46112 | S75: QR; thanh toán quốc tế; QR thanh toán quốc tế; du lịch | T75: 3 | U75: 3 | V75: 5 | W75: 2 | X75: =IF(G75<DATE(2026,4,30),T75*$T$1+U75*$U$1+V75*$V$1+W75*$W$1,T75*$T$2+U75*$U$2) -> 3.25 | Y75: Thanh toán | Z75: QR thanh toán quốc tế
A76: =ROW()-3 -> 73 | B76: https://www.facebook.com/share/p/18w4rZ64Av/?mibextid=wwXIfr | C76: =HYPERLINK(B76,O76) -> Gamification: Đua top săn vé Concert 33+ Hưng Yên | D76: Zalopay Facebook | E76: =VLOOKUP(X76,'Updating-Scoring'!$C$2:$D$7,2,TRUE) -> 4 - Strategic shift | F76: =WEEKNUM(G76,2) -> 14 | G76: 46111 | H76: Đặt vé du lịch & vé phim - Cơ hội trung vé Concert 33+ Hưng Yên | I76: 46109 | J76: Players Movement | K76: Zalopay | L76: Marketing | M76: Transaction growth | N76: =L76&" | "&M76 -> Marketing | Transaction growth | O76: Gamification: Đua top săn vé Concert 33+ Hưng Yên | P76: Zalo triển khai mini-game nhằm tăng tương tác của người dùng với những dịch vụ trong Zalopay - Cách thức : Người dùng hoàn thành nhiệm vụ thanh toán đặt vé phim, thanh toán vé máy bay, vé xe khách hoặc vé tàu, vé vui chơi, khách sạn để nhận lượt quay - Tích lũy lượt quay: 26/3 - 19/4. Quay thưởng vào chủ nhật hàng tuần - Quà tặng: + 40 vé Concert Gai Home miễn phí + Bộ voucher du lịch đi lại + Xu Zalopay | Q76: 46107 | R76: 46138 | S76: mini-game; săn vé concert; mua vé xem phim; đặt vé máy bay; đặt vé xe khác/tàu hỏa; đặt khách sạn; vé vui chơi | T76: 4 | U76: 3 | V76: 5 | W76: 2 | X76: =IF(G76<DATE(2026,4,30),T76*$T$1+U76*$U$1+V76*$V$1+W76*$W$1,T76*$T$2+U76*$U$2) -> 3.65 | Y76: Thanh toán | Z76: Du lịch đi lại; Giải trí
A77: =ROW()-3 -> 74 | B77: https://www.facebook.com/share/v/1Ar8w7vvqM/?mibextid=wwXIfr | C77: =HYPERLINK(B77,O77) -> Zalopay tung hàng loạt voucher khởi động mùa lễ 30/4 "Lễ lớn, không chờ lương - Đi đã trả sau" | D77: Zalopay Facebook | E77: =VLOOKUP(X77,'Updating-Scoring'!$C$2:$D$7,2,TRUE) -> 4 - Strategic shift | F77: =WEEKNUM(G77,2) -> 14 | G77: 46111 | H77: Lễ lớn không chờ lương - Du lịch ĐÃ trả sau | I77: 46107 | J77: Players Movement | K77: Zalopay | L77: Marketing | M77: Transaction growth | N77: =L77&" | "&M77 -> Marketing | Transaction growth | O77: Zalopay tung hàng loạt voucher khởi động mùa lễ 30/4 "Lễ lớn, không chờ lương - Đi đã trả sau" | P77: Nhằm thúc đẩy giao dịch qua ví và tài khoản trả sau, Zalopay đã triển khai hàng loạt voucher dịp lễ lớn - Ưu đãi cả ngày: Giảm 90-100k cho lần đầu thanh toán tài khoản trả sau, 40k cho mọi khách hàng thanh toàn tài khoản trả sau - Ưu đãi flash sale giảm mạnh 50% trong khung 12h các ngày cố định (19/3 - 19/4, 22/3 & 4,6,13,20/4) - Phạm vi: Mọi dịch vụ Du lịch đi lại | Q77: 46101 | R77: 46146 | S77: du lịch; ví; tài khoản trả sau; flashsale | T77: 4 | U77: 3 | V77: 5 | W77: 2 | X77: =IF(G77<DATE(2026,4,30),T77*$T$1+U77*$U$1+V77*$V$1+W77*$W$1,T77*$T$2+U77*$U$2) -> 3.65 | Y77: Thanh toán | Z77: Ví; Tài khoản trả sau
A78: =ROW()-3 -> 75 | B78: https://www.facebook.com/share/v/1Ar8w7vvqM/?mibextid=wwXIfr | C78: =HYPERLINK(B78,O78) -> Quét QR chuyển khoản - Nhận 30k xu | D78: Zalopay Facebook | E78: =VLOOKUP(X78,'Updating-Scoring'!$C$2:$D$7,2,TRUE) -> 3 - Market signal | F78: =WEEKNUM(G78,2) -> 14 | G78: 46111 | H78: Quét QR chuyển khoản - Nhận 30k | I78: 46093 | J78: Players Movement | K78: Zalopay | L78: Marketing | M78: User activation | N78: =L78&" | "&M78 -> Marketing | User activation | O78: Quét QR chuyển khoản - Nhận 30k xu | P78: - Ưu đãi: Nhận ngay 30k xu khi quét QR chuyển khoản ngân hàng - Mục tiêu: tăng tỷ lệ adoption cho tính năng quét QR thanh toán của Zalopay | Q78: 46093 | R78: 46112 | S78: QR; thanh toán; QR thanh toán; chuyển khoản ngân hàng | T78: 3 | U78: 3 | V78: 5 | W78: 2 | X78: =IF(G78<DATE(2026,4,30),T78*$T$1+U78*$U$1+V78*$V$1+W78*$W$1,T78*$T$2+U78*$U$2) -> 3.25 | Y78: Thanh toán | Z78: QR thanh toán
A79: =ROW()-3 -> 76 | C79: =HYPERLINK(B79,O79) -> Đồng giá từ 85k khi đặt vé xem phim Hẹn em ngày nhật thức | D79: Zalo App | E79: =VLOOKUP(X79,'Updating-Scoring'!$C$2:$D$7,2,TRUE) -> 3 - Market signal | F79: =WEEKNUM(G79,2) -> 14 | G79: 46111 | H79: Xem phim "hot" nhận ưu đãi xịn | I79: 46093 | J79: Players Movement | K79: Zalopay | L79: Marketing | M79: Transaction growth | N79: =L79&" | "&M79 -> Marketing | Transaction growth | O79: Đồng giá từ 85k khi đặt vé xem phim Hẹn em ngày nhật thức | P79: - Đối tượng: Mọi khách hàng đặt vé xem phim trên Zalopay - Yêu cầu: thanh toán qua Ví Zalopay, Số dư sinh lời, Tài khoản trả sau, Thẻ và TKNH liên kết - Ưu đãi: 85k (Galaxy), 95k - 100k (Lotte), 109k - 120k (CGV) | Q79: 46106 | R79: 46123 | S79: QR; thanh toán; QR thanh toán; chuyển khoản ngân hàng | T79: 3 | U79: 3 | V79: 5 | W79: 2 | X79: =IF(G79<DATE(2026,4,30),T79*$T$1+U79*$U$1+V79*$V$1+W79*$W$1,T79*$T$2+U79*$U$2) -> 3.25 | Y79: Thanh toán | Z79: Vé xem phim
A80: =ROW()-3 -> 77 | C80: =HYPERLINK(B80,O80) -> Giảm 50% khi nạp game qua Zalopay tại cổng thanh toán của NPH Game | D80: Zalo App | E80: =VLOOKUP(X80,'Updating-Scoring'!$C$2:$D$7,2,TRUE) -> 3 - Market signal | F80: =WEEKNUM(G80,2) -> 14 | G80: 46111 | H80: Tặng bạn code nạp game giảm 50% | I80: 46093 | J80: Players Movement | K80: Zalopay | L80: Marketing | M80: Transaction growth | N80: =L80&" | "&M80 -> Marketing | Transaction growth | O80: Giảm 50% khi nạp game qua Zalopay tại cổng thanh toán của NPH Game | P80: - Giảm 50% tối đa 100k cho khách hàng mới - Giảm 50% tối đa 20k cho khách hàng chưa từng nạp game bằng Zalopay - Giảm 50% tối đa 10k cho khashc hàng đã từng nạp game bằng Zalopay - NPH Game: VNGGames, Funtap Game, VMGE Game, JEDI Game, JoyGames, MiGame | Q80: 46098 | R80: 46112 | S80: QR; thanh toán; QR thanh toán; chuyển khoản ngân hàng | T80: 3 | U80: 3 | V80: 5 | W80: 2 | X80: =IF(G80<DATE(2026,4,30),T80*$T$1+U80*$U$1+V80*$V$1+W80*$W$1,T80*$T$2+U80*$U$2) -> 3.25 | Y80: Thanh toán | Z80: Nạp game
A81: =ROW()-3 -> 78 | B81: https://social.zalopay.vn/mega/sharing/10025/0?share_key=1vRayxdKDxoe | C81: =HYPERLINK(B81,O81) -> Gamification: Phất cờ nhận xu, rinh ngay quà khủng - Minigame mừng đại lễ 30.4 | D81: Zalo App | E81: =VLOOKUP(X81,'Updating-Scoring'!$C$2:$D$7,2,TRUE) -> 4 - Strategic shift | F81: =WEEKNUM(G81,2) -> 14 | G81: 46111 | H81: Minigame Mừng đại lễ 30/4 | I81: 46093 | J81: Players Movement | K81: Zalopay | L81: Marketing | M81: User engagement | N81: =L81&" | "&M81 -> Marketing | User engagement | O81: Gamification: Phất cờ nhận xu, rinh ngay quà khủng - Minigame mừng đại lễ 30.4 | P81: Chiến dịch Gamification tăng tương tác với chương trình Loyalty (Xu); đặc biệt cho hội viên Priority của Zalopay nhân dịp lễ 30/4 - Cách tham gia: + Hoàn thành thử thách để nhận lượt phất cờ: điểm danh hội viên, đổi voucher trong "Dùng xu đổi quà", Dùng xu cho GD thanh toán, chuyển tiền bằng QR, etc. + Người dùng có thể đổi xu nhận quà - Nguyên tắc: 100% trúng quà (xu hoặc gấu bông) | Q81: 46105 | R81: 46150 | S81: QR; thanh toán; QR thanh toán; chuyển khoản ngân hàng | T81: 4 | U81: 3 | V81: 5 | W81: 3 | X81: =IF(G81<DATE(2026,4,30),T81*$T$1+U81*$U$1+V81*$V$1+W81*$W$1,T81*$T$2+U81*$U$2) -> 3.8 | Y81: Loyalty
A82: =ROW()-3 -> 79 | B82: https://www.techinasia.com/news/tiktok-shop-shopee-lead-vietnams-beauty-ecommerce-market | C82: =HYPERLINK(B82,O82) -> TikTok Shop & Shopee dẫn dắt thị trường TMĐT ngành làm đẹp tại Việt Nam | D82: TechInAsia | E82: =VLOOKUP(X82,'Updating-Scoring'!$C$2:$D$7,2,TRUE) -> 5 - Industry disruption | F82: =WEEKNUM(G82,2) -> 15 | G82: 46119 | H82: TikTok Shop, Shopee lead Vietnam's beauty e-commerce market | I82: 46115 | J82: Market Pulse | K82: Trong nước | L82: Economic | M82: Market growth/ market size | N82: =L82&" | "&M82 -> Economic | Market growth/ market size | O82: TikTok Shop & Shopee dẫn dắt thị trường TMĐT ngành làm đẹp tại Việt Nam | P82: Người tiêu dùng Việt Nam chi ~US$3 tỷ cho beauty & personal care online năm 2025, tăng ~30% YoY; TikTok Shop và Shopee chiếm gần như toàn bộ thị phần, trong đó TikTok Shop dẫn đầu ở Q4/2025 về beauty GMV. Shop Mall/brand chính hãng đóng góp ~64% doanh thu; số lượng shop hoạt động giảm (–8% QoQ, –13% YoY), cho thấy thị trường bước vào giai đoạn sàng lọc Mô hình content-led commerce (video ngắn, livestream) trở thành lợi thế cạnh tranh cốt lõi của TikTok Shop | S82: TikTok Shop; Shopee; beauty; Vietnam e-commerce; live streaming; market share; competitor | T82: 5 | U82: 4 | V82: 5 | W82: 2 | X82: =IF(G82<DATE(2026,4,30),T82*$T$1+U82*$U$1+V82*$V$1+W82*$W$1,T82*$T$2+U82*$U$2) -> 4.3
A83: =ROW()-3 -> 80 | B83: https://dantri.com.vn/cong-nghe/cong-ty-lam-lo-tai-lieu-noi-bo-he-mo-mo-hinh-ai-co-the-tan-cong-mang-20260328090451830.htm | C83: =HYPERLINK(B83,O83) -> Lộ tài liệu nội bộ hé mở mô hình AI có thể bị khai thác để tấn công mạng | D83: Dân Trí | E83: =VLOOKUP(X83,'Updating-Scoring'!$C$2:$D$7,2,TRUE) -> 2 - Minor signal | F83: =WEEKNUM(G83,2) -> 15 | G83: 46119 | H83: Công ty làm lộ tài liệu nội bộ, hé mở mô hình AI có thể tấn công mạng | I83: 46109 | J83: Market Pulse | K83: Quốc tế | L83: Technology | M83: AI/ Gen AI | N83: =L83&" | "&M83 -> Technology | AI/ Gen AI | O83: Lộ tài liệu nội bộ hé mở mô hình AI có thể bị khai thác để tấn công mạng | P83: Một công ty AI bị lộ tài liệu nội bộ mô tả chi tiết cách LLM có thể tự động hóa các cuộc tấn công mạng quy mô lớn. Sự cố đặt ra lo ngại về rủi ro kép: AI vừa là công cụ bảo vệ vừa có thể bị vũ khí hóa cho mục đích tấn công. Các tổ chức triển khai AI cần đánh giá lại chính sách bảo mật tài liệu kỹ thuật nội bộ. | S83: AI security; data leak; LLM weaponization; cybersecurity; AI risk | T83: 3 | U83: 3 | V83: 2 | W83: 4 | X83: =IF(G83<DATE(2026,4,30),T83*$T$1+U83*$U$1+V83*$V$1+W83*$W$1,T83*$T$2+U83*$U$2) -> 2.95
A84: =ROW()-3 -> 81 | B84: https://vneconomy.vn/techconnect/san-thuong-mai-dien-tu-tang-truong-34-vi-sao-nhieu-doanh-nghiep-van-khong-kiem-duoc-tien.htm | C84: =HYPERLINK(B84,O84) -> TMĐT Việt Nam tăng 34% nhưng doanh nghiệp vẫn không có lãi – Bài toán unit economics nan giải | D84: VNEconomy | E84: =VLOOKUP(X84,'Updating-Scoring'!$C$2:$D$7,2,TRUE) -> 5 - Industry disruption | F84: =WEEKNUM(G84,2) -> 15 | G84: 46119 | H84: Sàn thương mại điện tử tăng trưởng 34%, vì sao nhiều doanh nghiệp vẫn không kiếm được tiền? | I84: 46113 | J84: Market Pulse | K84: Trong nước | L84: Economic | M84: Market growth/ market size | N84: =L84&" | "&M84 -> Economic | Market growth/ market size | O84: TMĐT Việt Nam tăng 34% nhưng doanh nghiệp vẫn không có lãi – Bài toán unit economics nan giải | P84: Doanh thu 4 sàn lớn (Shopee, TikTok Shop, Lazada, Tiki) 9T/2025 đạt ~305,9 nghìn tỷ đồng, +34% YoY. Nghịch lý lợi nhuận: chi phí marketing (ads, KOL/KOC, khuyến mãi) tăng nhanh hơn tăng trưởng chuyển đổi → CPA tăng, margin bị bào mòn. Hành trình mua sắm phân mảnh đa điểm chạm khiến DN buộc phải hiện diện đa kênh, gia tăng chi phí cố định. | S84: Vietnam e-commerce; GMV growth; profitability; Shopee; TikTok Shop; unit economics; market data | T84: 5 | U84: 5 | V84: 4 | W84: 2 | X84: =IF(G84<DATE(2026,4,30),T84*$T$1+U84*$U$1+V84*$V$1+W84*$W$1,T84*$T$2+U84*$U$2) -> 4.35
A85: =ROW()-3 -> 82 | B85: https://genk.vn/nganh-am-nhac-sung-sot-truoc-ai-300-trieu-usd-nam-7-trieu-bai-moi-ngay-va-mot-spotify-moi-sau-moi-2-tuan-165263003211211401.chn | C85: =HYPERLINK(B85,O85) -> AI tạo 7 triệu bài nhạc/ngày – Ngành âm nhạc đứng trước làn sóng disruption chưa từng có | D85: GenK | E85: =VLOOKUP(X85,'Updating-Scoring'!$C$2:$D$7,2,TRUE) -> 2 - Minor signal | F85: =WEEKNUM(G85,2) -> 15 | G85: 46119 | H85: Ngành âm nhạc sững sốt trước AI: 300 triệu USD/năm, 7 triệu bài mới mỗi ngày và một Spotify mới sau mỗi 2 tuần | I85: 46111 | J85: Market Pulse | K85: Quốc tế | L85: Technology | M85: AI/ Gen AI | N85: =L85&" | "&M85 -> Technology | AI/ Gen AI | O85: AI tạo 7 triệu bài nhạc/ngày – Ngành âm nhạc đứng trước làn sóng disruption chưa từng có | P85: Ngành âm nhạc đang đối mặt với làn sóng AI sản xuất 7 triệu bài hát mới mỗi ngày với chi phí vận hành chỉ 300 triệu USD/năm, tương đương một Spotify mới ra đời mỗi 2 tuần. Sự xuất hiện của Suno, Udio và các platform AI music đang phá vỡ mô hình doanh thu truyền thống của các label và nghệ sĩ. Xu hướng này nhanh chóng lan sang marketing – jingle, nhạc nền quảng cáo sẽ bị disrupted đầu tiên. | S85: AI music; Suno; Udio; music industry disruption; generative AI; AI productization | T85: 2 | U85: 3 | V85: 2 | W85: 4 | X85: =IF(G85<DATE(2026,4,30),T85*$T$1+U85*$U$1+V85*$V$1+W85*$W$1,T85*$T$2+U85*$U$2) -> 2.55
A86: =ROW()-3 -> 83 | B86: https://www.techinasia.com/news/mobifone-launches-payments-platform-vietnam | C86: =HYPERLINK(B86,O86) -> MobiFone ra mắt nền tảng hạ tầng thanh toán (MDP) | D86: TechInAsia | E86: =VLOOKUP(X86,'Updating-Scoring'!$C$2:$D$7,2,TRUE) -> 5 - Industry disruption | F86: =WEEKNUM(G86,2) -> 15 | G86: 46119 | H86: MobiFone launches payments platform in Vietnam | I86: 46114 | J86: Market Pulse | K86: Trong nước | L86: Economic | M86: Market growth/ market size | N86: =L86&" | "&M86 -> Economic | Market growth/ market size | O86: MobiFone ra mắt nền tảng hạ tầng thanh toán (MDP) | P86: MobiFone Digital Payments (MDP) được NHNN cấp phép cho chuyển mạch, bù trừ điện tử, cổng thanh toán, trở thành đơn vị thứ hai cạnh tranh trong mảng hạ tầng lõi. Đã kết nối >20 tổ chức tài chính và hợp tác với Visa; ký MOU với NAPAS để nghiên cứu liên thông. Việc MobiFone tham gia hạ tầng lõi cho thấy định hướng mở rộng cạnh tranh có kiểm soát của cơ quan quản lý, đồng thời có thể tác động đến cấu trúc phí, chất lượng dịch vụ và khả năng kết nối trong hệ sinh thái thanh toán – fintech – e-commerce tại Việt Nam | S86: MobiFone; mobile payment; Vietnam fintech; new entrant; digital wallet; competition; VNPay | T86: 5 | U86: 4 | V86: 4 | W86: 3 | X86: =IF(G86<DATE(2026,4,30),T86*$T$1+U86*$U$1+V86*$V$1+W86*$W$1,T86*$T$2+U86*$U$2) -> 4.25
A87: =ROW()-3 -> 84 | B87: https://genk.vn/nhieu-tai-khoan-ban-hang-tren-facebook-bi-bay-mau-dieu-gi-dang-xay-ra-165260402072842972.chn | C87: =HYPERLINK(B87,O87) -> Tài khoản bán hàng Facebook bị vô hiệu hóa hàng loạt – Rủi ro nền tảng với seller TMĐT | D87: GenK | E87: =VLOOKUP(X87,'Updating-Scoring'!$C$2:$D$7,2,TRUE) -> 2 - Minor signal | F87: =WEEKNUM(G87,2) -> 15 | G87: 46119 | H87: Nhiều tài khoản bán hàng trên Facebook bị bay màu: Điều gì đang xảy ra? | I87: 46114 | J87: Market Pulse | K87: Quốc tế | L87: Social | M87: Digital adoption | N87: =L87&" | "&M87 -> Social | Digital adoption | O87: Tài khoản bán hàng Facebook bị vô hiệu hóa hàng loạt – Rủi ro nền tảng với seller TMĐT | P87: Hàng loạt tài khoản bán hàng Facebook đột ngột bị vô hiệu hóa không có cảnh báo, ảnh hưởng trực tiếp doanh thu của merchant. Meta chưa cung cấp giải thích chính thức, cộng đồng seller nghi ngờ hệ thống AI kiểm duyệt hoạt động quá mức. Sự việc làm nổi bật rủi ro phụ thuộc vào nền tảng đơn lẻ trong kinh doanh thương mại điện tử xã hội. | S87: Facebook; account ban; seller risk; social commerce; Meta; platform risk | T87: 3 | U87: 3 | V87: 3 | W87: 3 | X87: =IF(G87<DATE(2026,4,30),T87*$T$1+U87*$U$1+V87*$V$1+W87*$W$1,T87*$T$2+U87*$U$2) -> 3
A88: =ROW()-3 -> 85 | B88: https://genk.vn/nguoi-dung-macbook-ru-nhau-lam-may-keu-ren-mua-mat-phi-nhung-quay-reel-ma-viral-la-duoc-tra-lai-tien-165260329184620414.chn | C88: =HYPERLINK(B88,O88) -> Người dùng MacBook tạo tiếng kêu giả để được hoàn tiền bảo hành – Chiêu viral lan rộng | D88: GenK | E88: =VLOOKUP(X88,'Updating-Scoring'!$C$2:$D$7,2,TRUE) -> 1 - Noise | F88: =WEEKNUM(G88,2) -> 15 | G88: 46119 | H88: Người dùng MacBook rủ nhau làm máy kêu rèn mua mất phí, nhưng quay Reel mà viral là được trả lại tiền | I88: 46110 | J88: Market Pulse | K88: Quốc tế | L88: Social | M88: Digital lifestyle | N88: =L88&" | "&M88 -> Social | Digital lifestyle | O88: Người dùng MacBook tạo tiếng kêu giả để được hoàn tiền bảo hành – Chiêu viral lan rộng | P88: Người dùng MacBook phát hiện cách tạo tiếng kêu giả trên máy để vượt qua bảo hành Apple, sau đó quay video viral lên mạng xã hội. Câu chuyện này lan nhanh như một xu hướng nhưng không có giá trị chiến lược cho thị trường fintech hay super-app. Phân loại là Noise. | S88: MacBook; Apple warranty; viral hack; consumer behavior | T88: 1 | U88: 1 | V88: 1 | W88: 1 | X88: =IF(G88<DATE(2026,4,30),T88*$T$1+U88*$U$1+V88*$V$1+W88*$W$1,T88*$T$2+U88*$U$2) -> 1
A89: =ROW()-3 -> 86 | B89: https://genk.vn/vntt-cong-bo-smart-robotics-huong-toi-he-sinh-thai-tu-dong-hoa-san-xuat-va-logistics-165260330175209289.chn | C89: =HYPERLINK(B89,O89) -> VNTT ra mắt Smart Robotics – Xây dựng hệ sinh thái tự động hóa sản xuất và logistics tại Việt Nam | D89: GenK | E89: =VLOOKUP(X89,'Updating-Scoring'!$C$2:$D$7,2,TRUE) -> 2 - Minor signal | F89: =WEEKNUM(G89,2) -> 15 | G89: 46119 | H89: VNTT công bố Smart Robotics, hướng tới hệ sinh thái tự động hóa sản xuất và logistics | I89: 46111 | J89: Market Pulse | K89: Trong nước | L89: Technology | M89: Cloud/ Infrastructure | N89: =L89&" | "&M89 -> Technology | Cloud/ Infrastructure | O89: VNTT ra mắt Smart Robotics – Xây dựng hệ sinh thái tự động hóa sản xuất và logistics tại Việt Nam | P89: VNTT chính thức công bố dòng sản phẩm Smart Robotics nhằm cung cấp giải pháp tự động hóa toàn diện cho nhà máy và kho hàng tại Việt Nam. Đây là bước đi trong chiến lược đa dạng hóa sang AI và deep tech của VNTT sau khi tái cơ cấu. Mảng robotics đang thu hút đầu tư tăng khi các khu công nghiệp tìm giải pháp giảm chi phí nhân công. | S89: VNTT; robotics; automation; logistics; Vietnam tech; Industry 4.0 | T89: 2 | U89: 2 | V89: 2 | W89: 3 | X89: =IF(G89<DATE(2026,4,30),T89*$T$1+U89*$U$1+V89*$V$1+W89*$W$1,T89*$T$2+U89*$U$2) -> 2.15
A90: =ROW()-3 -> 87 | B90: https://genk.vn/thoi-dai-ai-khi-agency-khong-con-ban-gio-lam-viec-ma-ban-kieng-3-chan-165260331161338534.chn | C90: =HYPERLINK(B90,O90) -> AI buộc agency sáng tạo tái cấu trúc: Từ mô hình bán giờ sang kiềng 3 chân chiến lược | D90: GenK | E90: =VLOOKUP(X90,'Updating-Scoring'!$C$2:$D$7,2,TRUE) -> 2 - Minor signal | F90: =WEEKNUM(G90,2) -> 15 | G90: 46119 | H90: Thời đại AI: Khi agency không còn bán giờ làm việc mà bán kiềng 3 chân | I90: 46112 | J90: Market Pulse | K90: Quốc tế | L90: Social | M90: Digital lifestyle | N90: =L90&" | "&M90 -> Social | Digital lifestyle | O90: AI buộc agency sáng tạo tái cấu trúc: Từ mô hình bán giờ sang kiềng 3 chân chiến lược | P90: Trong kỷ nguyên AI, các agency đang chuyển dịch từ time-based billing sang mô hình giá trị 3 trụ: chiến lược, công nghệ và sáng tạo. AI đã thay thế phần lớn công việc thực thi theo giờ, buộc agency tái định vị ở tầng giá trị cao hơn. Đây là tín hiệu chuỗi giá trị dịch vụ marketing đang bị tái cấu trúc toàn diện. | S90: AI agency; creative industry; business model disruption; AI productization; marketing | T90: 2 | U90: 3 | V90: 2 | W90: 4 | X90: =IF(G90<DATE(2026,4,30),T90*$T$1+U90*$U$1+V90*$V$1+W90*$W$1,T90*$T$2+U90*$U$2) -> 2.55
A91: =ROW()-3 -> 88 | B91: https://genk.vn/facebook-chinh-thuc-dong-cua-messenger-trinh-duyet-web-tu-16-4-165260403080157366.chn | C91: =HYPERLINK(B91,O91) -> Facebook đóng cửa Messenger trên trình duyệt web từ 16/4 – Meta siết chặt hệ sinh thái mobile | D91: GenK | E91: =VLOOKUP(X91,'Updating-Scoring'!$C$2:$D$7,2,TRUE) -> 2 - Minor signal | F91: =WEEKNUM(G91,2) -> 15 | G91: 46119 | H91: Facebook chính thức đóng cửa Messenger trình duyệt web từ 16/4 | I91: 46115 | J91: Market Pulse | K91: Quốc tế | L91: Social | M91: Digital adoption | N91: =L91&" | "&M91 -> Social | Digital adoption | O91: Facebook đóng cửa Messenger trên trình duyệt web từ 16/4 – Meta siết chặt hệ sinh thái mobile | P91: Meta chính thức ngưng hỗ trợ Messenger trên web browser từ 16/4, buộc người dùng chuyển sang ứng dụng mobile hoặc desktop app. Quyết định phản ánh chiến lược tập trung toàn lực vào trải nghiệm mobile của Meta và thu hẹp điểm chạm web đang giảm dần. Đây là tín hiệu tiếp theo trong xu hướng 'mobile-first' của các nền tảng mạng xã hội lớn. | S91: Facebook; Messenger; Meta; desktop shutdown; mobile-first; platform strategy | T91: 3 | U91: 2 | V91: 4 | W91: 1 | X91: =IF(G91<DATE(2026,4,30),T91*$T$1+U91*$U$1+V91*$V$1+W91*$W$1,T91*$T$2+U91*$U$2) -> 2.65
A92: =ROW()-3 -> 89 | B92: https://www.techinasia.com/grabs-greater-southeast-asia-play | C92: =HYPERLINK(B92,O92) -> Grab và “Greater Southeast Asia play” | D92: TechInAsia | E92: =VLOOKUP(X92,'Updating-Scoring'!$C$2:$D$7,2,TRUE) -> 5 - Industry disruption | F92: =WEEKNUM(G92,2) -> 15 | G92: 46119 | H92: Grab's greater Southeast Asia play | I92: 46114 | J92: Market Pulse | K92: SEA | L92: Economic | M92: Market growth/ market size | N92: =L92&" | "&M92 -> Economic | Market growth/ market size | O92: Grab và “Greater Southeast Asia play” | P92: Grab khởi động giai đoạn mở rộng mới thông qua M&A (tiêu biểu: Foodpanda Taiwan ~US$600m), biến Taiwan thành thị trường ngoài SEA đầu tiên Trọng tâm chiến lược: finance - logistics – delivery – app ecosystem, hơn là tăng trưởng mỗi ride-hailing Việt Nam được nhìn nhận là điểm nóng cạnh tranh logistics/commerce, nơi Grab tìm kiếm hiệu quả vận hành và tần suất sử dụng | S92: Grab; super-app; SEA expansion; regional strategy; competitor; ride-hailing; food delivery | T92: 5 | U92: 4 | V92: 5 | W92: 3 | X92: =IF(G92<DATE(2026,4,30),T92*$T$1+U92*$U$1+V92*$V$1+W92*$W$1,T92*$T$2+U92*$U$2) -> 4.45
A93: =ROW()-3 -> 90 | B93: https://techcrunch.com/2026/04/05/as-people-look-for-ways-to-make-new-friends-here-are-the-apps-promising-to-help/ | C93: =HYPERLINK(B93,O93) -> Ứng dụng kết bạn AI nở rộ tại Mỹ – Xu hướng social-tech đối phó với dịch cô đơn | D93: TechCrunch | E93: =VLOOKUP(X93,'Updating-Scoring'!$C$2:$D$7,2,TRUE) -> 1 - Noise | F93: =WEEKNUM(G93,2) -> 15 | G93: 46119 | H93: As people look for ways to make new friends, here are the apps promising to help | I93: 46117 | J93: Market Pulse | K93: Quốc tế | L93: Social | M93: Digital lifestyle | N93: =L93&" | "&M93 -> Social | Digital lifestyle | O93: Ứng dụng kết bạn AI nở rộ tại Mỹ – Xu hướng social-tech đối phó với dịch cô đơn | P93: Làn sóng app kết bạn mới như Timeleft, Bumble BFF và We3 đang nổi lên khi nghiên cứu chứng minh người trẻ ngày càng cô đơn dù hyperconnected. Các app dùng AI ghép cặp dựa trên sở thích và lịch trình, vượt ra ngoài kết nối địa lý đơn thuần. Xu hướng này chưa có đối ứng rõ ràng tại Việt Nam nhưng đáng chú ý cho mảng community features trong super-app. | S93: social apps; AI matching; friend-finding; digital loneliness; community; platform ecosystem | T93: 2 | U93: 1 | V93: 2 | W93: 1 | X93: =IF(G93<DATE(2026,4,30),T93*$T$1+U93*$U$1+V93*$V$1+W93*$W$1,T93*$T$2+U93*$U$2) -> 1.6
... A144: =ROW()-3 -> 141 | B144: https://www.techinasia.com/news/ai-online-shopping-hits-82-indonesia-report | C144: =HYPERLINK(B144,O144) -> 82% người dùng Indonesia mua sắm online có yếu tố AI | D144: TechInAsia | E144: =VLOOKUP(X144,'Updating-Scoring'!$C$2:$D$7,2,TRUE) -> 3 - Market signal | F144: =WEEKNUM(G144,2) -> 15 | G144: 46119 | H144: AI online shopping hits 82% in Indonesia: Report | I144: 46116 | J144: Market Pulse | K144: SEA | L144: Social | M144: Digital adoption | N144: =L144&" | "&M144 -> Social | Digital adoption | O144: 82% người dùng Indonesia mua sắm online có yếu tố AI | P144: Báo cáo cho thấy 82% người mua sắm online tại Indonesia đã tiếp cận tính năng AI. AI được dùng chủ yếu trong gợi ý sản phẩm, tìm kiếm và hỗ trợ chat.Người tiêu dùng ngày càng kỳ vọng AI là một phần mặc định của TMĐT.Indonesia nổi lên như thị trường AI commerce tăng trưởng nhanh ở Đông Nam Á. | S144: Indonesia; AI shopping; e-commerce; SEA; AI adoption; market research; consumer behavior | T144: 3 | U144: 4 | V144: 3 | W144: 3 | X144: =IF(G144<DATE(2026,4,30),T144*$T$1+U144*$U$1+V144*$V$1+W144*$W$1,T144*$T$2+U144*$U$2) -> 3.25
A145: =ROW()-3 -> 142 | B145: https://www.momo.vn/tin-tuc/thong-bao/sap-ra-mat-homie-tram-ket-noi-gia-dinh-ngay-tren-8574 | C145: =HYPERLINK(B145,O145) -> MoMo nhà mình: Trạm kết nối gia đình | D145: MoMo Website | E145: =VLOOKUP(X145,'Updating-Scoring'!$C$2:$D$7,2,TRUE) -> 4 - Strategic shift | F145: =WEEKNUM(G145,2) -> 15 | G145: 46119 | H145: MoMo nhà mình: Trạm kết nối gia đình ngay trên Momo | I145: 46114 | J145: Players Movement | K145: MoMo | L145: Feature | M145: New feature | N145: =L145&" | "&M145 -> Feature | New feature | O145: MoMo nhà mình: Trạm kết nối gia đình | P145: Tính năng mới giúp kết nối các tài khoản MoMo riêng của ba mẹ và con, dự kiến ra mắt từ 31/03/2026, triển khai theo từng đợt cho một số gia đình trải nghiệm sớm:​ Tối đa 1 MoMo Nhà Mình tại một thời điểm​ Tối đa 10 thành viên/ 1 MoMo Nhà Mình​ Tính năng chính: Nhiệm vụ xin thưởng (Cha mẹ tạo nhiệm vụ cho con); Nhật ký nhà mình; Góp tiếp sức bằng meme; Quản lý chi tiêu | Q145: 46112 | S145: MoMo nhà mình;MoMo; kết nối gia đình; quản lý chi tiêu gia đình; tài chính cho con; giáo dục tài chính; gắn kết gia đình | T145: 4 | U145: 4 | V145: 5 | W145: 3 | X145: =IF(G145<DATE(2026,4,30),T145*$T$1+U145*$U$1+V145*$V$1+W145*$W$1,T145*$T$2+U145*$U$2) -> 4.05 | Y145: Thanh toán | Z145: Nhóm gia đình
A146: =ROW()-3 -> 143 | B146: https://www.momo.vn/tin-tuc/khuyen-mai/thang-tu-la-loi-tien-that-co-hoi-cung-chia-thuong-8592 | C146: =HYPERLINK(B146,O146) -> Chuyển tiền qua ví: chuyển tiền 111đ – Tổng giá trị tới 1 triệu xu; 10 triệu tiền mặt | D146: MoMo Website | E146: =VLOOKUP(X146,'Updating-Scoring'!$C$2:$D$7,2,TRUE) -> 4 - Strategic shift | F146: =WEEKNUM(G146,2) -> 15 | G146: 46119 | H146: Tháng Tư là lời… lì xì thật: Cơ hội cùng chia thưởng 1 triệu Xu, rinh 1 chỉ vàng hoặc lì xì đến 10 triệu | I146: 46113 | J146: Players Movement | K146: MoMo | L146: Marketing | M146: User activation | N146: =L146&" | "&M146 -> Marketing | User activation | O146: Chuyển tiền qua ví: chuyển tiền 111đ – Tổng giá trị tới 1 triệu xu; 10 triệu tiền mặt | P146: Chiến dịch khuyến mãi dựa trên hành vi chuyển tiền P2P​ Cách thức: Chuyển tiền tới ví MoMo đúng 111đ và nhận ngẫn nhiên ưu đãi trong 24h​ Ưu đãi: 1 triệu xu; Cặp vé máy bay ~10 triệu; Hoàn tiền 10 triệu; Cặp vé xem phim ~100k tiền mặt | Q146: 46113 | R146: 46142 | S146: Khuyến mãi MoMo; Chuyển tiền MoMo; Chia thưởng tiền mặt; Xu MoMo; Túi Thần Tài; ưu đãi tháng 4; lì xì MoMo; ví điện tử MoMo; chương trình tri ân | T146: 4 | U146: 3 | V146: 5 | W146: 3 | X146: =IF(G146<DATE(2026,4,30),T146*$T$1+U146*$U$1+V146*$V$1+W146*$W$1,T146*$T$2+U146*$U$2) -> 3.8 | Y146: Thanh toán | Z146: Chuyển tiền tới SĐT
A147: =ROW()-3 -> 144 | B147: https://www.momo.vn/tin-tuc/khuyen-mai/giam-them-10-toi-da-100000d-tren-app-guardian-vn-8591 | C147: =HYPERLINK(B147,O147) -> MoMo x Guardian VN: Ưu đãi giảm 10% (tối đa 100.000đ) cho đơn đầu tiên trên app Guardian VN | D147: MoMo Website | E147: =VLOOKUP(X147,'Updating-Scoring'!$C$2:$D$7,2,TRUE) -> 4 - Strategic shift | F147: =WEEKNUM(G147,2) -> 15 | G147: 46119 | H147: Giảm thêm 10% tối đa 100.000đ trên app Guardian VN với mã MOMOBEAUTY cực hời | I147: 46111 | J147: Players Movement | K147: MoMo | L147: Partnership | M147: Merchant partnership | N147: =L147&" | "&M147 -> Partnership | Merchant partnership | O147: MoMo x Guardian VN: Ưu đãi giảm 10% (tối đa 100.000đ) cho đơn đầu tiên trên app Guardian VN | P147: Đối tượng: khách hàng mới có đơn hàng online đầu tiên trên app Guardian VN khi thanh toán bằng MoMo​ Cơ chế: sử dụng mã MoMoBEAUTY khi thanh toán; giảm 10% tối đa 100.000đ ​ Tối đa 01 lần/ khách hàng | Q147: 46113 | R147: 46172 | S147: Khuyến mãi MoMo; Chuyển tiền MoMo; Chia thưởng tiền mặt; Xu MoMo; Túi Thần Tài; ưu đãi tháng 4; lì xì MoMo; ví điện tử MoMo; chương trình tri ân | T147: 4 | U147: 4 | V147: 5 | W147: 3 | X147: =IF(G147<DATE(2026,4,30),T147*$T$1+U147*$U$1+V147*$V$1+W147*$W$1,T147*$T$2+U147*$U$2) -> 4.05 | Y147: Thanh toán
A148: =ROW()-3 -> 145 | B148: https://www.momo.vn/tin-tuc/khuyen-mai/thanh-toan-quoc-te-qua-momo-tai-mang-luoi-napas-8596 | C148: =HYPERLINK(B148,O148) -> MoMo x NAPAS: Thanh toán Quốc tế qua MoMo tại Mạng lưới NAPAS: Hoàn tiền đến 50% | D148: MoMo Website | E148: =VLOOKUP(X148,'Updating-Scoring'!$C$2:$D$7,2,TRUE) -> 4 - Strategic shift | F148: =WEEKNUM(G148,2) -> 15 | G148: 46119 | H148: Thanh toán quốc tế qua Momo | I148: 46119 | J148: Players Movement | K148: MoMo | L148: Partnership | M148: Payment integration | N148: =L148&" | "&M148 -> Partnership | Payment integration | O148: MoMo x NAPAS: Thanh toán Quốc tế qua MoMo tại Mạng lưới NAPAS: Hoàn tiền đến 50% | P148: Phạm vi: sử dụng MoMo thanh toán tại các cửa hàng thuộc mạng lưới liên thông Napas quốc tế​ Ưu đãi: Hoàn 50% tới 200k cho đơn giá trị từ 200k​ Giới hạn: Mỗi khách hàng được hưởng ưu đãi tối đa 3 lần | Q148: 46122 | R148: 46203 | S148: NAPAS; Thanh toán quốc tế; VietQR Global | T148: 5 | U148: 3 | V148: 5 | W148: 3 | X148: =IF(G148<DATE(2026,4,30),T148*$T$1+U148*$U$1+V148*$V$1+W148*$W$1,T148*$T$2+U148*$U$2) -> 4.2 | Y148: Thanh toán | Z148: Thanh toán quốc tế
A149: =ROW()-3 -> 146 | B149: https://www.momo.vn/tin-tuc/khuyen-mai/mo-bat-2026-voi-3-ngay-vang-gioi-thieu-momo-nhan-8325 | C149: =HYPERLINK(B149,O149) -> Ngày vàng mừng bạn trả lại: giới thiệu bạn bè, thưởng tiền mặt (Lần 2 trong năm) | D149: MoMo Website | E149: =VLOOKUP(X149,'Updating-Scoring'!$C$2:$D$7,2,TRUE) -> 4 - Strategic shift | F149: =WEEKNUM(G149,2) -> 15 | G149: 46119 | H149: Ngày Vàng Mời Bạn trở lại: 100% nhận thưởng 100K hoặc 999K tiền mặt khi giới thiệu MoMo. Tổng thưởng 1 tỷ! | I149: 46119 | J149: Players Movement | K149: MoMo | L149: Marketing | M149: User acquisition | N149: =L149&" | "&M149 -> Marketing | User acquisition | O149: Ngày vàng mừng bạn trả lại: giới thiệu bạn bè, thưởng tiền mặt (Lần 2 trong năm) | P149: Người giới thiệu nhận 100% thưởng tiền mặt (100.000đ hoặc 999.000đ) khi người được mời hoàn tất giao dịch đầu tiên (nạp tối thiểu 10.000đ) trong khung giờ vàng 11h–18h | Q149: 46119 | R149: 46121 | S149: Mời bạn mới; Ngày vàng; Nạp tiền vào Momo | T149: 4 | U149: 4 | V149: 5 | W149: 2 | X149: =IF(G149<DATE(2026,4,30),T149*$T$1+U149*$U$1+V149*$V$1+W149*$W$1,T149*$T$2+U149*$U$2) -> 3.9
A150: =ROW()-3 -> 147 | B150: https://vinwonders.com/vi/uu-dai/zalopay-nhan-uu-dai-dat-vinpearl-vinwonders/?utm_source=chatgpt.com | C150: =HYPERLINK(B150,O150) -> ZaloPay x VinPearl x VinWonders: Thanh toán ZaloPay nhận combo ưu đãi tới 2 triệu VNĐ | D150: Zalo App | E150: =VLOOKUP(X150,'Updating-Scoring'!$C$2:$D$7,2,TRUE) -> 4 - Strategic shift | F150: =WEEKNUM(G150,2) -> 15 | G150: 46119 | H150: Thanh toán dễ dàng - Mở ngàn trải nghiệm - Nhận ưu đãi Vinpearl, Vinwonder cực khủng | I150: 46119 | J150: Players Movement | K150: Zalopay | L150: Partnership | M150: Merchant partnership | N150: =L150&" | "&M150 -> Partnership | Merchant partnership | O150: ZaloPay x VinPearl x VinWonders: Thanh toán ZaloPay nhận combo ưu đãi tới 2 triệu VNĐ | P150: Đây partnership campaign theo vertical Du lịch - Giải trí nhằm thúc đẩy Thanh toán bằng Zalopay/ Zalopay Later khi đặt phòng Vinpearl hoặc vé vui chơi VinWonders - Hoàn tiền mọi giao dịch: từ 5k đến 1 triệu VNĐ - Giảm giá trực tiếp cho khách hàng thanh toán lần đầu - Ưu đãi khi thanh toán bằng ví trả sau: Giảm 20k đến 50% max 100k | Q150: 46119 | R150: 46387 | S150: Thanh toán du lịch đi lại; Thanh toán vé vui chơi; Hoàn tiền; Giảm giá trực tiếp; Ưu đãi | T150: 4 | U150: 4 | V150: 4 | W150: 2 | X150: =IF(G150<DATE(2026,4,30),T150*$T$1+U150*$U$1+V150*$V$1+W150*$W$1,T150*$T$2+U150*$U$2) -> 3.7 | Y150: Thanh toán | Z150: Du lịch đi lại; Vui chơi
A151: =ROW()-3 -> 148 | C151: =HYPERLINK(B151,O151) -> ZaloPay triển khai Sale du lịch lễ lớn 4.4 | D151: Zalo App | E151: =VLOOKUP(X151,'Updating-Scoring'!$C$2:$D$7,2,TRUE) -> 4 - Strategic shift | F151: =WEEKNUM(G151,2) -> 15 | G151: 46119 | H151: Sale du lịch lễ lớn 4.4 | I151: 46113 | J151: Players Movement | K151: Zalopay | L151: Marketing | M151: Transaction growth | N151: =L151&" | "&M151 -> Marketing | Transaction growth | O151: ZaloPay triển khai Sale du lịch lễ lớn 4.4 | P151: Seasonal mega campaign (travel vertical), tận dụng peak nhu cầu dịp lễ để kéo booking vé, khách sạn và di chuyển vào hệ sinh thái ZaloPay - Flash sale 12h 4.4: Giảm 1 triệu hoặc 44% tối đa 44k - Flash sale 12h 1.4 - 7.4: Giảm 50% tối đa 200k mỗi ngày - 03/04 - 04/04: Voucher giảm 44% tối đa 14k và 44k - Duy nhất ngày 01/04: Đổi voucher bằng xu, Voucher 44% tối đa 100k, Giảm 4% tối đa 400k MoMo cũng triển khai chiến dịch Sale ngày đôi mua du lịch tương tự | Q151: 46113 | R151: 46119 | S151: Flashsale; Thanh toán du lịch đi lại; | T151: 4 | U151: 4 | V151: 4 | W151: 2 | X151: =IF(G151<DATE(2026,4,30),T151*$T$1+U151*$U$1+V151*$V$1+W151*$W$1,T151*$T$2+U151*$U$2) -> 3.7 | Y151: Thanh toán | Z151: Du lịch đi lại
A152: =ROW()-3 -> 149 | C152: =HYPERLINK(B152,O152) -> ZaloPay x Fahasa: Ưu đãi khi thanh toán bằng ZaloPay trên website/ app | D152: Zalo App | E152: =VLOOKUP(X152,'Updating-Scoring'!$C$2:$D$7,2,TRUE) -> 4 - Strategic shift | F152: =WEEKNUM(G152,2) -> 15 | G152: 46119 | H152: Ưu đãi tháng 4 tại Fahasa | I152: 46113 | J152: Players Movement | K152: Zalopay | L152: Partnership | M152: Merchant partnership | N152: =L152&" | "&M152 -> Partnership | Merchant partnership | O152: ZaloPay x Fahasa: Ưu đãi khi thanh toán bằng ZaloPay trên website/ app | P152: Partnership Campaign thúc đẩy hành vi thanh toán bằng ZaloPay - ví trả sau trên web/ app Fahasa - Giảm 25k đơn từ 150k thanh toán bằng Tài khoản trả sau đến 30/4 - Giảm 15k đơn từ 300k thanh toán bằng ZalopPay đến 30/4 - Giảm 50k đơn từ 300k ngày 1, 8, 15 và 25/4 - Giảm 30k đơn từ 300k ngày 1,8,15,25/4 - Điều kiện: 1 lần/ tháng | Q152: 46113 | R152: 46142 | S152: Thanh toán ZaloPay; Thanh toán ví trả sau; Thanh toán mua sách | T152: 4 | U152: 4 | V152: 4 | W152: 2 | X152: =IF(G152<DATE(2026,4,30),T152*$T$1+U152*$U$1+V152*$V$1+W152*$W$1,T152*$T$2+U152*$U$2) -> 3.7 | Y152: Thanh toán | Z152: Nhà sách
A153: =ROW()-3 -> 150 | C153: =HYPERLINK(B153,O153) -> ZaloPay x YAME: Ưu đãi khi thanh toán bằng ZaloPay tại hệ thống YAME | D153: Zalo App | E153: =VLOOKUP(X153,'Updating-Scoring'!$C$2:$D$7,2,TRUE) -> 4 - Strategic shift | F153: =WEEKNUM(G153,2) -> 15 | G153: 46119 | H153: Sắm hè thả ga tại YAME | I153: 46113 | J153: Players Movement | K153: Zalopay | L153: Partnership | M153: Merchant partnership | N153: =L153&" | "&M153 -> Partnership | Merchant partnership | O153: ZaloPay x YAME: Ưu đãi khi thanh toán bằng ZaloPay tại hệ thống YAME | P153: Partnership Campaign thúc đẩy hành vi thanh toán bằng ZaloPay - ví trả sau trên web/ app Yame​ Giảm 25K đơn từ 400K​ Giảm 50K đơn từ 550K​ Điều kiện: 1 lần/ tháng | Q153: 46113 | R153: 46142 | S153: Thanh toán ZaloPay; Thanh toán ví trả sau; Thanh toán mua quần áo; Thanh toán thời trang | T153: 4 | U153: 4 | V153: 4 | W153: 2 | X153: =IF(G153<DATE(2026,4,30),T153*$T$1+U153*$U$1+V153*$V$1+W153*$W$1,T153*$T$2+U153*$U$2) -> 3.7 | Y153: Thanh toán | Z153: Thời trang
A154: =ROW()-3 -> 151 | C154: =HYPERLINK(B154,O154) -> ZaloPay x Bit's: Ưu đãi khi thanh toán bằng ZaloPay trên website/ cửa hàng | D154: Zalo App | E154: =VLOOKUP(X154,'Updating-Scoring'!$C$2:$D$7,2,TRUE) -> 4 - Strategic shift | F154: =WEEKNUM(G154,2) -> 15 | G154: 46119 | H154: Mùa hè trải nghiệm tại Biti's | I154: 46113 | J154: Players Movement | K154: Zalopay | L154: Partnership | M154: Merchant partnership | N154: =L154&" | "&M154 -> Partnership | Merchant partnership | O154: ZaloPay x Bit's: Ưu đãi khi thanh toán bằng ZaloPay trên website/ cửa hàng | P154: Partnership Campaign thúc đẩy hành vi thanh toán bằng ZaloPay - ví trả sau trên web hoặc hệ thống cửa hàng Biti's - Giảm 25K đơn từ 400K - Giảm 50K đơn từ 550K - Điều kiện: 1 lần/ tháng | Q154: 46113 | R154: 46203 | S154: Thanh toán ZaloPay; Thanh toán ví trả sau; Thanh toán mua giày; Thanh toán thời trang | T154: 4 | U154: 4 | V154: 4 | W154: 2 | X154: =IF(G154<DATE(2026,4,30),T154*$T$1+U154*$U$1+V154*$V$1+W154*$W$1,T154*$T$2+U154*$U$2) -> 3.7 | Y154: Thanh toán | Z154: Thời trang
A155: =ROW()-3 -> 152 | C155: =HYPERLINK(B155,O155) -> ZaloPay x NPH Game: Ưu đãi khi thanh toán nạp game lần đầu | D155: Zalo App | E155: =VLOOKUP(X155,'Updating-Scoring'!$C$2:$D$7,2,TRUE) -> 4 - Strategic shift | F155: =WEEKNUM(G155,2) -> 15 | G155: 46119 | H155: Tặng voucher nạp game giảm 50% | I155: 46113 | J155: Players Movement | K155: Zalopay | L155: Partnership | M155: Merchant partnership | N155: =L155&" | "&M155 -> Partnership | Merchant partnership | O155: ZaloPay x NPH Game: Ưu đãi khi thanh toán nạp game lần đầu | P155: Thúc đẩy adoption người dùng thanh toán nạp game bằng ZaloPay - Đối tượng: Khách hàng chưa từng phát sinh bất kì giao dịch nạp game - Cách thức: Giảm 50% tối đa 10k nạp game bằng ZaloPay - Phạm vi: VNGGames, VMGE Games, ACE Games, JEDI Games, JoyGames, MiGame, OEG Game | Q155: 46113 | R155: 46145 | S155: Thanh toán ZaloPay; Thanh toán ví trả sau; Thanh toán nạp game | T155: 4 | U155: 4 | V155: 4 | W155: 2 | X155: =IF(G155<DATE(2026,4,30),T155*$T$1+U155*$U$1+V155*$V$1+W155*$W$1,T155*$T$2+U155*$U$2) -> 3.7 | Y155: Thanh toán | Z155: Nạp game
...

Sheet Database_clean
A1: 1 - Noise | B1: 2 - Minor signal | C1: 3 - Market signal | D1: 4 - Strategic shift | E1: 5 - Industry disruption | G1: 18
A3: =Database!A3 -> id | B3: =Database!B3 -> url | C3: =Database!C3 -> hyperlink | D3: =Database!D3 -> source_name | E3: =Database!E3 -> signal_level | F3: =Database!F3 -> week | G3: =Database!G3 -> crawl_date | H3: =Database!H3 -> title_raw | ... Z3: =Database!Z3 -> related_product_2
A4: {=_xlfn._xlws.FILTER(Database[]&"",(Database[week]=G1)*((Database[signal_level] = Database_clean!C1)+(Database[signal_level] = Database_clean!D1)+(Database[signal_level] = Database_clean!E1)),"")} -> 358 | B4: https://www.techinasia.com/news/goto-review-comply-prabowos-8-platform-fee-cap | C4: Indonesia Prabowo ký sắc lệnh cắt hoa hồng ride-hailing xuống 8% – Tác động trực tiếp Grab và GoTo | D4: Tech in Asia | E4: 5 - Industry disruption | F4: 18 | G4: 46145 | H4: GoTo review to comply with Prabowo's 8% platform fee cap | I4: 46143 | J4: Market Pulse | K4: SEA | L4: Legal | M4: eCommerce regulation | N4: Legal | eCommerce regulation | O4: Indonesia Prabowo ký sắc lệnh cắt hoa hồng ride-hailing xuống 8% – Tác động trực tiếp Grab và GoTo | P4: Tổng thống Prabowo ký sắc lệnh tổng thống giảm hoa hồng tối đa của nền tảng gọi xe từ 20% xuống 8%, công bố tại Ngày Lao động 1/5 tại Monas Jakarta. Bằng cách ký Quy định của Tổng thống (Perpres) số 27 năm 2026, Tổng thống đã quy định về mặt pháp lý rằng ít nhất 92% giá vé phải đi trực tiếp vào túi của các tài xế. Tuy chưa có ngày hiệu lực chính thức cụ thể, nhưng được yêu cầu thực thi ngay lập tức trong dịp May Day để bảo vệ tài xế. GoTo báo cáo lợi nhuận ròng đầu tiên 171 tỷ rupiah Q1/2026. Indonesia chiếm 17-19% Mobility GMV và ~20% EBITDA của Grab. Sắc lệnh của Tổng thống sẽ buộc các nền tảng điều chỉnh mô hình vận hành và phân chia doanh thu. Theo đó, GoTo cho biết đang rà soát và chuẩn bị tuân thủ quy định mới của Indonesia. Việc áp trần phí nền tảng 8% làm co hẹp đáng kể take rate của mảng gọi xe (Gojek) – vốn là trụ cột tạo lưu lượng trong mô hình super app. Điều này khiến GoTo khó duy trì lợi nhuận từ mobility nếu không tái cấu trúc chi phí hoặc tìm nguồn bù đắp khác. Đây có thể trở thành tiền lệ để Việt Nam cân nhắc siết phí nền tảng trong các lĩnh vực thiết yếu như gọi xe, giao đồ ăn nhằm bảo vệ đối tác và người lao động | T4: 5 | U4: 5 | X4: 5 | Y4: Ride-hailing / Delivery
A5: 359 | B5: https://vneconomy.vn/techconnect/trung-quoc-ra-chinh-sach-bao-ve-tai-xe-cong-nghe-nhan-vien-giao-hang.htm | C5: Trung Quốc ban hành chính sách bảo vệ tài xế gig economy | D5: VNEconomy | E5: 5 - Industry disruption | F5: 18 | G5: 46145 | H5: Trung Quốc ra chính sách bảo vệ tài xế công nghệ, nhân viên giao hàng | I5: 46132 | J5: Market Pulse | K5: Trung quốc | L5: Legal | M5: eCommerce regulation | N5: Legal | eCommerce regulation | O5: Trung Quốc ban hành chính sách bảo vệ tài xế gig economy | P5: Trung Quốc ban hành khung chính sách toàn diện đầu tiên cho lao động nền tảng (tài xế công nghệ, giao hàng, livestream…), yêu cầu các nền tảng chuẩn hóa quan hệ lao động và ký hợp đồng rõ ràng. Chính sách buộc doanh nghiệp đảm bảo thu nhập hợp lý, phúc lợi và an sinh xã hội, đồng thời chấm dứt tình trạng lao động làm toàn thời gian nhưng không được công nhận chính thức. Trung Quốc cũng siết chặt việc sử dụng thuật toán, yêu cầu minh bạch hơn trong phân bổ đơn hàng và trả lương; mục tiêu là chuẩn hóa kinh tế nền tảng vào năm 2027. Động thái của Trung Quốc cho thấy mô hình gig economy đang bước sang giai đoạn “lao động hóa”, buộc các nền tảng gọi xe–giao hàng phải hy sinh biên lợi nhuận để đổi lấy ổn định xã hội, và có thể trở thành tiền lệ chính sách quan trọng cho các thị trường như Việt Nam khi quy mô lao động nền tảng ngày càng lớn. | T5: 5 | U5: 5 | X5: 5 | Y5: Ride-hailing / Delivery
A6: 360 | B6: https://techcrunch.com/2026/04/30/stripe-link-digital-wallet-ai-agents-shopping/ | C6: Stripe Link ra mắt: ví điện tử cho AI agent tự động thanh toán thay user | D6: TechCrunch | E6: 5 - Industry disruption | F6: 18 | G6: 46145 | H6: Stripe introduces Link, a digital wallet that autonomous AI agents can use, too | I6: 46142 | J6: Market Pulse | K6: Quốc tế | L6: Technology | M6: Open banking/ API | N6: Technology | Open banking/ API | O6: Stripe Link ra mắt: ví điện tử cho AI agent tự động thanh toán thay user | P6: Stripe ra mắt Link — ví điện tử hỗ trợ nhiều PTTT như thẻ, bank, crypto, BNPL cho phép AI agent (OpenClaw và các agent khác) tự thanh toán trong giới hạn được phép, không cần giao thông tin thẻ thật cho agent tại Sessions 2026 (San Francisco, 30/04/2026). Hiện tại Link có trên web, iOS, Android. Tính năng thêm: xem chi tiêu, theo dõi subscription, bảo vệ mua hàng 90 ngày cùng cơ chế giới hạn chi tiêu linh hoạt. Người dùng ủy quyền cho AI agents qua cơ chế OAuth và phê duyệt chi tiêu từng giao dịch, giúp AI hoạt động mà không lộ thông tin thanh toán gốc Context: Mac Mini Apple bán hết vì nhiều người dùng làm nền tảng chạy AI agent. Việc Stripe “trao ví cho AI agents” cho thấy thanh toán đang dịch chuyển từ hành vi của con người sang hành vi của phần mềm, buộc các nền tảng ví và fintech phải sớm chuẩn bị hạ tầng cho agent‑driven commerce | Q6: 46142 | T6: 4.8 | U6: 5 | X6: 4.88 | Y6: Fintech/ Đầu tư
A7: 361 | B7: https://www.techinasia.com/news/wechat-pay-expands-qr-payments-5-asian-countries | C7: WeChat Pay mở rộng QR payments sang 5 nước châu Á – Cạnh tranh trực tiếp với Alipay+ và QR nội địa | D7: Tech in Asia | E7: 5 - Industry disruption | F7: 18 | G7: 46145 | H7: WeChat Pay expands QR payments to 5 Asian countries | I7: 46137 | J7: Market Pulse | K7: SEA | L7: Technology | M7: Open banking/ API | N7: Technology | Open banking/ API | O7: WeChat Pay mở rộng QR payments sang 5 nước châu Á – Cạnh tranh trực tiếp với Alipay+ và QR nội địa | P7: WeChat Pay mở rộng thanh toán QR xuyên biên giới sang 5 quốc gia châu Á gồm Hàn Quốc, Sri Lanka, Thái Lan, Malaysia và Singapore, cho phép người dùng quét trực tiếp QR nội địa khi chi tiêu ở nước ngoài. Dịch vụ được tích hợp trực tiếp với hệ thống QR quốc gia (như PromptPay, DuitNow, SGQR), giúp người dùng không cần tải app địa phương hay đổi tiền. Động thái diễn ra trong bối cảnh du lịch xuyên biên giới của Trung Quốc phục hồi mạnh, mở rộng vai trò WeChat Pay trong hệ sinh thái thanh toán quốc tế. cuộc cạnh tranh ví điện tử sẽ dịch chuyển sang khả năng liên thông xuyên biên giới, gây áp lực lên các ví nội địa (trong đó có Việt Nam) phải mở rộng interoperability hoặc liên kết khu vực. MoMo hay Zalopay đều có những động thái để mở rộng QR thanh toán quốc tế trong thời gian gần đây | T7: 4.8 | U7: 5 | X7: 4.88 | Y7: Fintech/ Đầu tư
A8: 362 | B8: https://www.techsignin.com/040526-ant-international-ket-noi-2-ty-nguoi-dung/ | C8: Ant International ra mắt AMP – Giao thức agentic payment đầu tiên cho mobile | D8: Tech in Asia | E8: 5 - Industry disruption | F8: 18 | G8: 46145 | H8: Ant International links 150 million merchants with AI payments | I8: 46142 | J8: Market Pulse | K8: SEA | L8: Technology | M8: Open banking/ API | N8: Technology | Open banking/ API | O8: Ant International ra mắt AMP – Giao thức agentic payment đầu tiên cho mobile | P8: Tại diễn đàn cấp cao thường niên về công nghệ tài chính (fintech) MoMents 2026 ở Kuala Lumpur, Malaysia,Ant International công bố chiến lược mới nhấn mạnh sự phối hợp giữa các dịch vụ Thanh toán Toàn cầu (Alipay+), Tài khoản Toàn cầu (Antom, WorldFirst) và Tài chính Toàn diện & Tích hợp dựa trên AI, được xây dựng dựa trên những tiến bộ về AI và khả năng tương tác. Là nền tảng cho hoạt động kinh doanh, các dịch vụ thanh toán toàn cầu của Ant International hỗ trợ hơn 300 phương thức thanh toán, bao gồm hơn 10 hệ thống mã QR quốc gia cùng 50 ví điện tử và ứng dụng ngân hàng, đạt trung bình hơn 20 triệu giao dịch mỗi ngày Sản phẩm nổi bật: Giao thức AMP mã nguồn mở – khung thanh toán dựa trên tác nhân đầu tiên trên thế giới được thiết kế cho giao diện di động – nhằm thúc đẩy thương mại AI; Nền tảng AI dưới dạng dịch vụ GenAI Cockpit; AI SHIELD xác định các giao dịch rủi ro cao với độ chính xác trên 95%, đồng thời cải thiện tỷ lệ thanh toán thành công lên đến 13,5%; Falcon TST FX đưa ra các dự báo dài hạn với độ chính xác tới 93% để quản lý dòng tiền và rủi ro ngoại hối, giảm chi phí ngoại hối của công ty tới 60%; EPOS360 POS SME ứng dụng tiên phong dành cho doanh nghiệp vừa và nhỏ (SME) được hỗ trợ bởi trí tuệ nhân tạo (AI), tích hợp các công cụ AI thiết thực với hệ thống POS, thanh toán, ngân hàng, tài chính và các hoạt động tăng trưởng; Antom Copilot cung cấp khả năng tự động hóa và hỗ trợ cho các nhà bán hàng dựa trên các trường hợp thực tế, giúp cải thiện hiệu quả của các dịch vụ như xử lý tranh chấp bồi hoàn (chargeback) lên đến 46% Tại Việt Nam, công ty hợp tác với NAPAS và Vietcombank để triển khai dịch vụ thanh toán mã QR xuyên biên giới, đồng thời cũng đang làm việc với chính quyền TP.HCM nhằm phát triển Trung tâm Tài chính Quốc tế (IFC) | T8: 4.8 | U8: 4.5 | X8: 4.68 | Y8: Fintech/ Đầu tư
A9: 363 | B9: https://www.bloomberg.com/news/articles/2026-04-29/uber-adds-hotel-bookings-to-its-app-through-new-expedia-partnership | C9: Uber tích hợp đặt khách sạn qua Expedia – Super-app ride+food+travel đang hình thành tại Mỹ | D9: Bloomberg | E9: 5 - Industry disruption | F9: 18 | G9: 46145 | H9: Uber adds hotel bookings to its app through new Expedia partnership | I9: 46141 | J9: Market Pulse | K9: Quốc tế | L9: Economic | M9: Business model change | N9: Economic | Business model change | O9: Uber tích hợp đặt khách sạn qua Expedia – Super-app ride+food+travel đang hình thành tại Mỹ | P9: Uber hợp tác Expedia tích hợp đặt 700.000+ khách sạn trực tiếp trong app, triển khai đầu tại Mỹ và mở rộng quốc tế. Người dùng tại Mỹ có thể truy cập hơn 700.000 khách sạn, với ưu đãi cho Uber One members nhận 10% Uber credits và giảm ít nhất 20%. Thêm AI voice booking, Travel Mode với gợi ý địa điểm + OpenTable + Uber Eats giao đến khách sạn. Uber rides cũng sẽ tích hợp vào Expedia app từ tháng 6/2026. Vrbo sẽ thêm vào cuối 2026. Việc tích hợp booking lưu trú giúp Uber kết nối hành trình đi lại – ăn uống – lưu trú trong một trải nghiệm liền mạch, củng cố tham vọng “everything app” | T9: 4 | U9: 5 | X9: 4.4 | Y9: Ride-hailing / Delivery
A10: 364 | B10: https://genk.vn/nguoi-viet-mua-gi-ma-moi-ngay-chot-toi-126-trieu-san-pham-tren-san-tmdt-165260429075817689.chn | C10: Người Việt chốt 126 triệu sản phẩm/ngày trên TMĐT – Số liệu thực tế quy mô thị trường | D10: GenK | E10: 4 - Strategic shift | F10: 18 | G10: 46145 | H10: Người Việt mua gì mà mỗi ngày chốt tới 126 triệu sản phẩm trên sàn TMĐT | I10: 46141 | J10: Market Pulse | K10: Trong nước | L10: Economic | M10: Business model change | N10: Economic | Business model change | O10: Người Việt chốt 126 triệu sản phẩm/ngày trên TMĐT – Số liệu thực tế quy mô thị trường | P10: Theo báo cáo Thị trường sàn bán lẻ trực tuyến quý I/2026 của nền tảng tổng hợp và khai thác dữ liệu Metric.vn, quý I sàn thương mại điện tử (TMĐT) ghi nhận tổng sản lượng 1.138,6 triệu sản phẩm, tương ứng mức tăng 19,7% so với cùng kỳ năm 2025. Với thời gian thống kê từ ngày 1/1 đến 31/3, bình quân mỗi ngày người Việt chốt khoảng 12,6 triệu sản phẩm trên 4 sàn Shopee, Lazada, Tiki và TikTok Shop Cùng với sản lượng tăng, doanh số toàn thị trường đạt 148,6 nghìn tỷ đồng, tăng 46,6% so với cùng kỳ năm trước. Số shop phát sinh đơn hàng đạt 490,9 nghìn shop, tăng 3,91% Top doanh số theo danh mục: Nhóm Làm đẹp dẫn đầu về doanh số với 24.427,3 tỷ đồng. Đây cũng là ngành đứng đầu toàn thị trường trong quý đầu năm. Xếp sau là Nhà cửa - Đời sống với doanh số 18.246 tỷ đồng, tiếp đến là Thời trang nữ đạt 20.953,71 tỷ đồng. Ở nhóm hàng tiêu dùng, Bách hóa - Thực phẩm đạt 9.111,96 tỷ đồng doanh số. Điện thoại và Máy tính bảng đạt 7.133,65 tỷ đồng, trong khi Thời trang nam đạt 9.464,42 tỷ đồng. Top tốc độ tăng trưởng doanh số theo danh mục: Thời trang nam là ngành tăng mạnh nhất với 151,08% so với cùng kỳ năm trước. Theo sau là Phụ kiện thời trang tăng 92,88%, Thời trang nữ tăng 74,75%, Giày dép nữ tăng 45,27% và Điện thoại & Máy tính bảng tăng 44,73% Top sản phẩm bán ra theo số lượng: Nhà cửa - Đời sống dẫn đầu với 210,96 triệu sản phẩm. Làm đẹp đứng thứ hai với 159,96 triệu sản phẩm, tiếp theo là Thời trang nữ với 146,15 triệu sản phẩm Top sàn theo số lượng sản phẩm: Shopee dẫn đầu (629 triệu sp, 55%), TikTok Shop thứ 2 (289 triệu, 25%) | T10: 4 | U10: 4.5 | X10: 4.2 | Y10: TMĐT
A11: 365 | B11: https://baotintuc.vn/thi-truong-tien-te/giao-hang-nhanh-dinh-hinh-lai-cuoc-dua-thuong-mai-dien-tu-20260416172320540.htm | C11: Giao Hàng Nhanh tái định vị để chiếm lợi thế trong cuộc đua TMĐT | D11: Báo Tin Tức | E11: 4 - Strategic shift | F11: 18 | G11: 46145 | H11: Giao hàng nhanh định hình lại cuộc đua thương mại điện tử | I11: 46128 | J11: Market Pulse | K11: Trong nước | L11: Economic | M11: Business model change | N11: Economic | Business model change | O11: Giao Hàng Nhanh tái định vị để chiếm lợi thế trong cuộc đua TMĐT | P11: Giao Hàng Nhanh (GHN) đang tái định vị vai trò từ đơn vị giao vận sang đối tác hạ tầng TMĐT, tham gia sâu hơn vào khâu vận hành và tối ưu đơn hàng cho nhà bán. Doanh nghiệp tập trung vào tốc độ giao hàng, kiểm soát chi phí và giải pháp đặc thù cho người bán nhỏ – vừa, thay vì chạy đua mở rộng bằng trợ giá. Động thái này diễn ra khi cuộc cạnh tranh TMĐT chuyển từ “đốt tiền lấy thị phần” sang tối ưu hiệu quả và trải nghiệm. | T11: 4 | U11: 4 | X11: 4 | Y11: Ride-hailing / Delivery
A12: 366 | B12: https://www.techinasia.com/airwallex-launch-indonesia-vietnam-southeast-asia-push | C12: Airwallex chính thức mở rộng hoạt động sang Indonesia và Việt Nam | D12: Tech in Asia | E12: 4 - Strategic shift | F12: 18 | G12: 46145 | H12: Airwallex launches in Indonesia and Vietnam as part of Southeast Asia push | I12: 46136 | J12: Market Pulse | K12: SEA | L12: Economic | M12: Funding/ Investment | N12: Economic | Funding/ Investment | O12: Airwallex chính thức mở rộng hoạt động sang Indonesia và Việt Nam | P12: Airwallex, fintech đa tiền tệ và thanh toán xuyên biên giới, chính thức ra mắt tại Indonesia và Việt Nam trong năm 2026 sau mua lại giấy phép: CTIN Pay (Việt Nam, trung gian thanh toán) năm 2025 và Skye Sab (Indonesia, dịch vụ thanh toán), đưa hai thị trường này vào trọng tâm chiến lược mở rộng tại Đông Nam Á. Tại Việt Nam, Airwallex cung cấp hệ sinh thái tài chính toàn cầu cho doanh nghiệp xuất khẩu, tập trung chiến lược vào hai hệ sinh thái trọng tâm: Game/App và Ecommerce - ưu tiên doanh nghiệp cần thanh toán xuyên biên giới nhanh, tiết kiệm chi phí so VNPAY/MoMo Sản phẩm chính: Cổng thanh toán quốc tế (60+ tiền tệ, phí thấp minh bạch, API linh hoạt, PCI DSS), Tài khoản Toàn cầu (nhận tiền nội địa Mỹ/EU/Úc/SG/HK không phí SWIFT, hỗ trợ VND 0,6%), Chuyển tiền quốc tế (tỷ giá liên ngân hàng), Thẻ doanh nghiệp đa tiền tệ (cashback), và Banking-as-a-Service nhúng cho nền tảng | T12: 4 | U12: 4 | X12: 4 | Y12: Fintech/ Đầu tư
A13: 367 | B13: https://www.techinasia.com/news/tiktok-launches-restaurant-recommendation-service-indonesia | C13: TikTok ra dịch vụ gợi ý nhà hàng tại Indonesia – Mở rộng sang local services, cạnh tranh Grab | D13: Tech in Asia | E13: 4 - Strategic shift | F13: 18 | G13: 46145 | H13: TikTok launches restaurant recommendation service in Indonesia | I13: 46140 | J13: Market Pulse | K13: SEA | L13: Technology | M13: AI/ Gen AI | N13: Technology | AI/ Gen AI | O13: TikTok ra dịch vụ gợi ý nhà hàng tại Indonesia – Mở rộng sang local services, cạnh tranh Grab | P13: TikTok ra mắt dịch vụ gợi ý nhà hàng tại Indonesia mang tên TikTok Go by Tokopedia, kết nối nội dung video, livestream và tìm kiếm với trải nghiệm ăn uống ngoài đời thực. Việc TikTok chuyển từ “đề xuất nội dung” sang dẫn dắt hành vi tiêu dùng offline cho thấy mạng xã hội đang tiến sâu vào local services & commerce Người dùng có thể xem video → tìm địa điểm → mua voucher → đến quán, trong khi creator được hưởng hoa hồng từ giao dịch, mở ra mô hình kiếm tiền mới cho hệ sinh thái. Dịch vụ tận dụng hành vi khám phá ẩm thực trên TikTok trong bối cảnh Indonesia có hơn 5,2 triệu doanh nghiệp F&B và nhu cầu tìm quán qua nền tảng số tăng mạnh. | T13: 4 | U13: 4 | X13: 4 | Y13: TMĐT
A14: 368 | B14: https://techcrunch.com/2026/04/30/tiktoks-new-campus-hub-features-college-group-chats-and-feeds/ | C14: TikTok mở rộng đối tượng Sinh viên với tính năng Campus Hub | D14: TechCrunch | E14: 4 - Strategic shift | F14: 18 | G14: 46145 | H14: TikTok's new campus hub features college group chats and feeds | I14: 46142 | J14: Market Pulse | K14: Quốc tế | L14: Technology | M14: AI/ Gen AI | N14: Technology | AI/ Gen AI | O14: TikTok mở rộng đối tượng Sinh viên với tính năng Campus Hub | P14: TikTok ra mắt Campus Hub tại Mỹ, bổ sung group chat và feed riêng cho sinh viên từng trường đại học (>6.000 trường đại học qua UNiDAYS), nhằm tăng tương tác theo cộng đồng khép kín. Tính năng chính: College Group Chats (tạo/tham gia nhóm 300 bạn cùng trường, chỉ verified students, tổ chức reunion/họp học); College Feeds cá nhân hóa nội dung từ sinh viên trường + cập nhật xu hướng/sự kiện. Campus Hub được xem là nỗ lực giữ chân nhóm người dùng trẻ Gen Z, gắn TikTok với đời sống hàng ngày chứ không chỉ là nền tảng giải trí ngắn hạn. | Q14: 46142 | T14: 4 | U14: 4 | X14: 4 | Y14: MXH/ Chat/ Giải trí
A15: 369 | B15: https://vnexpress.net/bidv-cung-cac-doi-tac-trien-khai-dich-vu-thanh-toan-qr-viet-han-5066506.html | C15: BIDV mở rộng thanh toán QR xuyên biên giới Việt – Hàn | D15: VnExpress | E15: 4 - Strategic shift | F15: 18 | G15: 46145 | H15: BIDV cùng các đối tác triển khai dịch vụ thanh toán QR Việt-Hàn | I15: 46137 | J15: Market Pulse | K15: Trong nước | L15: Technology | M15: Open banking/ API | N15: Technology | Open banking/ API | O15: BIDV mở rộng thanh toán QR xuyên biên giới Việt – Hàn | P15: BIDV phối hợp với đối tác Hàn Quốc triển khai dịch vụ thanh toán QR Việt–Hàn, cho phép khách Hàn Quốc thanh toán tại Việt Nam và ngược lại bằng ứng dụng ngân hàng nội địa. Giải pháp tận dụng kết nối hạ tầng QR quốc gia của hai nước, giúp người dùng không cần đổi tiền mặt hay tải thêm ví mới. Dịch vụ nhắm tới nhóm khách du lịch, lao động và doanh nghiệp hai chiều Việt–Hàn, nơi có giao thương và di chuyển lớn. Việc BIDV đẩy mạnh thanh toán QR xuyên biên giới cho thấy ngân hàng Việt đang chủ động trong sân chơi cross‑border payments, tạo áp lực cạnh tranh trực tiếp lên ví điện tử và mở ra tiền lệ để Việt Nam tham gia sâu hơn vào mạng lưới QR khu vực. | T15: 4 | U15: 4 | X15: 4 | Y15: Fintech/ Đầu tư
A16: 370 | B16: https://www.techinasia.com/news/ant-international-upgrades-alipay-with-privacy-tech | C16: Ant International tăng cường công nghệ bảo mật để mở rộng Alipay toàn cầu | D16: Tech in Asia | E16: 4 - Strategic shift | F16: 18 | G16: 46145 | H16: Ant International upgrades Alipay with privacy tech | I16: 46140 | J16: Market Pulse | K16: SEA | L16: Technology | M16: Open banking/ API | N16: Technology | Open banking/ API | O16: Ant International tăng cường công nghệ bảo mật để mở rộng Alipay toàn cầu | P16: Ant International nâng cấp Alipay với loạt công nghệ bảo vệ quyền riêng tư, tập trung vào mã hóa dữ liệu, xử lý phân tách và kiểm soát truy cập theo ngữ cảnh. Các cải tiến nhằm giúp Alipay đáp ứng yêu cầu tuân thủ chặt chẽ tại nhiều thị trường, đặc biệt trong các kịch bản thanh toán xuyên biên giới. Ant nhấn mạnh cách tiếp cận “privacy‑by‑design”, coi bảo mật và tuân thủ là nền tảng cho tăng trưởng quốc tế dài hạn. Việc Alipay đầu tư mạnh vào privacy tech cho thấy niềm tin và tuân thủ đang trở thành lợi thế cạnh tranh cốt lõi của fintech toàn cầu, tạo áp lực để các ví và nền tảng thanh toán tại Việt Nam nâng chuẩn bảo mật nếu muốn tham gia sâu hơn vào hệ sinh thái thanh toán khu vực và quốc tế. | T16: 4 | U16: 4 | X16: 4 | Y16: Fintech/ Đầu tư
A17: 371 | B17: https://vnexpress.net/nhieu-ngan-hang-dung-chuyen-tien-nhanh-tren-500-trieu-dong-5063913.html | C17: Nhiều ngân hàng VN dừng chuyển tiền nhanh >500 triệu đồng – Siết quy định thanh toán tức thì lớn | D17: VnExpress | E17: 4 - Strategic shift | F17: 18 | G17: 46145 | H17: Nhiều ngân hàng dừng chuyển tiền nhanh trên 500 triệu đồng | I17: 46133 | J17: Market Pulse | K17: Trong nước | L17: Legal | M17: Fintech/ Wallet | N17: Legal | Fintech/ Wallet | O17: Nhiều ngân hàng VN dừng chuyển tiền nhanh >500 triệu đồng – Siết quy định thanh toán tức thì lớn | P17: Nhiều ngân hàng như Eximbank, TPBank, VPBank dừng tính năng tự động chia nhỏ giao dịch trên 500 triệu đồng, khiến các khoản chuyển liên ngân hàng giá trị lớn không còn đi qua kênh Napas 24/7. Các giao dịch từ 500 triệu đồng trở lên sẽ chuyển sang luồng chuyển khoản thường, có thể mất vài giờ hoặc sang ngày làm việc kế tiếp nếu ngoài giờ hành chính. Việc điều chỉnh nhằm tuân thủ quy định mới của Ngân hàng Nhà nước, tăng kiểm soát rủi ro và phòng chống gian lận, rửa tiền trong giao dịch giá trị lớn. | T17: 4 | U17: 3.5 | X17: 3.8 | Y17: Fintech/ Đầu tư
A18: 372 | B18: https://genk.vn/openclaw-moi-phien-ban-cloud-an-toan-tien-dung-cho-nguoi-viet-165260421151000535.chn | C18: OpenClaw ra phiên bản cloud cho người Việt – AI agent trên nền tảng đám mây | D18: GenK | E18: 4 - Strategic shift | F18: 18 | G18: 46145 | H18: OpenClaw mới: Phiên bản cloud an toàn, tiện dụng cho người Việt | I18: 46133 | J18: Market Pulse | K18: Trong nước | L18: Technology | M18: AI/ Gen AI | N18: Technology | AI/ Gen AI | O18: OpenClaw ra phiên bản cloud cho người Việt – AI agent trên nền tảng đám mây | P18: OpenClaw ra mắt phiên bản cloud mới, tập trung vào bảo mật dữ liệu và trải nghiệm người dùng Việt, cho phép truy cập và quản lý tài nguyên từ xa thuận tiện hơn. Nền tảng nhấn mạnh lưu trữ và xử lý dữ liệu trên cloud nội địa, giúp giảm độ trễ, tăng kiểm soát dữ liệu và phù hợp yêu cầu tuân thủ trong nước. OpenClaw hướng tới người dùng cá nhân và doanh nghiệp nhỏ, cung cấp giải pháp cloud dễ dùng, chi phí hợp lý thay cho các dịch vụ quốc tế phức tạp. | T18: 3.6 | U18: 4 | X18: 3.76 | Y18: AI
A19: 373 | B19: https://vnexpress.net/cach-cong-ty-cong-nghe-trung-quoc-chuyen-hoa-ai-thanh-loi-nhuan-5061856.html | C19: Doanh nghiệp công nghệ Trung Quốc đẩy nhanh thương mại hóa AI để tạo lợi nhuận | D19: VnExpress | E19: 4 - Strategic shift | F19: 18 | G19: 46145 | H19: Cách công ty công nghệ Trung Quốc chuyển hóa AI thành lợi nhuận | I19: 46131 | J19: Market Pulse | K19: Trung quốc | L19: Economic | M19: Business model change | N19: Economic | Business model change | O19: Doanh nghiệp công nghệ Trung Quốc đẩy nhanh thương mại hóa AI để tạo lợi nhuận | P19: Nhiều công ty công nghệ Trung Quốc đang chuyển trọng tâm từ nghiên cứu AI sang thương mại hóa, tích hợp AI trực tiếp vào sản phẩm và dịch vụ tạo doanh thu. AI được ứng dụng mạnh trong quảng cáo, thương mại điện tử, cloud, dịch vụ doanh nghiệp và công cụ làm việc, giúp tối ưu chi phí và tăng hiệu suất vận hành. Thay vì chạy đua mô hình lớn nhất, các doanh nghiệp ưu tiên AI “dùng được – bán được – sinh lời”, phù hợp nhu cầu thị trường nội địa quy mô lớn. Alibaba: Dùng AI tăng hiệu quả quảng cáo và bán giải pháp AI/LLM qua Alibaba Cloud cho doanh nghiệp. Tencent: Ứng dụng AI để tối ưu hiển thị quảng cáo và nội dung trong WeChat, mini‑program và game, gia tăng doanh thu trên mỗi người dùng. Baidu: Thương mại hóa AI thông qua quảng cáo tìm kiếm thông minh và bán giải pháp AI cho doanh nghiệp, chính quyền. ByteDance: AI âm thầm tối ưu phân phối nội dung và quảng cáo trên Douyin/TikTok để tăng doanh thu ads. Meituan: AI trong dự báo nhu cầu, điều phối tài xế và tối ưu logistics, từ đây mở rộng biên lợi nhuận trong giao đồ ăn và local services | T19: 3.5 | U19: 4 | X19: 3.7 | Y19: AI
A20: 374 | B20: https://techcrunch.com/2026/04/21/yelps-updated-ai-assistant-can-answer-questions-and-book-a-restaurant-or-service-in-one-conversation/ | C20: Yelp nâng cấp AI assistant thành “trợ lý hành động” cho ăn uống và dịch vụ | D20: TechCrunch | E20: 4 - Strategic shift | F20: 18 | G20: 46145 | H20: Yelp's updated AI assistant can answer questions and book a restaurant in one conversation | I20: 46133 | J20: Market Pulse | K20: Quốc tế | L20: Technology | M20: AI/ Gen AI | N20: Technology | AI/ Gen AI | O20: Yelp nâng cấp AI assistant thành “trợ lý hành động” cho ăn uống và dịch vụ | P20: Yelp ra mắt phiên bản AI assistant mới có thể trả lời câu hỏi và hoàn tất đặt bàn/đặt dịch vụ trong cùng một cuộc hội thoại. Tính năng chính: Trả lời câu hỏi phức tạp ("nhà hàng Ý gần đây có chỗ trống tối nay, món pasta ngon"), đặt bàn tự động qua Yelp Guest Manager/Vagaro/Zocdoc/Calendly, gọi delivery (DoorDash/Grubhub), dựa trên hàng triệu review thực tế Tính năng này tận dụng dữ liệu đánh giá, bối cảnh và lịch trống để rút ngắn hành trình người dùng từ khám phá đến giao dịch. | Q20: 46133 | T20: 3.5 | U20: 4 | X20: 3.7 | Y20: Ride-hailing / Delivery
A21: 375 | B21: https://techcrunch.com/2026/04/28/snapchat-brings-ai-powered-conversational-advertising-to-its-app/ | C21: Snapchat đưa quảng cáo hội thoại bằng AI vào trải nghiệm người dùng | D21: TechCrunch | E21: 4 - Strategic shift | F21: 18 | G21: 46145 | H21: Snapchat brings AI-powered conversational advertising to its app | I21: 46140 | J21: Market Pulse | K21: Quốc tế | L21: Technology | M21: AI/ Gen AI | N21: Technology | AI/ Gen AI | O21: Snapchat đưa quảng cáo hội thoại bằng AI vào trải nghiệm người dùng | P21: Snapchat ra mắt hình thức quảng cáo hội thoại chạy bằng AI - AI Sponsored Snaps - kết hợp quy mô gần một tỷ người dùng hàng tháng với các cuộc trò chuyện do AI cung cấp để thúc đẩy sự tương tác, cho phép thương hiệu trò chuyện trực tiếp với người dùng thay vì chỉ hiển thị banner hay video Người dùng có thể hỏi đáp, khám phá sản phẩm và nhận gợi ý cá nhân hóa ngay trong cuộc trò chuyện với chatbot của nhãn hàng. Giải pháp được thiết kế nhằm tăng mức độ tương tác và đo lường hiệu quả quảng cáo sâu hơn, phù hợp với hành vi chat‑first của Gen Z. | Q21: 46140 | T21: 3.5 | U21: 4 | X21: 3.7 | Y21: MXH/ Chat/ Giải trí
A22: 376 | B22: https://techcrunch.com/2026/04/23/whatsapp-adds-prepaid-phone-recharges-in-india-as-its-payments-usage-still-lags/ | C22: WhatsApp mở rộng nạp tiền di động để thúc đẩy mảng thanh toán tại Ấn Độ | D22: TechCrunch | E22: 4 - Strategic shift | F22: 18 | G22: 46145 | H22: WhatsApp adds prepaid phone recharges in India — payments still lags | I22: 46135 | J22: Market Pulse | K22: Quốc tế | L22: Technology | M22: Open banking/ API | N22: Technology | Open banking/ API | O22: WhatsApp mở rộng nạp tiền di động để thúc đẩy mảng thanh toán tại Ấn Độ | P22: WhatsApp hợp tác PayU thêm nạp tiền điện thoại trả trước tại Ấn Độ (Jio, Airtel, Vodafone), triển khai cho toàn bộ 500M+ người dùng. Việc triển khai mới nhất bổ sung vào nỗ lực rộng lớn hơn của WhatsApp nhằm mở rộng thanh toán và dịch vụ trong ứng dụng ở Ấn Độ, nơi người dùng đã có thể thanh toán hóa đơn, đặt vé tàu điện ngầm và truy cập một loạt các dịch vụ của chính phủ thông qua giao diện dựa trên trò chuyện Tính năng mới nhằm tăng mức độ sử dụng WhatsApp Payments. Ứng dụng nhắn tin đã xử lý hơn 130 triệu giao dịch trong tháng 3, theo số liệu thống kê mới nhất từ Tập đoàn Thanh toán Quốc gia Ấn Độ, bỏ xa các đối thủ như PhonePe và Google Pay thuộc sở hữu của Walmart, xử lý lần lượt hơn 10,5 tỷ và 7,5 tỷ giao dịch trong cùng kỳ | Q22: 46135 | T22: 3.5 | U22: 4 | X22: 3.7 | Y22: MXH/ Chat/ Giải trí
A23: 377 | B23: https://www.techinasia.com/news/indian-ecommerce-firms-build-agentic-ai-storefronts | C23: Thương mại điện tử Ấn Độ chuyển sang mô hình storefront dùng AI age | D23: Tech in Asia | E23: 4 - Strategic shift | F23: 18 | G23: 46145 | H23: Indian ecommerce firms build agentic AI storefronts | I23: 46137 | J23: Market Pulse | K23: Quốc tế | L23: Technology | M23: AI/ Gen AI | N23: Technology | AI/ Gen AI | O23: Thương mại điện tử Ấn Độ chuyển sang mô hình storefront dùng AI age | P23: Các công ty TMĐT Ấn Độ đang xây dựng storefront sử dụng AI agent, cho phép khách hàng trò chuyện, hỏi đáp và mua sắm thay vì duyệt danh mục truyền thống. AI agent có thể hiểu nhu cầu, gợi ý sản phẩm, so sánh giá và hoàn tất đơn hàng trong một luồng hội thoại liền mạch. Mô hình này tận dụng hành vi mobile‑first và chatbot‑friendly của người dùng Ấn Độ, đồng thời giúp doanh nghiệp cá nhân hóa trải nghiệm ở quy mô lớn. | T23: 4 | U23: 3 | X23: 3.6 | Y23: TMĐT
A24: 378 | B24: https://techcrunch.com/2026/04/22/threads-is-adding-live-chats-to-boost-real-time-engagement/ | C24: Threads bổ sung live chat để tăng tương tác theo thời gian thực | D24: TechCrunch | E24: 4 - Strategic shift | F24: 18 | G24: 46145 | H24: Threads is adding live chats to boost real-time engagement | I24: 46134 | J24: Market Pulse | K24: Quốc tế | L24: Technology | M24: AI/ Gen AI | N24: Technology | AI/ Gen AI | O24: Threads bổ sung live chat để tăng tương tác theo thời gian thực | P24: Threads triển khai tính năng live chat, cho phép người dùng tham gia trò chuyện trực tiếp, theo dõi diễn biến tức thì theo chủ đề (thể thao, giải trí, sản phẩm) ngay trong ứng dụng với tối đa 150 người cùng lúc Tính năng này nhằm thúc đẩy tương tác real‑time, vốn là điểm yếu của Threads so với X trong các cuộc thảo luận nóng. Live chat được tích hợp gọn nhẹ, tập trung vào tốc độ và tính thời sự, thay vì xây dựng cộng đồng phức tạp. | T24: 4 | U24: 3 | X24: 3.6 | Y24: MXH/ Chat/ Giải trí
